Workbook

Sheet Raw_Data
A1: product_id | B1: product_name | C1: category | D1: discounted_price | E1: actual_price | F1: discount_percentage | G1: rating | H1: rating_count | I1: about_product | J1: user_id | K1: user_name | L1: review_id | M1: review_title | N1: review_content | O1: img_link | P1: product_link
A2: B07JW9H4J1 | B2: Wayona Nylon Braided USB to Lightning Fast Charging and Data Sync Cable Compatible for iPhone 13, 12,11, X, 8, 7, 6, 5, iPad Air, Pro, Mini (3 FT Pack of 1, Grey) | C2: Computers&Accessories|Accessories&Peripherals|Cables&Accessories|Cables|USBCables | D2: â‚¹399 | E2: â‚¹1,099 | F2: 0.64 | G2: 4.2 | H2: 24269 | I2: High Compatibility : Compatible With iPhone 12, 11, X/XsMax/Xr ,iPhone 8/8 Plus,iPhone 7/7 Plus,iPhone 6s/6s Plus,iPhone 6/6 Plus,iPhone 5/5s/5c/se,iPad Pro,iPad Air 1/2,iPad mini 1/2/3,iPod nano7,iPod touch and more apple devices.|Fast Charge&Data Sync : It can charge and sync simultaneously at a rapid speed, Compatible with any charging adaptor, multi-port charging station or power bank.|Durability : Durable nylon braided design with premium aluminum housing and toughened nylon fiber wound tightly around the cord lending it superior durability and adding a bit to its flexibility.|High Security Level : It is designed to fully protect your device from damaging excessive current.Copper core thick+Multilayer shielding, Anti-interference, Protective circuit equipment.|WARRANTY: 12 months warranty and friendly customer services, ensures the long-time enjoyment of your purchase. If you meet any question or problem, please don't hesitate to contact us. | J2: AG3D6O4STAQKAY2UVGEUV46KN35Q,AHMY5CWJMMK5BJRBBSNLYT3ONILA,AHCTC6ULH4XB6YHDY6PCH2R772LQ,AGYHHIERNXKA6P5T7CZLXKVPT7IQ,AG4OGOFWXJZTQ2HKYIOCOY3KXF2Q,AENGU523SXMOS7JPDTW52PNNVWGQ,AEQJHCVTNINBS4FKTBGQRQTGTE5Q,AFC3FFC5PKFF5PMA52S3VCHOZ5FQ | K2: Manav,Adarsh gupta,Sundeep,S.Sayeed Ahmed,jaspreet singh,Khaja moin,Anand,S.ARUMUGAM | L2: R3HXWT0LRP0NMF,R2AJM3LFTLZHFO,R6AQJGUP6P86,R1KD19VHEDV0OR,R3C02RMYQMK6FC,R39GQRVBUZBWGY,R2K9EDOE15QIRJ,R3OI7YT648TL8I | M2: Satisfied,Charging is really fast,Value for money,Product review,Good quality,Good product,Good Product,As of now seems good | N2: Looks durable Charging is fine tooNo complains,Charging is really fast, good product.,Till now satisfied with the quality.,This is a good product . The charging speed is slower than the original iPhone cable,Good quality, would recommend,https://m.media-amazon.com/images/W/WEBP_402378-T1/images/I/81---F1ZgHL._SY88.jpg,Product had worked well till date and was having no issue.Cable is also sturdy enough...Have asked for replacement and company is doing the same...,Value for money | O2: https://m.media-amazon.com/images/W/WEBP_402378-T1/images/I/51UsScvHQNL._SX300_SY300_QL70_FMwebp_.jpg | P2: https://www.amazon.in/Wayona-Braided-WN3LG1-Syncing-Charging/dp/B07JW9H4J1/ref=sr_1_1?qid=1672909124&s=electronics&sr=1-1
A3: B098NS6PVG | B3: Ambrane Unbreakable 60W / 3A Fast Charging 1.5m Braided Type C Cable for Smartphones, Tablets, Laptops & other Type C devices, PD Technology, 480Mbps Data Sync, Quick Charge 3.0 (RCT15A, Black) | C3: Computers&Accessories|Accessories&Peripherals|Cables&Accessories|Cables|USBCables | D3: â‚¹199 | E3: â‚¹349 | F3: 0.43 | G3: 4 | H3: 43994 | I3: Compatible with all Type C enabled devices, be it an android smartphone (Mi, Samsung, Oppo, Vivo, Realme, OnePlus, etc), tablet, laptop (Macbook, Chromebook, etc)|Supports Quick Charging (2.0/3.0)|Unbreakable â€“ Made of special braided outer with rugged interior bindings, it is ultra-durable cable that wonâ€™t be affected by daily rough usage|Ideal Length â€“ It has ideal length of 1.5 meters which is neither too short like your typical 1meter cable or too long like a 2meters cable|Supports maximum 3A fast charging and 480 Mbps data transfer speed|6 months manufacturer warranty from the date of purchase | J3: AECPFYFQVRUWC3KGNLJIOREFP5LQ,AGYYVPDD7YG7FYNBXNGXZJT525AQ,AHONIZU3ICIEHQIGQ6R2VFRSBXOQ,AFPHD2CRPDZMWMBL7WXRSVYWS5JA,AEZ346GX3HJ4O4XNRPHCNHXQURMQ,AEPSWFPNECKO34PUC7I56ITGXR6Q,AHWVEHR5DYLVFTO2KF3IZATFQSWQ,AH4QT33M55677I7ISQOAKEQWACYQ | K3: ArdKn,Nirbhay kumar,Sagar Viswanathan,Asp,Placeholder,BharanI,sonia,Niam | L3: RGIQEG07R9HS2,R1SMWZQ86XIN8U,R2J3Y1WL29GWDE,RYGGS0M09S3KY,R17KQRUTAN5DKS,R3AAQGS6HP2QUK,R1HDNOG6TO2CCA,R3PHKXYA5AFEOU | M3: A Good Braided Cable for Your Type C Device,Good quality product from ambrane,Super cable,As,Good quality,Good product,its good,Good quality for the price but one issue with my unit | N3: I ordered this cable to connect my phone to Android Auto of car. The cable is really strong and the connection ports are really well made. I already has a Micro USB cable from Ambrane and it's still in good shape. I connected my phone to the car using the cable and it got connected well and no issues. I also connected it to the charging port and yes it has Fast Charging support.,It quality is good at this price and the main thing is that i didn't ever thought that this cable will be so long it's good one and charging power is too good and also supports fast charging,Value for money, with extra lengthðŸ‘,Good, working fine,Product quality is good,Good,very good,Bought for my daughter's old phone.Brand new cable it was not charging, I already repacked and requested for replacement.I checked again, and there was some green colour paste/fungus inside the micro USB connector. I cleaned with an alcoholic and starts working again.Checked the ampere of charging speed got around 1400ma-1500ma - not bad, came with braided 1.5m long cable, pretty impressive for the price.Can't blame the manufacturer.But quality issues by the distributor, they might have stored in very humid place. | O3: https://m.media-amazon.com/images/W/WEBP_402378-T2/images/I/31zOsqQOAOL._SY445_SX342_QL70_FMwebp_.jpg | P3: https://www.amazon.in/Ambrane-Unbreakable-Charging-Braided-Cable/dp/B098NS6PVG/ref=sr_1_2?qid=1672909124&s=electronics&sr=1-2
A4: B096MSW6CT | B4: Sounce Fast Phone Charging Cable & Data Sync USB Cable Compatible for iPhone 13, 12,11, X, 8, 7, 6, 5, iPad Air, Pro, Mini & iOS Devices | C4: Computers&Accessories|Accessories&Peripherals|Cables&Accessories|Cables|USBCables | D4: â‚¹199 | E4: â‚¹1,899 | F4: 0.9 | G4: 3.9 | H4: 7928 | I4: ã€ Fast Charger& Data Syncã€‘-With built-in safety proctections and four-core copper wires promote maximum signal quality and strength and enhance charging & data transfer speed with up to 480 mb/s transferring speed.|ã€ Compatibilityã€‘-Compatible with iPhone 13, 12,11, X, 8, 7, 6, 5, iPad Air, Pro, Mini & iOS devices.|ã€ Sturdy & Durableã€‘-The jacket and enforced connector made of TPE and premium copper, are resistant to repeatedly bending and coiling.|ã€ Ultra High Qualityã€‘: According to the experimental results, the fishbone design can accept at least 20,000 bending and insertion tests for extra protection and durability. Upgraded 3D aluminum connector and exclusive laser welding technology, which to ensure the metal part won't break and also have a tighter connection which fits well even with a protective case on and will never loose connection.|ã€ Good After Sales Serviceã€‘-Our friendly and reliable customer service will respond to you within 24 hours ! you can purchase with confidence,and every sale includes a 365-day worry-free Service to prove the importance we set on quality. | J4: AGU3BBQ2V2DDAMOAKGFAWDDQ6QHA,AESFLDV2PT363T2AQLWQOWZ4N3OA,AHTPQRIMGUD4BYR5YIHBH3CCGEFQ,AEUVWXYP5LT7PZLLZENEO2NODPBQ,AHC7MPW55DOO6WNCOQVA2VHOD26A,AFDI6FRPFBTNBG7BAEB7JDJSMKDQ,AFQKCEEEKXCOHTDG4WUN3XPPHJQQ,AHKUUFNMBZIDLSSPA4FEHIO2EC7Q | K4: Kunal,Himanshu,viswanath,sai niharka,saqib malik,Aashiq,Ramu Challa,Sanjay gupta | L4: R3J3EQQ9TZI5ZJ,R3E7WBGK7ID0KV,RWU79XKQ6I1QF,R25X4TBMPY91LX,R27OK7G99VK0TR,R207CYDCHJJTCJ,R3PCU8XMU173BT,R1IMONDOWRNU5V | M4: Good speed for earlier versions,Good Product,Working good,Good for the price,Good,Worth for money,Working nice,it's a really nice product | N4: Not quite durable and sturdy,https://m.media-amazon.com/images/W/WEBP_402378-T1/images/I/71rIggrbUCL._SY88.jpg,Working good,https://m.media-amazon.com/images/W/WEBP_402378-T1/images/I/61bKp9YO6wL._SY88.jpg,Product,Very nice product,Working well,It's a really nice product | O4: https://m.media-amazon.com/images/W/WEBP_402378-T1/images/I/31IvNJZnmdL._SY445_SX342_QL70_FMwebp_.jpg | P4: https://www.amazon.in/Sounce-iPhone-Charging-Compatible-Devices/dp/B096MSW6CT/ref=sr_1_3?qid=1672909124&s=electronics&sr=1-3
A5: B08HDJ86NZ | B5: boAt Deuce USB 300 2 in 1 Type-C & Micro USB Stress Resistant, Tangle-Free, Sturdy Cable with 3A Fast Charging & 480mbps Data Transmission, 10000+ Bends Lifespan and Extended 1.5m Length(Martian Red) | C5: Computers&Accessories|Accessories&Peripherals|Cables&Accessories|Cables|USBCables | D5: â‚¹329 | E5: â‚¹699 | F5: 0.53 | G5: 4.2 | H5: 94363 | I5: The boAt Deuce USB 300 2 in 1 cable is compatible with smartphones, tablets, PC peripherals, Bluetooth speakers, power banks and all other devices with Type-C as well as Micro USB port|It ensures 3A fast charging and data transmissions with rapid sync at 480 mbps|The premium Nylon braided skin makes it sturdy and invincible against external damage|Its Aluminium alloy shell housing makes it last longer with 10000+ Bends Lifespan with extended frame protection for strain relief|The resilient and flexible design offers a tangle free experience seamlessly|Deuce USB 300 cable offers a perfect 1.5 meters in length for smooth & hassle-free user experience|2 years warranty from the date of purchase | J5: AEWAZDZZJLQUYVOVGBEUKSLXHQ5A,AG5HTSFRRE6NL3M5SGCUQBP7YSCA,AH725ST5NW2Y4JZPKUNTIJCUK2BA,AHV3TXIFCJPMS4D5JATCEUR266MQ,AGWIGDEMFIIUAOXYY2QATNBSUGHA,AFSTSLQUV4EVEXWKBOLEFHL2H5YQ,AGAKDNBHY2FKX7I4ACRGILU7QL7A,AFNWJUWJRHCC6HN52KMG5AKZY37Q | K5: Omkar dhale,JD,HEMALATHA,Ajwadh a.,amar singh chouhan,Ravi Siddan,Himanshu Goel,Udaykumar | L5: R3EEUZKKK9J36I,R3HJVYCLYOY554,REDECAZ7AMPQC,R1CLH2ULIVG5U3,R2DMKIBGFKBD6R,RC89B5IAJUTR5,R3B3DDON5FH8DS,R13WAEJDI5RS36 | M5: Good product,Good one,Nice,Really nice product,Very first time change,Good,Fine product but could be better,Very nice it's charging like jet | N5: Good product,long wire,Charges good,Nice,I bought this cable for Rs.339 worthy product for this price, i tested it in various charger adapters 33w and 18w it supports fast charging as well.,Good,Ok,I had got this at good price on sale on Amazon and product is useful with warranty but for warranty you need to go very far not practical for such a cost and mine micro to type c connector stopped working after few days only.,I like this product | O5: https://m.media-amazon.com/images/I/41V5FtEWPkL._SX300_SY300_QL70_FMwebp_.jpg | P5: https://www.amazon.in/Deuce-300-Resistant-Tangle-Free-Transmission/dp/B08HDJ86NZ/ref=sr_1_4?qid=1672909124&s=electronics&sr=1-4
A6: B08CF3B7N1 | B6: Portronics Konnect L 1.2M Fast Charging 3A 8 Pin USB Cable with Charge & Sync Function for iPhone, iPad (Grey) | C6: Computers&Accessories|Accessories&Peripherals|Cables&Accessories|Cables|USBCables | D6: â‚¹154 | E6: â‚¹399 | F6: 0.61 | G6: 4.2 | H6: 16905 | I6: [CHARGE & SYNC FUNCTION]- This cable comes with charging & Data sync function|[HIGH QUALITY MATERIAL]- TPE + Nylon Material to make sure that the life of the cable is enhanced significantly|[LONG CORD]- The Cable is extra thick 1.2 meter long, optimized for an easy use for your comfort at home or office|[MORE DURABLE]-This cable is unique interms of design and multi-use and is positioned to provide the best comfort and performance while using|[UNIVERSAL COMPATIBILITY]- Compatible with all devices like iPhone XS, X, XR, 8, 7, 6S, 6, 5S, iPad Pro, iPad mini and iPad Air | J6: AE3Q6KSUK5P75D5HFYHCRAOLODSA,AFUGIFH5ZAFXRDSZHM4QB2KPKFUQ,AFK4NJOLFSJGWLOJIUIAROJF6YVA,AFUOTYRFUXVPEBGIXVZZ7DR3CZUA,AFDLRSXKDZ6U3U3KD46SQLFGZQRA,AH5VLM66SIK7J3IRG4NY7XVOQ55A,AE3MQNNHHLUHXURL5S7IAR7JTGNQ,AFSEOFZY67MYC7UAJU264Z5NFTLA | K6: rahuls6099,Swasat Borah,Ajay Wadke,Pranali,RVK,Bhargav,Durai Vignesh,Amazon Customer | L6: R1BP4L2HH9TFUP,R16PVJEXKV6QZS,R2UPDB81N66T4P,R3KK4GT934ST3I,RCFHMWUSBIJO,RDO7DACXMAJ84,R3A6MEZL3LY66Z,R1ESIEKPGAYA29 | M6: As good as original,Decent,Good one for secondary use,Best quality,GOOD,Amazing product at a mind blowing price!,Nice Quality,Good product | N6: Bought this instead of original apple, does the work for 150rs, not as fast as apple charger but its a good option if you want cheap and good product, bought it for iPad pro 10.5 and it's working flawlessly, build quality is ok, its not like i am gonna hang my clothes on it and i want a very strong cable, even a braided cable stop working after a year, i have used both Anker and Apple store strong braided cable they all stop working after a year so please don't buy high end cables just for that instead choose a this one and even if it's stops working withing a year you only loose 150rs compares to 2000rs.UPDATE------------------------------------pin has stopped charging from one side, now i have to slip the pin to charge from other side, but i will update and let know for how long does it work,,Itâ€™s good. Not sure about durability as the pin area feels a bit fragile,Does not support apple carplaySo was little disappointed about thatOther than that cable is made up of very good quality,Best to buy,100% NOT FATHFUL,Writing this review post 10 months and 3 orders of the same product.Honestly Portronics Konnect L lightning cable works like magic with the original Apple charging brick.Seeing the price of the cable I initially hesitated buying as it was as low as â‚¹99/- with the offers and so I wasnâ€™t sure if it would work well with my iPhone 12 or whether it would impact my iPhoneâ€™s battery health because all the other lightning cable brands were costing over â‚¹350/- like Wayona, Amazon Basics, etc.Earlier I was using Wayona Brand lightning cable with eventually frayed and stopped working.Charging Speed:Charges my iPhone fast enough almost similar compared to the original cable level when used with 12W Original Apple power adapter.Quality and Durability:Great quality braided cable and doesnâ€™t tangle easily and can withstand day-to-day usage.L-Shaped pin:This is very innovative by Portronics and it makes sure the cable doesnâ€™t get damaged even if used while charging.CarPlay and Data Sync:Works smoothly with CarPlay and syncs data effortlessly.PS: I have used this cable only with the Original Apple Charging Brick and extremely satisfied with its performance.,Better than I expect the product I like that Quality and I plan to buy same type cable come with usb C to Lighting cable for emergency purpose that much I love this cable. Buy for this cable only emergency uses only since Good one,Good product and value for money | O6: https://m.media-amazon.com/images/W/WEBP_402378-T2/images/I/31VzNhhqifL._SX300_SY300_QL70_FMwebp_.jpg | P6: https://www.amazon.in/Portronics-Konnect-POR-1080-Charging-Function/dp/B08CF3B7N1/ref=sr_1_5?qid=1672909124&s=electronics&sr=1-5
A7: B08Y1TFSP6 | B7: pTron Solero TB301 3A Type-C Data and Fast Charging Cable, Made in India, 480Mbps Data Sync, Strong and Durable 1.5-Meter Nylon Braided USB Cable for Type-C Devices for Charging Adapter (Black) | C7: Computers&Accessories|Accessories&Peripherals|Cables&Accessories|Cables|USBCables | D7: â‚¹149 | E7: â‚¹1,000 | F7: 0.85 | G7: 3.9 | H7: 24871 | I7: Fast Charging & Data Sync: Solero TB301 Type-C cable supports fast charge up to 5V/3A for devices and data syncing speed up to 480Mbps.|Universal Compatibility: This USB charging cable connects USB Type-C devices with standard USB devices like laptops, hard drives, power banks, wall and car chargers, etc..Connector One: Reversible Type C|Connector Two: USB A Type|Rough & Tough Type-C Cable: Charging cable with a double-braided exterior, premium aramid fiber core and metal plugs. It has passed 10,000 bending tests and can easily withstand daily use.|Extended Length: 1.5-meter long c-type cable uses nylon material to protect the wire and avoid knots.|Perfect Fit Connectors: pTron Soler USB-C has passed the 5KG load test, swing test, 5000+ times connect & disconnect to ensure that there are no loose connections. | J7: AEQ2YMXSZWEOHK2EHTNLOS56YTZQ,AGRVINWECNY7323CWFXZYYIZOFTQ,AHBAT6VLOXWGYDL57KHCNCLPXAKA,AF7NDY2H6JVYTSQOZP76GCATQ34Q,AFV7ZA733ZLME4KNLZPMPCBUNPPA,AHFAAPSY2MJ5HYOU2VQDJ7AQY4NQ,AH2WGV2PEBUTICRPBEEVKF24G5LA,AEP4MK3EKOBDKTGPJTRN5RBDIODA | K7: Jayesh,Rajesh k.,Soopy,amazon customer,Aman,Shankar,dinesh,Chitra,Ajaybabu.O.M | L7: R7S8ANNSDPR40,R3CLZFLHVJU26P,RFF7U7MPQFUGR,R1MV1NKC23DWPI,R11D3U0V2XKDKF,R18MP1KLUE18PC,RWGJNVEH5ZQME,R1XN72FU6Q37IH | M7: It's pretty good,Average quality,very good and useful usb cable,Good USB cable. My experience was very good it is long lasting,Good,Nice product and useful,-,Sturdy but does not support 33w charging | N7: It's a good product.,Like,Very good item strong and useful USB cableValue for moneyThanks to amazon and producer,https://m.media-amazon.com/images/I/51112ZRE-1L._SY88.jpg,Good,Nice product and useful product,-,Sturdy but does not support 33w charging | O7: https://m.media-amazon.com/images/I/31wOPjcSxlL._SX300_SY300_QL70_FMwebp_.jpg | P7: https://www.amazon.in/Solero-TB301-Charging-480Mbps-1-5-Meter/dp/B08Y1TFSP6/ref=sr_1_6?qid=1672909124&s=electronics&sr=1-6
A8: B08WRWPM22 | B8: boAt Micro USB 55 Tangle-free, Sturdy Micro USB Cable with 3A Fast Charging & 480mbps Data Transmission (Black) | C8: Computers&Accessories|Accessories&Peripherals|Cables&Accessories|Cables|USBCables | D8: â‚¹176.63 | E8: â‚¹499 | F8: 0.65 | G8: 4.1 | H8: 15188 | I8: It Ensures High Speed Transmission And Charging By Offering 3A Fast Charging And Data Transmissions With Rapid Sync At 480 Mbps|The Braided Skin Makes It Durable And Invincible Against External Damage So You Can Have An Absolute Hassle-Free & Tangle Free Experience|Its Durable Pvc Housing And The Flexible Design Makes It Last 6 Times Longer Than Other Cables|Usb Cable Offers A Perfect 1.5 Meters In Length For Smooth & Hassle-Free User Experience For Superior Charging & Data Transfer Tasks|The Compact And Smooth Aluminium Connector Fits Most Cases Seamlessly And Resists Corrosion For Signal Purity|Micro Usb 55 Cable Offers Universal Compatibility As It Is Compatible With Most Android Smartphones, Tablets, Pc Peripherals, Bluetooth Speakers, Power Banks, Game Consoles & All Micro-Usb Enabled Devices|2 years warranty from the date of purchase | J8: AG7C6DAADCTRQJG2BRS3RIKDT52Q,AFU7BOMPVJ7Q3TTA4G67RASTGYIQ,AER5ZGIXXVYG3AWZTRZT7M2BYCEA,AHE76XQSOLGOP5ZEKTIW6KUPDWBQ,AGXTMB2XHZBEWZ2UIX7ODZ4XTU6Q,AHNM2XVU745EDPNGUOAG74PTSNRA,AH5RWQ4S72IVLZD6O75OPCFIVDXQ,AG322TYKVPLPBDXE7ABEUK5QTALQ | K8: Vivek kumar,Amazon Customer,SARTHAK,Chiranjeevi,V V GIRI KUMAR,Rajnandini,Akshay Talla,sudhanshu chaubey | L8: R8E73K2KWJRDS,RSD0JTIIWQQL8,R64CRSTE9SLW1,R2FRTNIIUFJE1F,RWGNX3W7UOJ7W,R32TYHHODHTF5D,RQL9ZMQUTY7P2,R280XJ5VZUBOXV | M8: Long durable.,good,Does not charge Lenovo m8 tab,Best charging cable,good,Boat,Product was good,1.5 m à¤•à¤¾ à¤•à¥‡à¤¬à¤² à¤®à¥‡à¤°à¥‡ à¤²à¤¿à¤ à¤¬à¤¹à¥à¤¤ à¤¹à¥€ à¤²à¤¾à¤­à¤¦à¤¾à¤¯à¤• à¤¹à¥ˆ à¥¤ | N8: Build quality is good and it is comes with 2 year warranty.,Good Product,Bought it for charging my mobile & tab but it doesn't work for Lenovo m8 tab,Guys this cable is is best compare of everyone over heat protection, quickly charging, but chance to shock circuit,good,Nice,Good quality,1.5à¤à¤® à¤•à¤¾ à¤¡à¤¾à¤Ÿà¤¾ à¤•à¥‡à¤¬à¤² à¤®à¥‡à¤°à¥‡ à¤²à¤¿à¤ à¤¬à¤¹à¥à¤¤ à¤¹à¥€ à¤²à¤¾à¤­à¤¦à¤¾à¤¯à¤• à¤¹à¥ˆ à¥¤ à¤®à¥ˆà¤‚ à¤‡à¤¸ à¤•à¥‡à¤¬à¤² à¤•à¥‹ à¤²à¤¾à¤‡à¤¨ à¤®à¥‡à¤‚ à¤šà¤¾à¤°à¥à¤œ à¤•à¤°à¤¤à¥‡ à¤¸à¤®à¤¯ à¤«à¥‹à¤¨ à¤¬à¤¹à¥à¤¤ à¤†à¤°à¤¾à¤® à¤¸à¥‡ à¤‰à¤ªà¤¯à¥‹à¤— à¤•à¤° à¤ªà¤¾ à¤°à¤¹à¤¾ à¤¹à¥ à¥¤ à¤†à¤ª à¤‡à¤¸ à¤•à¥‡à¤¬à¤² à¤¸à¥‡ 15watt à¤•à¤¾ à¤šà¤¾à¤°à¥à¤œà¤° à¤‰à¤¸à¥‡ à¤•à¤° à¤¸à¤•à¤¤à¥‡ à¤¹à¥ˆ (à¤‡à¤¸à¤¸à¥‡ à¤œà¤¡à¤¼à¤¾ à¤¨à¤¹à¥€) à¥¤ à¤²à¥‹à¤•à¤² à¤¬à¤¾à¤œà¤¾à¤° à¤®à¥‡à¤‚ à¤‡à¤¸à¤•à¤¾ à¤¦à¤¾à¤® 150 à¤¹à¥ˆ , à¤…à¤®à¥‡à¤œà¤¨ à¤ªà¥‡ à¤¯à¥‡ à¤•à¥‡à¤¬à¤² à¤®à¥à¤à¥‡ 67 à¤®à¥‡à¤‚ à¤®à¤¿à¤²à¤¾ à¥¤ à¤—à¤°à¥à¤µ à¤¸à¥‡ à¤•à¤¹à¥‹ à¤¹à¤® à¤¹à¤¿à¤‚à¤¦à¥‚ à¤¹à¥ˆ , à¤œà¤¯ à¤¹à¤¿à¤‚à¤¦ à¤œà¤¯ à¤­à¤¾à¤°à¤¤ , | O8: https://m.media-amazon.com/images/W/WEBP_402378-T2/images/I/41jlwEZpa5L._SX300_SY300_QL70_FMwebp_.jpg | P8: https://www.amazon.in/boAt-Micro-USB-Tangle-Free-Transmission/dp/B08WRWPM22/ref=sr_1_8?qid=1672909124&s=electronics&sr=1-8
A9: B08DDRGWTJ | B9: MI Usb Type-C Cable Smartphone (Black) | C9: Computers&Accessories|Accessories&Peripherals|Cables&Accessories|Cables|USBCables | D9: â‚¹229 | E9: â‚¹299 | F9: 0.23 | G9: 4.3 | H9: 30411 | I9: 1m long Type-C USB Cable|Sturdy and Durable. With USB cable you can transfer data with speeds of upto 480 Mbps|Upto 3A output|6months warranty|Sturdy and Durable. With USB cable you can transfer data with speeds of upto 480 Mbps|6months warranty|Up To 3A Output | J9: AHW6E5LQ2BDYOIVLAJGDH45J5V5Q,AF74RSGCHPZITVFSZN76K6GKPICA,AHDD7ZNB47QA2JLYU53HD4ML3VNQ,AHV3ELGDSOWBYUQLXSPDCSHBQRHQ,AEJU4L3ZM2GTILSJZZSNSF6VUOIA,AFVD66VQMSHPDT3A6HBBBGKRXBZA,AELKHQXVSSG6NHXLFJLLNEFRQQUQ,AGYSMAC6V6RFJJOHG2FIRPOZ6CSQ | K9: Pavan A H,Jayesh bagad,Shridhar,rajendran,karuppu k,Akshay wani,Abbimaniu Singh,VISHAL H BADSHE | L9: R2X090D1YHACKR,R32ZCIH9AFNJ60,R3N57EVVG0EHAF,R3QWLE8JHROKC1,R2VTSDOOUTSQ5X,R3E6FZ75Q074KH,R1SYBQLTPFCW20,RYQT96J8HPIXE | M9: Worth for money - suitable for Android auto,Good Product,Length,Nice,Original,Very good quay Cable support fast charging.,Original MI cable for charging upto 33 watt,I am veri happy with this product as it provide turbo charging. | N9: Worth for money - suitable for Android auto... my purpose served in car....got it for Rs.150,Everything is Okay. But packaging is not good feeling like seller gave is used cable.,Good product,Good product but cost is more.,Original cable,I bought this cable at 129. Using this cable for Android auto in my car. Perfectly works without any glitch.,Original MI cable. Will charge upto 33 watts. Got it for Rs 150. I have 67 watt charger and I want a cable for my car so I went for it. I checked the performance with battery charging app. The charging speed is exactly half of my 67 watt original cable. Go for it.,It provided me turbo charging. I recommend for all Redmi note 10s mobile phones. As it provide turbo charging. I am veri happy with this product. | O9: https://m.media-amazon.com/images/I/31XO-wfGGGL._SX300_SY300_QL70_FMwebp_.jpg | P9: https://www.amazon.in/MI-MTCY001IN-USB-Type-C-Cable/dp/B08DDRGWTJ/ref=sr_1_9?qid=1672909124&s=electronics&sr=1-9
A10: B008IFXQFU | B10: TP-Link USB WiFi Adapter for PC(TL-WN725N), N150 Wireless Network Adapter for Desktop - Nano Size WiFi Dongle Compatible with Windows 11/10/7/8/8.1/XP/ Mac OS 10.9-10.15 Linux Kernel 2.6.18-4.4.3 | C10: Computers&Accessories|NetworkingDevices|NetworkAdapters|WirelessUSBAdapters | D10: â‚¹499 | E10: â‚¹999 | F10: 0.5 | G10: 4.2 | H10: 179691 | I10: USB WiFi Adapter â€”â€” Speedy wireless transmission at up to 150Mbps ideal for video streaming or internet calls|Mini Design â€”â€” Sleek miniature design so small that once plugged in, can be left in a Laptopâ€™s USB port|Advanced Security â€”â€” Supports 64/128 WEP, WPA, PA2/WPA-PSK/WPA2-PSK(TKIP/AES)|Compatibility â€”â€” Windows 11/10/8.1/8/7/XP, Mac OS 10.15 and earlier, Linux|Easy Setup â€”â€” Connect in no time with easy setup utility in 14 languages|In an unlikely case of product quality related issue, we may ask you to reach out to brandâ€™s customer service support and seek resolution. We will require brand proof of issue to process replacement request | J10: AGV3IEFANZCKECFGUM42MRH5FNOA,AEBO7NWCNXKT4AESAN443HQH35FQ,AE7GD3VRRYQEAHDR7FXJIR23INYA,AHPAW24BI5X2GCX5M2LHI72VSJJQ,AE2VXY4CFO36MDSIMPG43XHNF4GA,AHHQEKUNVETALN7DTRHUQ2WAWEKQ,AFMIFTNTUD5PIHGONWOTRMMZ5EBA,AHOJBIZVVIIFJKRREY4B6ESVA4KA | K10: Azhar JuMan,Anirudh Sood,Hari Krishnan PS,Akash Jindal,PRADEEP,Rajesh,Divya Kothari,abhijit | L10: R1LW6NWSVTVZ2H,R3VR5WFKUS15C5,R2F6GC79OYWUKQ,R3QZ19MECGWG9A,R2MPU42MYK7GPO,R33DVXFB4VYPZZ,R1SQ7OGFR4JRUR,R1S5F9QI0M1VBZ | M10: Works on linux for me. Get the model with antenna.,Does what it say but other brands available at lesser price,Easy Handle,Great product,Perfect working,Speed is perfect,Great Design, Build, Connectivity Range, Packaging and other features but no linux support since v2,Very good | N10: I use this to connect an old PC to internet. I tried lubuntu 20 and ubuntu 22, it worked out of the box in both, didn't have to do any setup. There's an extender cable so you can place this in a comfortable place. Get the model with antenna because otherwise you'll have range problems if you're not directly in line of sight from your wifi router.,The wifi dongle is a simple plug & play device, will start catching available networks right after you plug it into your USB port, no additional installations/ softwares requires. Signal strength is good.... just wonder what would be different in other adapters of lesser known brands which are available at a much more competitive pricing, hence a star less.,Pros:*Easy to use & Portable*Can be connected to Mobile Hotspot and used in PC( Budget Friendly)*Less installation process*No heating issues & Good Coverage*Best alternative for USB Tethering (phone's battery may get damaged for long term run with Tethering)Cons:*Internet connection speed varies at times, also depends on your modem or cellular connection*Issues occur while installing via CD, which is available along with the product( Installation driver can be downloaded from TP-Link site)*Needed to reconnect the adapter every time system is turned ON*Will not work if your software has some issues, so encountered any just update your system(worked for me)*Support Center is worse, calls are unattended most of the times or just visit nearby storeConclusion:Brought this @499/-Ideal for users who don't need very high speed internet usage,a good alternative for USB Tethering and are on Budge(1080p Youtube videos can be easily played with this without any interruptions),wifi connectivity is a great good result for me. however, some jitter problems did exist.,This is perfect device to connect wifi. Go for it.,This wifi adopter is good working,(Pictures attached)Size/Design: â˜… â˜… â˜… â˜… â˜…Build Quality: â˜… â˜… â˜… â˜… â˜…Packaging: â˜… â˜… â˜… â˜… â˜…Software: â˜… â˜… â˜… â˜…Speed: â˜… â˜… â˜… â˜… â˜…Connectivity: â˜… â˜… â˜… â˜… â˜…Experience: â˜… â˜… â˜… â˜… â˜…Warranty: â˜… â˜… â˜… â˜… â˜…Size and Design:The best part about this is that it is very compact in size and very sober and elegant in design. This is a big plus as it is easy plug in and use, add to it the good sober design.Build Quality:The build quality is undoubtedly superb. Just no qualms about that, at all. When held, it doesnt give off that cheap and flimsy product-like feeling. It is good sturdy with its build quality.Packaging:This part is also a big plus as the item was well cushioned and packaged with all the necessary items that ensured that no damage could have been caused to the product during transportation. This ensures that I as a customer have received something not damaged internally already.Software:This is actually good but not great part with the product.The good part is that a CD has been provided with it along with a manual.The not great part is that NO LINUX SUPPORT has been given from Version 2 onwards. This is bad, really.Speed:It easily supports net speeds upto 300 Mbps. Practically speaking, I have tested it at my home and it easily supports net speed of over 100-150 Mbps without a sigh.On testing I found that it did connect to 5GHz network, without any issue.Connectivity:Please mark its not feet its metres. Multiply metres x 3 to get the distance in feet.It easily connects to my laptop or phone from 7 metres across one room. So thats 21 feet. I mean even our old bluetooth used to connect to about 15 ft.So 20-25 feet is not at all an issue with this. This is the big plus I found with the product.Experience:From this point of view, so far except the linux non-compatibility issue, I found no other flaws with this product.So overall its a great product.Warranty:Its 3 years so I am assured that atleast for 3 years I am tension-free and not just 1 year, contrary to most electronic items today that only provide 1 year warranty with their items.,Best adapter I have bought ever. Works nicely seemless connectivity | O10: https://m.media-amazon.com/images/W/WEBP_402378-T2/images/I/31e6ElWRymL._SX300_SY300_QL70_FMwebp_.jpg | P10: https://www.amazon.in/TP-Link-TL-WN725N-150Mbps-Wireless-Adapter/dp/B008IFXQFU/ref=sr_1_10?qid=1672909124&s=electronics&sr=1-10
A11: B082LZGK39 | B11: Ambrane Unbreakable 60W / 3A Fast Charging 1.5m Braided Micro USB Cable for Smartphones, Tablets, Laptops & Other Micro USB Devices, 480Mbps Data Sync, Quick Charge 3.0 (RCM15, Black) | C11: Computers&Accessories|Accessories&Peripherals|Cables&Accessories|Cables|USBCables | D11: â‚¹199 | E11: â‚¹299 | F11: 0.33 | G11: 4 | H11: 43994 | I11: Universal Compatibility â€“ It is compatible with all Micro USB enabled devices, be it an android smartphone, tablet, PC peripheral or any other micro USB compatible device|Unbreakable â€“ Made of special braided outer with rugged interior bindings, it is ultra-durable cable that wonâ€™t be affected by daily rough usage|Ideal Length â€“ It has ideal length of 1.5 meters which is neither too short like your typical 1meter cable or too long like a 2meters cable|Supports maximum 3A fast charging and 480 Mbps data transfer speed|6 Months manufacturer warranty from the date of purchase. | J11: AECPFYFQVRUWC3KGNLJIOREFP5LQ,AGYYVPDD7YG7FYNBXNGXZJT525AQ,AHONIZU3ICIEHQIGQ6R2VFRSBXOQ,AFPHD2CRPDZMWMBL7WXRSVYWS5JA,AEZ346GX3HJ4O4XNRPHCNHXQURMQ,AEPSWFPNECKO34PUC7I56ITGXR6Q,AHWVEHR5DYLVFTO2KF3IZATFQSWQ,AH4QT33M55677I7ISQOAKEQWACYQ | K11: ArdKn,Nirbhay kumar,Sagar Viswanathan,Asp,Placeholder,BharanI,sonia,Niam | L11: RGIQEG07R9HS2,R1SMWZQ86XIN8U,R2J3Y1WL29GWDE,RYGGS0M09S3KY,R17KQRUTAN5DKS,R3AAQGS6HP2QUK,R1HDNOG6TO2CCA,R3PHKXYA5AFEOU | M11: A Good Braided Cable for Your Type C Device,Good quality product from ambrane,Super cable,As,Good quality,Good product,its good,Good quality for the price but one issue with my unit | N11: I ordered this cable to connect my phone to Android Auto of car. The cable is really strong and the connection ports are really well made. I already has a Micro USB cable from Ambrane and it's still in good shape. I connected my phone to the car using the cable and it got connected well and no issues. I also connected it to the charging port and yes it has Fast Charging support.,It quality is good at this price and the main thing is that i didn't ever thought that this cable will be so long it's good one and charging power is too good and also supports fast charging,Value for money, with extra lengthðŸ‘,Good, working fine,Product quality is good,Good,very good,Bought for my daughter's old phone.Brand new cable it was not charging, I already repacked and requested for replacement.I checked again, and there was some green colour paste/fungus inside the micro USB connector. I cleaned with an alcoholic and starts working again.Checked the ampere of charging speed got around 1400ma-1500ma - not bad, came with braided 1.5m long cable, pretty impressive for the price.Can't blame the manufacturer.But quality issues by the distributor, they might have stored in very humid place. | O11: https://m.media-amazon.com/images/W/WEBP_402378-T2/images/I/31kj3q4SepL._SY445_SX342_QL70_FMwebp_.jpg | P11: https://www.amazon.in/Ambrane-Unbreakable-Charging-Braided-Android/dp/B082LZGK39/ref=sr_1_11?qid=1672909124&s=electronics&sr=1-11
A12: B08CF3D7QR | B12: Portronics Konnect L POR-1081 Fast Charging 3A Type-C Cable 1.2Meter with Charge & Sync Function for All Type-C Devices (Grey) | C12: Computers&Accessories|Accessories&Peripherals|Cables&Accessories|Cables|USBCables | D12: â‚¹154 | E12: â‚¹339 | F12: 0.55 | G12: 4.3 | H12: 13391 | I12: [CHARGE & SYNC FUNCTION]- This cable comes with charging & Data sync function for smartphones|[HIGH QUALITY MATERIAL]- TPE + Nylon Material to make sure that the life of the cable is enhanced significantly|[LONG CORD]- The Cable is extra thick 1.2 meter long, optimized for an easy use for your comfort at home or office|[MORE DURABLE]-This cable is unique interms of design and multi-use and is positioned to provide the best comfort and performance while using | J12: AGYLPKPZHVYKKZHOTHCTYVEDAJ4A,AGTTU64JMX722LYCN3SOWLFPKPAQ,AFWD4ZTM7473CDWARHCDQKK73MTA,AEXCQM3FDLX3YL3UJWWUIAIUJT4A,AHUKYUWRUVRTB3IQGISXWTSPAWLQ,AFWW4UEXAJH7EAB5LTMKMSGLUN2Q,AFM5JL37WY7G6MLQUI4WAXUJME7Q,AFECO24WYFOU2KL7C3DMHTEHRU7Q | K12: Tanya,Anu,Akshay,Vishal Sagara Shetty,Swatilekha Sarkar,Jithindas,IBRAHIM S,Sundaram J. | L12: R11MQS7WD9C3I0,R2AKH69XQY8BY4,R8GBOLYUN5UP6,R1AYVO4R25KJTA,R1HT6XM787V7FV,R339XJL1GMKHA3,R175VFSB2A32HG,R35T9LXYBSP09G | M12: Good for fast charge but not for data transfer,Good cable compares to local the brand.,good but doesnt last,Good product,Good Product,Good and worth it,very good material quality charging speed is 15 watt,Not a fast charger | N12: The cable is efficient in fast charging but in quick data transfer. Overall fine.,I like the usb c L shape. Nylon Shielded core wire it improves the life of the cable.,i think i buy these every 6 months or so. fast charging stops working after a while. probbly something to do with the cable design. the cable gets twisted over time and I suspect that breaks the high capacity wires inside. but i keep buying it because there arent too many options in an L shaped design,Good and durable product. Sometime the charges doesn't work on few adapters. there might be few cut off or something but works fine on apple adapter, Car charger, USB,The product is really good at affordable price.,Good and fast charging, and value for money,à®ªà¯Šà®°à¯à®³à¯ à®‰à®Ÿà¯ˆà®¯ à®•à®Ÿà®¿à®©à®¤à¯à®¤à®©à¯à®®à¯ˆà®¯à®¿à®©à¯ à®¨à®©à¯à®±à®¾à®• à®‰à®³à¯à®³à®¤à¯ à®šà®¾à®°à¯à®œà¯ à®à®±à¯à®®à¯ à®µà¯‡à®•à®®à¯ 15wat,Not a fast charger. Very slow charging with 65w. L-shape pin is very useful. | O12: https://m.media-amazon.com/images/I/31dJ+lXJq3L._SY300_SX300_.jpg | P12: https://www.amazon.in/Portronics-POR-1081-Charging-1-2Meter-Function/dp/B08CF3D7QR/ref=sr_1_12?qid=1672909124&s=electronics&sr=1-12
A13: B0789LZTCJ | B13: boAt Rugged v3 Extra Tough Unbreakable Braided Micro USB Cable 1.5 Meter (Black) | C13: Computers&Accessories|Accessories&Peripherals|Cables&Accessories|Cables|USBCables | D13: â‚¹299 | E13: â‚¹799 | F13: 0.63 | G13: 4.2 | H13: 94363 | I13: The boAt rugged cable features our special toughest polyethylene braided jacket and this unique jacket provides greater protection than anything else you have seen in its class. Round Cable|Extra tough polyethylene terephthalate cable skin ensures 10000 plus bend lifespan, stress and stretch resistance|The boAt rugged Micro USB cable is compatible with most android smartphones, windows phone, tablets, PC peripherals and other micro USB compatible devices|2.4A rapid charge, fast data transmission and rapid speed to sync your device at the speed up to 480mbps|boAt rugged micro USB cable offers a perfect 1.5 meters in length, optimized for an easy use for your comfort at home or office|2 years warranty from the date of purchase | J13: AEWAZDZZJLQUYVOVGBEUKSLXHQ5A,AG5HTSFRRE6NL3M5SGCUQBP7YSCA,AH725ST5NW2Y4JZPKUNTIJCUK2BA,AHV3TXIFCJPMS4D5JATCEUR266MQ,AGWIGDEMFIIUAOXYY2QATNBSUGHA,AFSTSLQUV4EVEXWKBOLEFHL2H5YQ,AGAKDNBHY2FKX7I4ACRGILU7QL7A,AFNWJUWJRHCC6HN52KMG5AKZY37Q | K13: Omkar dhale,JD,HEMALATHA,Ajwadh a.,amar singh chouhan,Ravi Siddan,Himanshu Goel,Udaykumar | L13: R3EEUZKKK9J36I,R3HJVYCLYOY554,REDECAZ7AMPQC,R1CLH2ULIVG5U3,R2DMKIBGFKBD6R,RC89B5IAJUTR5,R3B3DDON5FH8DS,R13WAEJDI5RS36 | M13: Good product,Good one,Nice,Really nice product,Very first time change,Good,Fine product but could be better,Very nice it's charging like jet | N13: Good product,long wire,Charges good,Nice,I bought this cable for Rs.339 worthy product for this price, i tested it in various charger adapters 33w and 18w it supports fast charging as well.,Good,Ok,I had got this at good price on sale on Amazon and product is useful with warranty but for warranty you need to go very far not practical for such a cost and mine micro to type c connector stopped working after few days only.,I like this product | O13: https://m.media-amazon.com/images/I/41SDfuK7L2L._SX300_SY300_QL70_FMwebp_.jpg | P13: https://www.amazon.in/Rugged-Extra-Tough-Unbreakable-Braided/dp/B0789LZTCJ/ref=sr_1_13?qid=1672909124&s=electronics&sr=1-13
... A283: B09PTT8DZF | B283: Lenovo USB A to Type-C Tangle-freeÂ Â Aramid fiber braidedÂ 1.2m cable with 4A Fast charging & 480 MBPS data transmission, certified 10000+ bend lifespan, Metallic Grey | C283: Computers&Accessories|Accessories&Peripherals|Cables&Accessories|Cables|USBCables | D283: â‚¹417.44 | E283: â‚¹670 | F283: 0.38 | G283: 3.9 | H283: 523 | I283: Accessibility meets universal compatibility: Engineered to be compatible with smart phones / tabs / Bluetooth speakers / power banks and any device with Type C port and matching power rating.|Dependable and sturdy: Superior quality with 1.2m Aramid fiber braided and tangle-free cable for longevity and hassle-free handling|Powerful Performance: Work on-the-go with high-speed transfer up to 480Mbps and a 4A fast charging|Simply Stunning : Ultra-modern premium metallic grey design with aluminium metallic connectors that elevates your aesthetics|Compatibility : Compatible with all Type C Devices including laptops, phones, tablets, speakers, headphones and more | J283: AHVAHTQWBVQ564OYZLFO3ABDUUMQ,AEL2DJG4RDMKBB4U7T7FB2D4QL6A,AEZLG2GOZ4US63MFG3TTGRIOWQVQ,AH5FQ2OMFSPNFEWKR7XRHAQXYDNA,AHCWB47L2VDCBKURUGKDLNC3BLAA,AHSLVN2FXVPUVWTY5Y2GW5STS5ZA,AEU3NDBYUVLPYDRFVCIY6IPVUA7A,AFH4EKSLJGS4ZDREEEO5PLDGDWUA | K283: Mohd Arshad,Yogesh Maini,YOGESH,Devaraj V,Sasikumar,Ankeet,Hemanta Das,satinder singh | L283: R3OI9NIP86EJMK,R19REKQNB6DHVK,RN8PZREKYVUCU,R7H07OI7LETQC,RFNCQH476BUID,RBRBI3TZWFXW7,R2ZR75W02IPC5C,RPUDZMSMR65WV | M283: Nice one,Not up to the mark.,Nice product working in Asus zen pro mobile,Good product ðŸ‘ðŸ‘ðŸ‘,Working everything as expected,VERY GOOD QUALITY,Lenovo USB A to Type-C Tangle-free Aramid fiber braided 1.2m cable with 4A Fast charging,Nice Products | N283: Go for it without any hesitation,Even after selecting a branded product(Lenovo), I got this cable which only works with Samsung devices but doesnâ€™t work with LG devices. Poor compatibility.,Nice experiance,,Files transfer okSuper fast charging cable goodMeets my expectation.,Very great Quality,Just purchased and using. Charging ok. Future, I can't say.,Good | O283: https://m.media-amazon.com/images/I/317Bv9KEltL._SX300_SY300_QL70_FMwebp_.jpg | P283: https://www.amazon.in/Lenovo-Tangle-free-Aramid-braided-1-2m-transmission-certified/dp/B09PTT8DZF/ref=sr_1_438?qid=1672909146&s=electronics&sr=1-438
A284: B0B94JPY2N | B284: Amazon Brand - Solimo 65W Fast Charging Braided Type C to C Data Cable | Suitable For All Supported Mobile Phones (1 Meter, Black) | C284: Computers&Accessories|Accessories&Peripherals|Cables&Accessories|Cables|USBCables | D284: â‚¹199 | E284: â‚¹999 | F284: 0.8 | G284: 3 | I284: USB C to C Cable: This cable has type C connector at both ends and a USB C type wall charger/adapter will be required to be used with this cable|Durable and sturdy: 1 meter long cable with 5mm thickness|65W fast charging up to 4A/ 65W|Comes with Smart Charge Auto Detect Technology|The cable supports data transfer at a speed of 480Mbps|Prevents overheating and overcharging with several built-in safeguards|Suitable for all major smartphones including OnePlus, Xiaomi, Realme, Oppo, etc. | J284: AE7CFHY23VAJT2FI4NZKKP6GS2UQ | K284: Pranav | L284: RUB7U91HVZ30 | M284: The cable works but is not 65W as advertised | N284: I have a pd supported car charger and I bought solimo cables previously which work perfectly fine but this one doesn't trigger full 3A fast charging unlike solimo usb a to usb c, which is strange because this is supposed to be a 65W charger with 4A fast charging support.Anyways it's a good built product and works but not as expected. It might be compatible with your chargers but I tested 2 different car chargers and both didn't go full speed. | O284: https://m.media-amazon.com/images/W/WEBP_402378-T2/images/I/41Vpx5MVtaL._SY300_SX300_QL70_FMwebp_.jpg | P284: https://www.amazon.in/Amazon-Brand-Charging-Suitable-Supported/dp/B0B94JPY2N/ref=sr_1_444?qid=1672909146&s=electronics&sr=1-444
A285: B0B3XXSB1K | B285: LG 139 cm (55 inches) 4K Ultra HD Smart LED TV 55UQ7500PSF (Ceramic Black) | C285: Electronics|HomeTheater,TV&Video|Televisions|SmartTelevisions | D285: â‚¹47,990 | E285: â‚¹79,990 | F285: 0.4 | G285: 4.3 | H285: 1376 | I285: Resolution: 4K Ultra HD (3840x2160) | Refresh Rate: 60 hertz|Connectivity: Wi-Fi (Built-in) | 3 HDMI ports to connect set top box, Blu Ray players, gaming console | 1 USB ports to connect hard drives and other USB devices | eARC | Bluetooth 5.0 | Optical | Ethernet|Sound: 20 Watts Output | 2.0 Ch Speaker | AI Sound (Virtual Surround 5.1 up-mix) | Auto Volume Levelling | Bluetooth Surround Ready|Smart TV Features: AI ThinQ & WebOS 22 with User Profiles | Game Optimizer & Dashboard | Î±5 Gen5 AI Processor 4K | Unlimited OTT App Support: Netflix, Prime Video, Disney+ Hotstar, Apple TV, SonyLIV, Discovery+, Zee5 | ALLM & HGiG Mode | HDR 10 Pro & Active HDR|Display: 4K Ultra HD LED Display | 4K Upscaler | AI Brightness Control|Warranty Information: 1 Year LG India Comprehensive Warranty and additional 1 year Warranty is applicable on panel/module from the date of purchase|Installation : For requesting installation/wall mounting/demo of this product once delivered, please directly call LG support (Please visit LG Website for Toll Free Numebrs) and provide product's model name as well as seller's details mentioned on the invoice | J285: AFCWL3MX7BP2ZUDD37MEAENZDQ2A,AGGFXDLCFZMTLJJDR3ZFKEOXCFLQ,AHEBPCKZFBKQMB6FXQLRP72OG4ZQ,AF2V6W7LKARBMZQLFL44AY6KYOCA,AGGGM5HE2PLQKZV33JOD6K2TYPQQ,AG5VQTV5OVY2Q42ZQPWXTRU2PSLQ,AFZ5KWM4MSPU25YIO2CYGGSNYV6Q,AE6THY5M7QTHCQRZ6PIUENS3NY4A | K285: Raj Mohammed,Samson,Haroon sayeed,P Imran Khan,Manohar P,SRF Prashant,Akash Sharma,Sumesh | L285: RC3ZLDRM8GA9T,RMDN4PSDM8SKK,R1YFAMDJ7P0SY3,R2WX7G1LIQSEBM,R2L4UCJ30902KF,R2MCXM8TACTRFL,R1KFS9LDEOT49N,R29FE7S1YAMO8N | M285: Love Amazon but lg is misleading,Amazing product,Worst service from LG,Good,Simply beautiful,Satisfied with the TV,Great deal,It is quite ok | N285: There's no magic remote and lg should include it by default as it makes life easier. The magic remote costs around 3k approximately.Display: when turned on tv and tested the display on black wallpaper found very small green and white dots.Immediately called up Amazon first and then we scheduled a tech visit.The tech did not come rather spoke on call and asked what's the problem and when informed about the problem he said needs to be replaced but no body came with it.So i waited for 2 days again and nothing was showing up on Amazon app about replacement so doubting it I called up Amazon customer care again and explained everything again and finally spoke to some one and she said she will get it replaced and i was given another date within 4 days.This time the replacement came and was good.,Amazing picture quality and sound clarity, but only drawback is that it did not come with a Magic remote.,The television is good but the installation service is pathetic first of all they did not contact us till 2 days after the TV delivery and we got frustrated and call LG customer service and they accepted our problem and send a technician after 2 hours and while installing the mount he installed 3 bolts successfully but he broke the last bolt and we asked him will it not cause a problem in future he said it wouldn't but we don't really believe him.,Good,Very nice good quality best in this price,Nice choice,Best deal,I like LGWorth for price. Very good | O285: https://m.media-amazon.com/images/W/WEBP_402378-T2/images/I/51dOjIreG4L._SX300_SY300_QL70_FMwebp_.jpg | P285: https://www.amazon.in/LG-inches-Ultra-55UQ7500PSF-Ceramic/dp/B0B3XXSB1K/ref=sr_1_445?qid=1672909146&s=electronics&sr=1-445
A286: B08RZ12GKR | B286: Tata Sky Digital TV HD Setup Box Remote | C286: Electronics|HomeTheater,TV&Video|Accessories|RemoteControls | D286: â‚¹215 | E286: â‚¹499 | F286: 0.57 | G286: 3.5 | H286: 121 | I286: Color black|Long lasting|Digital TV HD Setup Box Remote | J286: AHSXEBRVZO6MAYZRN6O6ZGT6TQIQ,AE3WP33376SA5IZT4Z5P25RW5SNA,AEP577REOPX5HAMEECZZKMOYZ3OQ,AHXFU2NP5EL5BNCYY3V2BOWDYX4Q,AEPLVXU6CECEGNG6EUUSHMERYNRA,AEQ7NM325SUT6YB62ZG376GF7O7Q,AEBV2AUCTSN3QJO4LJVJ66HVYSTQ,AHCLG7MIFKVJJEAVPYJPW2OPWWEQ | K286: Rajni Gupta,Lakshmipati Hari,Sriranga Pudupakkam,radha krishnan,Nandan,Dr Laksheswar Bora,Laxmi Narayan,KONGA VIJAYA NAGARAJU | L286: R1T3IMKX5I23BL,R2ACT45S9ER36B,R3JVGT39A4NCLG,R2ZS039FIJFE2X,RUE1VX5KVXKYM,RJUMN5TQXB046,RKB470J0YGFZS,R30Z26FC4CVOIK | M286: NOT GOOD IN DURIBILITY.,The remote lasted a grand total of one week.,Good product too early to say final word on durability,prompt delivery plus supet product,It's good.,satisfactory,Body problems,Damaged product | N286: It is just ok,The fist time I bought it lasted about 6 months. The second time, barely a week. Spent a little more money but went back to the original from Tata Sky. Not really going to buy this again,Good product,i like it for prompt delivery plus super touch operating t.v.,It's working as expected.,satisfactory,Weak of body,We received damaged product...there is a crack in front of the remote.....pls check n make sure this should not be repeat again... | O286: https://m.media-amazon.com/images/W/WEBP_402378-T1/images/I/41o4qDiFFwL._SX300_SY300_QL70_FMwebp_.jpg | P286: https://www.amazon.in/Tata-Sky-Digital-Setup-Remote/dp/B08RZ12GKR/ref=sr_1_447?qid=1672909146&s=electronics&sr=1-447
A287: B0B4T8RSJ1 | B287: pTron Solero T241 2.4A Type-C Data & Charging USB Cable, Made in India, 480Mbps Data Sync, Durable 1-Meter Long USB Cable for Smartphone, Type-C USB Devices (White) | C287: Computers&Accessories|Accessories&Peripherals|Cables&Accessories|Cables|USBCables | D287: â‚¹99 | E287: â‚¹800 | F287: 0.88 | G287: 3.9 | H287: 1075 | I287: Solero T241 data and charging cable is equipped with a Type-C USB port, the cable supports up to 2.4Amps of power output for powering and fast charging your smart device.|Charge & sync, this USB cable can charge and data sync simultaneously at 480Mbps speed, compatible with all devices with a C-Type USB port.|Durable PVC Outer Exterior: PVC cables are versatile, high in tensile strength, flexible, and good conductors.|pTron Solero T241 Type-C USB cable is 1 meter in length, optimized for easy use for your comfort at home or office, helps you to overcome distance restrictions.|This data and charging C-type USB cable has gone through scientific tests like 5000 times USB insert, 24 hours salt spray, and 10000+ bend life span which ensures long service life. | J287: AF477BP57JM7Z4JD4PYB2K33R6AQ,AGTDD34Y77OB36JNYQWQDN7MHECQ,AG7POKBSWQUO4VOYD4HDWYKMMJ4Q,AFZS6H2ZFJEJHRWIJ3IYL7V6KRPA,AHCYM2ECKI2MNOIDHDG4PT6IIN6A,AECZ4IP3TBM4EUG52BZAOQV3EKIA,AH6RQDXZYKAUPNBOYC4NAZERTFOQ,AFTVETL4HGH4KRUF4NXGJUEDPBAQ | K287: Placeholder,à¤¶à¥à¤°à¥€PKà¤œà¥€,Gauri salkar,aQeel,Ashish Raj Arora,Ankit,Amazon Customer,Ramamoorthy Jaykumar | L287: R1Q323BB35OP30,RJ0CSQUUWFF9W,R23OB4XMH3S9QD,R1K5FQR6CYMQAV,R3QMD6JDUGQUCI,R1R5LTMWOXI38M,R241G3F07D3OBH,R1O7BQ61DXRVWW | M287: The metal pin is losing it's strength,Sahi h bs 44 rupe ki and dilivery charge 40,Good Charging cable,Good sturdy micro usb cable with good charging speeds,Cheapest micro USB cable in the market,boat is better than this,I bought this for 199rs best charging cable for all mobiles,Good | N287: It's a good data cable and I recommend it to purchase,the only issue was the metal pin is not fixed firmly so it has become loose,otherwise no issue,must purchase,https://m.media-amazon.com/images/W/WEBP_402378-T2/images/I/615SgnWv1ML._SY88.jpg,Charging cable which is sturdy it's not a fast charging cable but the three outlets does the job.,Good sturdy micro usb cable with good charging speeds. Please don't raise prices,Nice product, a simpla microusb cable,ðŸ˜‚,Best for this price,Good one | O287: https://m.media-amazon.com/images/W/WEBP_402378-T2/images/I/31XFe74gRjL._SX300_SY300_QL70_FMwebp_.jpg | P287: https://www.amazon.in/pTron-Charging-480Mbps-Durable-Smartphone/dp/B0B4T8RSJ1/ref=sr_1_448?qid=1672909146&s=electronics&sr=1-448
A288: B0B7B9V9QP | B288: VU 108 cm (43 inches) Premium Series Full HD Smart LED TV 43GA (Black) | C288: Electronics|HomeTheater,TV&Video|Televisions|SmartTelevisions | D288: â‚¹18,999 | E288: â‚¹35,000 | F288: 0.46 | G288: 4 | H288: 1001 | I288: Resolution : Full HD (1920x1080) | Refresh Rate : 60 Hertz | 178 Degree wide viewing angle|Connectivity: 2 HDMI ports to connect set top box, Blu-ray speakers or gaming console | 2 USB ports to connect hard drives or other USB devices|Sound: 20 Watts output | Dolby Audio | DTS HD | Bass Boost | Dialog Clarity | TruVolume|Smart TV Features : Netflix | Prime Video | YouTube | YouTube Music | Zee5 | Wake up on LAN, WiFi | Wireless IEEE 802.11: b, g, n, 2.4GHz | Screen Mirrioring|Display : A+ Grade High Bright Panel I Natural Color Enhancer I Adaptive Contrast I Clear Motion I 1:1 Pixel Mapping I Cinema Day & Night Mode I Game Mode I Sports Mode I MPEG Noise Reduction|Warranty Information: 1 year warranty provided by Vu from date of purchase|Installation Information : Installation/Wall mounting/Demo will be arranged by AHS Team. For any other information, please contact VU support on (visit brand website for toll-free numbers)|Easy Returns: This product is eligible for replacement within 10 days of delivery in case of any product defects, damage or features not matching the description | J288: AHQCV7O3JOMFFMD7EGIZ2NGSU6JQ,AGTB6FEDSOBJNAVZSDSY73YUVTXQ,AFHULRP4IR7O4FQKWKI266O7VZQQ,AFKYLJ2CLPR7FIWD2MBXNIER7R3A,AFJRW562LETJUBBZYVI6VZA35WPQ,AEEMPL2VIRNJTYATMFPHFSHI4IOA,AGKQQC7ST26N5VFAHMURX3R2RAJA,AFICI6GI5DCTRS6JVCYRPATIPXSQ | K288: Logaraj m,KIRAN KUMAR GUDLA,Sandeep Kumar,Jaydeep Shah,Nagendra,Sumit pandey,Harsh Bhatia,Sivakrishna | L288: R22OHRDXFQ2O98,RSAB4HSG5ZH9H,R3FC8NLEZ4DJ8N,R1RTOHK5EM9WPX,RFVPFUT2AVH9A,R232XWKJREFG9M,RZAZ7VZRRHLFH,R1CEPOZCGKCSWH | M288: Vu brand superb quality,Value for price,Thik hai but android nahi hai,Good model for entry level 32" TV need.,Good product value of Money,Great TV,The sound quality, speakers, picture quality are just OK. MID GRADE PRODUCT AT MOST,Picture Quality | N288: Super,Good Quality , value for money.. in time installed,Tv thik hai but vu ka customer support bhot bekar hai , bacho se tv lock ho gya tha , vu me call kia to kahne lage Amazon me baat karo , matlb tv ka lock Amazon wale batenge , Amazon me baat ki to kahte hai vu me baat karo , baad me maine hi kisi tarah uska lock khola , but vu customer support bhot bekar hai , vu ka smart tv thik hai,In time delivery and proper installation at the time of delivery itself. Value for money for 32" TV requirement with branded product.,Good product,Tv is awesome, one problem is casting, whey you cast video from hotstar it comes black screen. Other than that picture and sound quality is awesome.,Picture quality Just OK. Sharpness missingSound and speakers Need lot of improvementSettings and Menu can be optimised furtherOverall it's a mid grade product,Picture quality good as expected, internet experience also good | O288: https://m.media-amazon.com/images/I/51eyIMn02bL._SX300_SY300_QL70_FMwebp_.jpg | P288: https://www.amazon.in/VU-inches-Premium-Smart-43GA/dp/B0B7B9V9QP/ref=sr_1_449?qid=1672909146&s=electronics&sr=1-449
A289: B08XXVXP3J | B289: Storite Super Speed USB 3.0 Male to Male Cable for Hard Drive Enclosures, Laptop Cooling Pad, DVD Players(60cm,Black) | C289: Computers&Accessories|Accessories&Peripherals|Cables&Accessories|Cables|USBCables | D289: â‚¹249 | E289: â‚¹999 | F289: 0.75 | G289: 4.3 | H289: 112 | I289: Cable Color- Black , Cable Length- 60 cm , Connector Type - USB Type A Male to Type A Male|Premium quality SuperSpeed USB 3.0 Type A to A M/M device cables|Double-shielded, twisted-pair data wiring minimizes cross talk for error free SuperSpeed data transfer rates Support data transfer rates up to 4.8Gbps|Backwards compatible with computer USB 2.0 and USB 1.1 ports - these cables also allow connection of USB 3.0 devices to legacy USB 2.0 computers|PLUG & PLAY : No driver needed for the usb 3.0 a to a cable. Just plug-and-play for hard drive enclosures, printers, modems, cameras, and other SuperSpeed USB peripherals.349-699 | J289: AEOHCZKNWRXT3H4Q66WMEMB672IA,AGUSIMQLSTJXNHNX4OT5KEJZO2NQ,AFLVRNJ3FWTYVR2QR7LMMAXOR2VQ,AGYNRF4LKWIYRL2EOCVDINQ62RAQ,AHUGZ3YEQ27J3KSESPRFRAKNF3LA,AGBP6M4EOJSBHZTYTH2T4BKNJ7MQ,AECZ7LYEACIXJTSOCFWLHVZLJPEA,AHOHKZ6CPYXLBXPKLZCDT7HHD6CA | K289: Shilpa M,Akash,Aman.MD,Manoj Yadav,Ashutosh,Patel,Saikrushna Dyaga,Amazon Customer | L289: RDLKA670FVMKY,RZZB1IDY3USBP,R30B6VRIVHWOIP,R31A5RDIAY3O0R,R26RJ6WBBMVVXJ,R1PZ0SMCXPJO9C,R3QLX0DTF1C3J7,R23GQW7DPSVOA0 | M289: Product life ia short,Good,Waste,Value for money,Very nice product at a reasonable price. Value for money.,Good replacement cable at this price,Worst cable. Not working even after replacement. Dont buy guys Manufactured in China.,Not working | N289: Good and easy to use but product life is hell short. It means you have to buy it within next six months.,Good,Better,Quality is good and working as expected.,,Decent replacement cable for my aging external hdd. Works at usb 3.0 speeds,Worst cable. Not working even after replacement. Dont buy guys Manufactured in China.,The USB cable was useless. After logging in this cable, I was not able to transfer data from one laptop too another. | O289: https://m.media-amazon.com/images/I/41XgWuRRNFL._SX300_SY300_QL70_FMwebp_.jpg | P289: https://www.amazon.in/Storite-USB-3-0-Transfer-Enclosures/dp/B08XXVXP3J/ref=sr_1_450?qid=1672909146&s=electronics&sr=1-450
A290: B06XGWRKYT | B290: Kodak 80 cm (32 Inches) HD Ready LED TV Kodak 32HDX900S (Black) | C290: Electronics|HomeTheater,TV&Video|Televisions|StandardTelevisions | D290: â‚¹7,999 | E290: â‚¹15,999 | F290: 0.5 | G290: 3.8 | H290: 3022 | I290: Resolution: HD Ready (1920 * 1080) | Refresh Rate: 60 Hertz|Connectivity: 2 HDMI ports to connect set top box, Blu Ray players, gaming console | 2 USB ports to connect hard drives and other USB devices | 1 VGA Port to connect the laptop|Sound: 20 Watts Output | Audio Boost 20 watts Output|Display: HD Ready | Dynamic Picture Enhancement | Wide Viewing | Perfect Panel | Sleek & Sophisticated Design|Easy returns: This product is eligible for replacement within 10 days of delivery in case of any product defects, damage or features not matching the description provided | J290: AHILWO2P2PT6EKK2HS4EALRJIQ7Q,AGBF4IFXPQPS3KTL2RET4NAYKSZA,AF3WE2A3BJW3ZK2XTUU7GTQ5P2IA,AGWS7K3SXNU4RJUBPYYEVO76HULQ,AGDSPVKPPJG2FSNEYACD45GIJ7WQ,AFSG7IWPY64B6DNMUDVXYCEK4G4A,AGABMXBJYA3LSM5LIRNXL3HMHTLA,AHBNWKWV73LMUFENL6T43ZEP2ASQ | K290: Sandip Shingrakhia,Abhishek Gagan,dasprathap,Pradeep,DrChirag Rajpara,Atanu Sarkar,Puja Das,Shankar | L290: R20Y7L8T8S0B2V,R19O1AZBIG1F5P,R1HA5IN5GZZEKJ,R3BGLBQWLQUBW0,R2GKH9JNW12AKY,RKEC16QEHA2WT,R1A9NXDM3RASAL,R25TUXKCEEATJ0 | M290: This is a Best kodak LED,Product is Good as per the price but customer service experience is too bad,It's ok,Company doesn't provide Installation.Demand change for it.,Good but not best,Good product ðŸ‘,Very nice,Display quality and incomplete product | N290: ,Product is Good as per the price but customer support team is very bad, asking for money for installation and the most important thing that customer service team have not good manner/behaviour to handle the customer...1 star for them, if possible then start should be in minuse for them.,It's ok,Everything is ok,I have used Kodak 32" led tv since last 3 year and running well so i want to purchasesame tv again (same model number) but when new tv received i notice that outer body is not so durable and have no volume or menu switch in new one!! (Old one habe 6 keys on right side panel) only have one on off switch.. Others in remote only!!Now lets see how many years it runs... +Point is it has optical port (thomsan and kodak both mfg by simtronic india ltd),Picture and sound quality is very good. Allover nice product. Vallu for money.,Very nice,VGA port is not present, display quality is not good. | O290: https://m.media-amazon.com/images/I/51xYKHUpdHL._SY300_SX300_QL70_FMwebp_.jpg | P290: https://www.amazon.in/Kodak-inches-32HDX900S-Ready-Black/dp/B06XGWRKYT/ref=sr_1_451?qid=1672909146&s=electronics&sr=1-451
A291: B07CWDX49D | B291: AmazonBasics Double Braided Nylon USB Type-C to Type-C 2.0 Cable, Charging Adapter, Smartphone 6 feet, Dark Grey | C291: Computers&Accessories|Accessories&Peripherals|Cables&Accessories|Cables|USBCables | D291: â‚¹649 | E291: â‚¹1,600 | F291: 0.59 | G291: 4.3 | H291: 5451 | I291: Connect USB Type-C enabled devices (MacBook, Chromebook Pixel, Galaxy Note 7, etc.) with standard USB Type-C 2.0 enabled devices and accessories (smartphones, car/wall charger, multi-port adapters, etc.)|Ideal for charging and powering USB Type-C enabled devices, as well as syncing data, photos, and music; Type-C port is half the width and one-third the height of a standard USB-A connector (slightly larger compared to Lightning or Micro-USB ports)|Reversible designâ€”easily insert the connector into any Type-C enabled device (does not matter which side is up)|Durable braided nylon fiber cloth provides protection, strength, and flexibility; added layer of protection for improved durability and to reduce fraying; cables have been tested to bend 95-degrees 5,000 times; fun contemporary color options for a trendy appearance|Up to 480 Mbps data transfer speed; power output up to 5V, 3 amp; certified by USB-IF to be compliant with USB 2.0|1 year limited warranty | J291: AGPOYBESW4JLTMELJLGMLV4JKJEA,AGJ2XZ2PPFHMYQ54KPSUGDLHTOIA,AEPLOFVKFHPQH4DFHKQXGKWL24NQ,AEXK3LPRGQWVMCIQZGHHJUBHHAZA,AG3J2PDHKL63SV6RT5SZKPHEJM7A,AHNO42W4KBB6YAKX3VZKVCLI67DQ,AEGCEHUVRPOYDRJHI4UJVB2XY6FA,AEQ5ZXLEZFYS2Q7GBBW6IDJTH5GQ | K291: Gaurab Chakraborty,Pratik Patel,Rahul sharma,SEKAR,Nilesh Madhani,Saurabh Dongre,s s.,Sumit jogade | L291: R2BUNT9GM6PUP1,R2Q5VBGDJQHT1E,R1CICFI88LJ1JV,RVYACTR72CHW1,R2XM5RGIHDDR05,RJZUZ9HFCXQSD,R16G8AJOJIMF8H,R10M9KZFIDFMAD | M291: Overall it's a good product for mobile charging.,Awesome ðŸ˜Ž,Gud data cabel....,Very good USB C TO USB C Cable .The one does not entangle to develop fold leading to cracks and cuts,Best,Rigid and high quality,Super durable,Great i have been using for 6 month | N291: Good product ðŸ‘ðŸ»,Nice products and easy to use.very good quality and the product is very good ðŸ˜Š,,Simply Go for it.I have been using this almost for the last 1.5 years. I have been using this every day, the whole day during office hours, and sometimes work at home both for my Phone and Laptop using with 65-watt charger.It is trouble-free and does its job as we expect it to do. No problem whatsoever.The big plus point with this cable is that it does not entangle to develop constant fold that becomes cracks over a period of time. This is the issue that I had with other cables. This one is perfect.As I said, You can simply go for it. Strongly recommended.,Best,The length could have been longer,Value for money,Godd quality material and fast charging | O291: https://m.media-amazon.com/images/W/WEBP_402378-T1/images/I/41AUgZQAs5L._SX300_SY300_QL70_FMwebp_.jpg | P291: https://www.amazon.in/AmazonBasics-Double-Braided-Nylon-Type-C/dp/B07CWDX49D/ref=sr_1_452?qid=1672909146&s=electronics&sr=1-452
A292: B09TY4MSH3 | B292: Firestick Remote | C292: Electronics|HomeTheater,TV&Video|Accessories|RemoteControls | D292: â‚¹1,289 | E292: â‚¹2,499 | F292: 0.48 | G292: 3.3 | H292: 73 | I292: by JBDE | Compatible For Amazon Fire TV Stick (3rd Gen, 2021) | Compatible For Amazon Fire TV Stick Lite | Compatible For Amazon Fire TV Stick (2nd Gen) | Compatible For Amazon Fire TV Stick 4K | Compatible For Amazon Fire TV Stick 4K Max streaming device | Compatible For Amazon Fire TV Stick Plus (2021) ||This is voice remote control, you need to pair it first before you use, and below is pairing steps: Press the Home button about 8-30 seconds until the LED starts to rapidly flash amber, then the remote should automatically pair with your device.|With standard navigation and playback controls, you can quickly skip to your favorite scenes.|Alexa funtion make it easily to find, launch and control all existing content you want, such as play music, view sports scores, check the weather, see live camera feeds, and control compatible smart home devices. | J292: AHH74UTDYQPVBMM4HEEMRAU2DNMQ,AEZYVA7F52G2DCIUPCDUKGNHJ6LA,AEZTZPXHRSWDF5D35QHDQE7QJJCA,AHR6VGN4EOF4UK4ZISINZJ4EFUTA,AEPLVJ2BAVC57LGFBTZCH2YBNJMQ,AE7BIR5NP6B6UA6DSJE23BBYJGHQ,AHEJQ5MN7YJB4A3XTDSTTZID3WKQ,AEHR3J2Y6MUL5B3J5KJNJAH24JDQ | K292: Harish Thirunahari,Gajanan Hirde,Tomi breeze,vasudha,Sowmya,Arpit Narula,NAVDEEP GUPTA,Vikram singh | L292: R39CZQR3ZPJ0Q7,R1XRT2636AEQEO,R2BSV4B70RKKC8,R2JBI9XCV1RU9E,RC0ZKG91JP10X,RAO17F0JUKD13,R1YWFT51T2HFXX,R2GVGI7SXLDIW9 | M292: Not how original remote works,Chinese quality,It's okay.,good one,Works great with Firestick,Substandard Copy of original at the cost of original,Pathetic,total waste product don't buy battery drain problem | N292: I bought this remote as My original remote of Fire tv 4k stopped working. This remote works OK OK. so when it works it is interesting,I get the right bottom popup note from Fire TV that the battery is too low in the remote even if the batteries are new.If you are in urge to go to specific show and play it, sudden it stopps responding to the remote. and all of a sudden your thumbnails keeps scrolling without you doing anything. so the response is in accurate some times.When it is working alright some times, it goes well without any issues. So don't know what to say. If you want to put 2k extra and buy the original , i suggest you do that. if you are running short on money and not feeling to put that amount for original and you can adjust with the above mentioned issues. then you are good to go with this one. All the best on your buy guys. Cheers!,You've to press too hard,Not as responsive as the previous one. Need to press harder.No real problems though.,nice product,Thankfully got this to replace firesticks remote which malfunctioned very soon.this option is best fit at best cost .Voice control as well works well,Not an original remote. Cheap copy. Working at the moment but can breakdown any moment.,Never buy separate remote, it is useless,don't buy this product battery drain problem | O292: https://m.media-amazon.com/images/I/31jcyZIAWWL._SX300_SY300_QL70_FMwebp_.jpg | P292: https://www.amazon.in/V-smash-Firestick-Remote/dp/B09TY4MSH3/ref=sr_1_453?qid=1672909146&s=electronics&sr=1-453
A293: B07RY2X9MP | B293: AmazonBasics 10.2 Gbps High-Speed 4K HDMI Cable with Braided Cord (10-Foot, Dark Grey) | C293: Electronics|HomeTheater,TV&Video|Accessories|Cables|HDMICables | D293: â‚¹609 | E293: â‚¹1,500 | F293: 0.59 | G293: 4.5 | H293: 1029 | I293: 10-Foot high-speed premium HDMI cable (A Male to A Male) for transmitting video and audio signals from source to display|Connect tablets, laptops and other HDMI enabled devices to projectors, video conference systems, HDTV, monitors, and more|Durable, double-shielded 30AWG cable with nylon braided jacket and aluminum housing|Supports Ethernet, 3D, 4K video, and Audio Return Channel (ARC); 30Hz, 10.2Gbps bandwith|Plug and play design removes the need for complicated drivers or setup time; Backed by an Amazon Basics 1-year limited warranty | J293: AFKKM4SXCCLJDRUQUZ6J4W7HLDYQ,AHHPWPWUPOBG2CH3CD4GHCKZP3VA,AGS3GOEZIOT6QABCS7GSKSRF6ZOA,AE2NS3LUBQ33MFLYXAFBOTZOUO5Q,AFMTLEM5MPBZOB3YBELL32ZO7W6Q,AFNCKSDO4JTIY2GAW4HZDSB5AXYQ,AHB4PR4VAIZKTQDBHC5P3IQ2B72A,AFTGBV2EOMQJUYBEV47YD4UEI24Q | K293: saatwik,Mubashir,Arup Datta,Amrut S,Kindle Customer,Rasheed,Amazon Customer,Akash Pradeep | L293: R3H4IRBX721OIC,R20KZD07FRNQKL,R1PLCFQQFJ5O5X,R15J54ID6Y9FF4,R175ZT8BC8T0GJ,R34ALRVGYAYJDY,RBKV67DDOAO0H,R34RBTS6ZN4MQ0 | M293: AmazonBasics Product,Good,Very good,Value for money product,Nice product quantity is nice connective is fast,Product,Good Quality Product,Never thought it be would this good!! | N293: The product quality is really amazing. The wire length is enough and it is a sturdy wire. It comes with one year warranty which makes it a good choice to have.,Quality is good,I like it very much. It is a very good product.,,,Nice one,High Quality product, HD picture was converted to 4kHD quality with better visibility.,The cable looks and feel very sturdy. Streaming experience was really good. I tried mirroring my laptop with the Tv screen, it works perfectly. I would really recommend to get this length (10 foot ~ 3m), it gives a good room space to work with. | O293: https://m.media-amazon.com/images/W/WEBP_402378-T2/images/I/41m1oMmTMCL._SX300_SY300_QL70_FMwebp_.jpg | P293: https://www.amazon.in/AmazonBasics-High-Speed-Braided-10-Foot-1-Pack/dp/B07RY2X9MP/ref=sr_1_454?qid=1672909146&s=electronics&sr=1-454
A294: B0B2C5MJN6 | B294: Hisense 126 cm (50 inches) Bezelless Series 4K Ultra HD Smart LED Google TV 50A6H (Black) | C294: Electronics|HomeTheater,TV&Video|Televisions|SmartTelevisions | D294: â‚¹32,990 | E294: â‚¹54,990 | F294: 0.4 | G294: 4.1 | H294: 1555 | I294: Resolution : 4K Ultra HD (3840x2160) | Refresh Rate : 60 Hertz | 178 Degree wide viewing angle|Connectivity: 3 HDMI ports to connect set top box, Blu Ray players, gaming console | 2 USB ports to connect hard drives and other USB devices | Dual-band Wi-Fi | Bluetooth 5.1|Sound : 24 Watts Output | Dolby Atmos | Dolby Digital|Smart TV features: Google TV | Watchlist | Google Assistant | Far Filed Vioce Control | Chromecast, Miracast, DLNA | Auto Low Latency Mode for VRR | Supported Apps : Netflix, Youtube, Prime Video, Hotstar, SonyLiv, Hungama, JioCinema, Zee5, Eros Now|Display :10 bit Panel | Bezel-less Floating Display Design | ALLM | Decoding of Dolby Vision, HDR10, HLG | 1 Billion Colours | MEMC|Warranty Information: 2 Year Comprehensive Warranty on product provided by Hisense from date of purchase.|Installation: For requesting installation/wall mounting/demo of this product once delivered, please directly call Hisense Support for assistance (Please visit Hisense Website for Toll Free Numbers) and provide product's model name and seller's details mentioned on your invoice. The service center will allot you a convenient slot for the service|Easy Returns: This product is eligible for replacement within 10 days of delivery in case of any product defects, damage or features not matching the description | J294: AFXA73X6367FW6C7AQNXOTR7BZ3A,AF5B3NOBEX5PXWD4SBDB5KE7JP5A,AET2WYQTCLGU3TB7VHZHJYJ4HMWQ,AF2LCFC5G6OATXBE73BMIXC5PNHA,AFJZOVZXLGXGULVMNOYLFI5TO4GQ,AEYQETW4Z4P4AT5KURWYCVXIV6QA,AH7AIXAIDIIIIZOPOOS4T3B7UI4A,AF537NCMNYM56KBWSILNOUOEI5CA | K294: yash,Amazon Customer,Nagababu,Krunal Patel,Omi Mayekar,Irfan Hussain,Arif,harshit | L294: R2QJLRRYLEJFIO,RC2JPYCTJRIWP,R2G6GUH2R64F4D,RRKKD7U3BYBEI,R2GMM9FNW2M5Z0,R194PI32Y48S87,R2I2156P73J3YL,R10LLYRO2Z4E2G | M294: Value for Money product.,Overall Tv is good,Good,Good performance so farâ€¦ considering the price range,Received a defective piece,Nice,TV bundled with Google ecosystem gives a extra boost,Good product | N294: Wifi connectivity is getting lost frequently. (at every 30 to 45 minutes). We have to re-connect to wifi.All other specs : Good for price.Jio cinema : not working (even 3rd party app is also not working)Startup time : comparatively high.Display : superb !!Sound : Not so good.Best if you gonna Buy Soundbar with woofer!,Tv is good but i have some question for manufacturer. I am not able to find a option to choose default input. As i want to see HDMI1 when tv start or whatever i choose last.,It is good within the price segment. But there is some delay when we increase or decrease volume it take few seconds to reflect on tv. Else everything is okay,Happy with the performance & picture quality in this price range comparing to other valuable brandâ€¦.,,Nice,TV picture clarity is good added with Google interface it gives good user experience,https://m.media-amazon.com/images/I/71aTqzdBRdL._SY88.jpg | O294: https://m.media-amazon.com/images/I/41uqZs26+oL._SY300_SX300_.jpg | P294: https://www.amazon.in/Hisense-inches-Bezelless-Google-50A6H/dp/B0B2C5MJN6/ref=sr_1_456?qid=1672909146&s=electronics&sr=1-456
A295: B0BBMGLQDW | B295: Tuarso 8K HDMI 2.1 Cable 48Gbps , 1.5 Meter High-Speed Braided HDMI Cable ( 8K@60HZã€4K@120HZã€2K@240HZ ) HDMI 2.1 Cable Compatible with Monitors , Television , Laptops , Projectors , Game Consoles and more with HDMI Ports Device | C295: Electronics|HomeTheater,TV&Video|Accessories|Cables|HDMICables | D295: â‚¹599 | E295: â‚¹1,999 | F295: 0.7 | G295: 4.2 | H295: 47 | I295: âš¡ [ Newest Technology 8K HDMI 2.1 Cable ] - Tuarso hdmi 2.1 cable have bandwidth of 48Gbps , supports 8K@60Hz and 4K@120Hz . Dynamic HDR and 12Bit color depth and eARC . It is also backward compatible with HDMI 2.0b / 2.0a / 1.4 / 1.3 / 1.2 / 1.1 versions .|âš¡ [ HDMI Cable For Game Enthusiasts ] - This HDMI Cable is not limited to 4K@60HZ , it can break through 4K and achieve 8K ultra-high image quality , It can also achieve a super smooth picture of 4K@120HZ . Variable Refresh Rate ( VRR ) synchronizes the refresh rate of the screen and the source to avoid picture lag . Quick Frame Transfer ( QFT ) transfers each frame at a higher rate . Maximizes the value of the graphics card and monitor .|âš¡ [ 24K Gold Plated & Braided Cable ] - 8K hdmi cable connectors made of 24K gold plated , aluminum shell stable heat dissipation .Cable core made of 30AWG tinned copper and features triple shielding , can seamlessly transfer high-quality video and audio signals , The nylon braided cover on the outer layer ensures excellent durability under heavy use and multiple mating and unplugging , and can withstand more than 25,000 flexes in rigorous laboratory testing .|âš¡ [ Immersive Cinema-like Sound Effect ] - 8K hdmi cable 2.1 supports the latest high-bitrate audio formats including DTS Master , DTS:X , Atoms , and enhanced Audio Return Channel ( eARC ) . It offers an immersive multi-dimensional experience and enhances audio detail and depth .|âš¡ [ 24 x 7 Customer Support ] - This hdmi cable 2.1 comes with professional after-sales support and 6-month warranty . You're welcome to contact us with any questions or concerns , We will deal with your problem as soon as possible . | J295: AH34W5DLRK5DLTLP73YKFLTTKWAQ,AE7KUNNQKS6JSHH7QVFPPRKCS4BQ,AEEWMW6LV5AVBCW6OTUO2TRYKY2A,AFYNKZR2T74OJU2LN2FKK7FM5BLQ,AEE3BW7DUIDZY367EH44OKNKDJDA,AEVZZKWDBY3YYS4AKWTRMY7ILF3Q,AFSFGSG745WPTJKCZ2FOAR2DMFCA,AHFYGVFMNT5FXKSBIHW7ANUJD22Q | K295: Jitu,Shan Raj,Brajmohan Gaur,shiv,shameer,Debasish nayak,9618259608,Lazy Lion Ankur | L295: R1S57TIOL6E20F,RIL69DS3C4JGC,R2GWGCF8S3OWCN,R1NI7YG9KNMCX2,RIQHKLJ3CV86P,R2SQH0UGZ9II5U,R5UPOXES8HS5T,R24SCGVHQZOYOA | M295: Good Product,Nice,Customer service support information not found on box.,Value for money,Good product,Nice ðŸ‘,Best the hdmi cable,Exactly as discribed, enchanced Quality | N295: As mention in description, its awesome.,Nice,Good lengthy with good Metalic body on jack side., Difference can't find with older cable.,Great Stuff and superb quality,Good product,Nice ðŸ‘,I am like the hdmi cable, | O295: https://m.media-amazon.com/images/I/41+BBk2fGcL._SX342_SY445_.jpg | P295: https://www.amazon.in/Tuarso-High-Speed-Compatible-Television-Projectors/dp/B0BBMGLQDW/ref=sr_1_457?qid=1672909147&s=electronics&sr=1-457
A296: B01LONQBDG | B296: AmazonBasics USB Type-C to Micro-B 2.0 Cable - 6 Inches (15.2 Centimeters) - White | C296: Computers&Accessories|Accessories&Peripherals|Cables&Accessories|Cables|USBCables | D296: â‚¹349 | E296: â‚¹899 | F296: 0.61 | G296: 4.1 | H296: 14896 | I296: Connect a computer with a Type-C USB port (MacBook, Chromebook Pixel, Galaxy Note 7, etc.) to a Micro-B USB 2.0 enabled device|Offers reliable connectivity for easy charging or syncing of a tablet, smartphone, digital camera, or legacy USB peripheral device with Micro USB|Reversible design - easily insert the Type-C connector into any Type-C enabled device (does not matter which side is up)|Type-C port is half the width and one-third the height of a standard USB-A connector (slightly larger compared to Lightning or Micro-USB ports)|Up to 480 Mbps data transfer speed; power output up to 5V, 3 Amp|Certified by USB-IF to be compliant with USB 2.0 Standard|1 year limited warranty | J296: AH42ECAG6LPCU22T5BYN5OXQO74A,AEW6XI52IO3H37U4WJ7TT4MQUIQQ,AGGWS4PPWKSNOVP2LLYNQK2Q7NIA,AG4GACSXM3RJ2UR3NTYNNR4YSHYA,AF7MSVVI52V27OGZ3FTE62QFWNBQ,AHQTTEDMJWGPWIEVA6T6SN2VOJ2Q,AHI3ZFOPJRASPDNKTIADQFUDLCJA,AHLHAY6IT22ZQX7BOBY6TV2PHC5A | K296: SOURAV DAS,GISHU,Bikkee Bakchi,David Gomes,prasanth,CK,Akhilesh Singh,Khushi | L296: RKU0YNFBI9H6U,R1L56U9MGEY65D,R1RTAR9ZHEKJKA,RZ9F1LMTYQSA5,RQ6JZDYGL266A,RU423VYROXUDD,R2SX0KB6M50PZU,RWXV1G9ORG22P | M296: Very good.,Good one. Worth Buy.,Wonderful,Amazon USB C to Micro USB : It works,Good,Laptop with only USB C ports? Buy this cable.,A must buy accessory for all MacBook M1 owners,Good quality usb c to usb b adapter cable 8 inch | N296: Go for it with out second thought.,It works well in my New Kia Carens Car. Excellent product my daughter enjoys charging her Mobile sitting in Second row ðŸ‘ðŸ‘ŒðŸŒ¹ðŸ™,Value for money,You can easily transfer files between two android phones, one with micro USB port and the other with USB C.You can also charge your phone, it supports 5V,3A fast charging (upto 15W)The product didn't look new to me since it had yellow stains on it..and little dirty at the two connector ends. Well, it's working as it should so that's that.It's functional and serving the purpose that I got it for.AmazonBasics products are generally good. Have used quite a few of them, mostly cables and they are durable.Hope this helps.,Good product,If you are a MacBook 2016 user, you only have USB C ports and have to carry dongles to manage cables. This little cable makes life easy. It is reasonably high quality, not too long (around 6 inches) and can be used to connect all your micro USB devices without an additional dongle - think phones, power banks, wifi dongles, etc. It has proved to be a lifesaver many times!,Connects an android device to faster versions of new generation laptops/PC/MacBooks USB c / thunderbolt ports. Quality of cable is similar to apple original cable, ports are perfect fit in any port. Data transfer speed is amazing , a must buy for all MacBook m1 owners.,Very good quality and finish. The cable could have been thicker. However solves the purpose of connecting your device to external source. I am using this small adapter cable to connect my note 8 (which has usb c port) to my external Dac Chord mojo( has micro usb port) to listen to my hd resolution music files. Now I dont need to connect a otg adapter along with a usb a to usb b cable. | O296: https://m.media-amazon.com/images/W/WEBP_402378-T1/images/I/31bCliyezAL._SX300_SY300_QL70_FMwebp_.jpg | P296: https://www.amazon.in/AmazonBasics-USB-Type-C-Micro-B-Cable/dp/B01LONQBDG/ref=sr_1_458?qid=1672909147&s=electronics&sr=1-458
... A325: B08FD2VSD9 | B325: TCL 108 cm (43 inches) 4K Ultra HD Certified Android Smart LED TV 43P615 (Black) | C325: Electronics|HomeTheater,TV&Video|Televisions|SmartTelevisions | D325: â‚¹24,990 | E325: â‚¹51,990 | F325: 0.52 | G325: 4.2 | H325: 2951 | I325: Resolution: 4K Ultra HD (3860 x 2160) | Refresh Rate: 60 Hertz|Connectivity : 3 HDMI ports to connect set top box, Blue Ray players | 1 USB ports to connect hard drives and other USB devices|Sound: 24 Watts Output | Dolby Audio Power Speakers | Surround Virtualizer|Smart TV Features :Built-In Wifi | Prime video |4K Android TV+HDR 10 |AI-Google Assistant | Certified Android P| Screen Cast+T-cast |2GB RAM - 16GB ROM |5000+ Apps YouTube, Netflix|Display : A+ Grade Panel | UHD | HDR 10 | Slim Design|Warranty Information: 2 year comprehensive warranty provided by the manufacturer from date of purchase|Installation: For Installation, Wall Mounting, Demo Of This Product Once Delivered, Directly Contact Brand Support (Visit Brand website for Toll free numebrs) and Provide Product's Model Name And Seller's Details Mentioned On Your Invoice. The Service Center Will Allot You A Convenient Slot For The Service | J325: AGJ42BXEHWTZHDEWDT6WH6PRY62A,AG2VO7W4S2AZ47V6O75TD7YVUE3A,AGT2DMEHAZSUBARHBTHUFBCJYBPA,AETJUR555HOF4TNUIRWFWKUDO72A,AFZ4C7KMK5UYX5GM55VQD4JRCWUA,AFEGEMHIRS3I5YMTIK7J6PLAAUXA,AFX2XYBWOEXU7XMUUHDSBSBS7UUQ,AH4ICLSEN7RPFV3ZNYHOPGP3CRHQ | K325: ESAMPALLI ANUDEEP,Pooja Purohit,GAURAV SINGH,Rajiv Abhyankar,THIRU,Akshay rajendra kothawade,KB raju,Venudevishetti | L325: R369A5WFHNY685,RU7ADO0K3THNI,R2C24XAHB09570,RF6FTZ2BMK3U7,R1BKYQ1GKAGGUM,R2JI0LCLSDDWMB,R2GFGRPUJPI039,R1QBBG7QM57OF7 | M325: Best one,Nice product,Nice Purchase,A nice TV,Good quality...i have a trust on TCL,Best survice,Good,value for money | N325: Best but slow response from tv,Product is good,https://m.media-amazon.com/images/I/71Knz9n24GL._SY88.jpg,Value for money,Super quality....go with TCL,,Best price,à°šà°¾à°²à°¾ à°¬à°¾à°—à±à°‚à°¦à°¿ à°•à°¾à°¨à±€ à°¯à±à°¾à°¸à± à°¬à°¿ à°ªà±‹à°°à±à°Ÿà±à°¸à± à°²à±‹à°ªà°² à°•à°¾à°•à±à°‚à°¡à°¾ à°¬à°¯à°Ÿà°¿à°•à°¿ à°‡à°¸à±à°¤à±‡ à°¬à°¾à°—à±à°‚à°Ÿà±à°‚à°¦à°¿ à°®à°°à°¿à°¯à± à°—à±à°¾à°—à±à°²à± à°•à±à°°à±‹à°®à± à°‡à°¨à± à°¬à±à°²à±à°Ÿà± à°—à°¾ à°‡à°¸à±à°¤à±‡ à°¬à°¾à°—à±à°‚à°Ÿà±à°‚à°¦à°¿ | O325: https://m.media-amazon.com/images/I/51UuhCYmBnL._SY300_SX300_QL70_FMwebp_.jpg | P325: https://www.amazon.in/TCL-inches-Certified-Android-43P615/dp/B08FD2VSD9/ref=sr_1_490?qid=1672909149&s=electronics&sr=1-490
A326: B0BQRJ3C47 | B326: REDTECH USB-C to Lightning Cable 3.3FT, [Apple MFi Certified] Lightning to Type C Fast Charging Cord Compatible with iPhone 14/13/13 pro/Max/12/11/X/XS/XR/8, Supports Power Delivery - White | C326: Computers&Accessories|Accessories&Peripherals|Cables&Accessories|Cables|USBCables | D326: â‚¹249 | E326: â‚¹999 | F326: 0.75 | G326: 5 | I326: ðŸ’Ž[The Fastest Charge] - This iPhone USB C cable supports PD 3.0 fast charging, up to 20W with USB-C Power Delivery adapters such as 18W, 20W, 29W, 30W, 61W, or 87W. Charge your iPhone from 0% to 50% in just 25 mins, and data transfer speeds up to 480Mbps (1200 songs synced per minute)|ðŸ’Ž[Amazing Durability] - With top-rated material and coated with premium TPE, Syncwire Apple USB C cable has exceptional durability to be bent at 90 degrees for 15000+ times and the connector is capable of holding up to 20kg of weight without falling off.|ðŸ’Ž[Perfect Compatibility] - Syncwire Type C to lightning cable supports PD Fast Charge 3A (max) for iPhone 14, iPhone 14 Pro, iPhone 14 Pro Max, iPhone 13 mini, iPhone 13 pro max, iPhone 13, iPhone 12 Pro, iPhone 12 Pro max, iPhone 11, iPhone 11 Pro, iPhone 11 Pro Max, iPhone 8, iPhone 8 Plus, iPhone X, iPhone XS, iPhone XR, iPhone XS Max, iPad 8, iPad Pro (10.5-inch), iPad Pro (12.9-inch) 1st generation, iPad Pro (12.9-inch) 2nd generation.|Apple MFi Certified - Lightning cable ensure 100% compatibility with iPhone 14, 13, 13 Pro, 13 Pro Max, 13 Mini, 12, 12 Mini, 12 Pro, 12 Pro Max, SE 2020, iPhone 11, 11 Pro, 11 Pro Max, XR , Xs , Xs Max, X, 8, 8 plus, and iPad|20W Fast Charging Cable: USB C to lightning cable supports safe high-speed charging and fast data transfer,working better and quick charge your devices.(Note:You need to use 20W or above USB-C power adapter to achieve power delivery fast charge.) | J326: AGJC5O5H5BBXWUV7WRIEIOOR3TVQ | K326: Abdul Gafur | L326: RQXD5SAMMPC6L | M326: Awesome Product | N326: Quick delivery.Awesome ProductPacking was goodJust opened the productExcited to you it | O326: https://m.media-amazon.com/images/I/31-q0xhaTAL._SY445_SX342_QL70_FMwebp_.jpg | P326: https://www.amazon.in/REDTECH-Lightning-Certified-Charging-Compatible/dp/B0BQRJ3C47/ref=sr_1_491?qid=1672909149&s=electronics&sr=1-491
A327: B095JPKPH3 | B327: OnePlus 163.8 cm (65 inches) U Series 4K LED Smart Android TV 65U1S (Black) | C327: Electronics|HomeTheater,TV&Video|Televisions|SmartTelevisions | D327: â‚¹61,999 | E327: â‚¹69,999 | F327: 0.11 | G327: 4.1 | H327: 6753 | I327: Resolution: 4K Ultra HD (3840x2160) | Refresh Rate : 60 Hertz | 178 Degree wide viewing angle|Connectivity: 3 HDMI ports (HDMI 2.1 Compatible, HDMI 1 supports eARC) to connect set top box, Blu Ray players, gaming console | 2 USB ports to connect hard drives and other USB devices|Sound : 30 Watts Output | Co-tuned with Dynaudio | Dolby Audio|Smart TV Features : Android TV 10 ï½œHands-free voice control with Speak Now | Google Assistant | OnePlus Connect 2.0 | OxygenPlay 2.0 | Data Saver Plus | Kids Mode | Game Mode, Dimension (Without Stand) - 1.448m*7.88cm*83.8cm|Display : 1 billion colors | Gamma Engine | HDR10+ certified, HDR10, HLG | MEMC | Bezel-less design | 95.3% Screen to Body Ratio|Warranty Information: 1 year comprehensive warranty and additional 1 year on panel provided by the manufacturer from date of purchase|Installation: This TV comes with a wall mount inside the box. Installation/Wall mounting/demo will be arranged by Amazon Home Services. For any other information, please contact Amazon customer support | J327: AG3QTVXT2ODRVKOQJJRDV5KA2F2A,AGEYM57JOHPNX77ZYVSXPTX4FVNA,AHH557DUFIPFPRKDZ3K76U2DJ35Q,AE5WEK33Q53BHDQAPWRPVEN5OPZA,AGFDV2VE2PFK2W7FQZXLEPHK2BAA,AFOOUANHTKWSTZRG3HSE3TR7L5CQ,AEV7X32J6CUVHXXRZJ7EI7XSXYVA,AG7MREPON3XAAGY4WT4YGA7DZWCA | K327: Rashmi,Raghvendra,Hari Prasad P,Vishnu singh,Tarun Kumar Sharma,Dharmendra,K j suresh,Mahore.lakhan | L327: R2PF9QV9JEQO9K,R2NEN86P63G4ES,R302B7X6H0GIC0,R3H9O8F9LUY5N9,R1RGSA8QU78640,R2B3DRF8V2A9QI,R1KF9HPUVJTM0I,R3OCQ19TZWHSN5 | M327: Almost Perfect!,Review After using 1month,Nice tv,Panel and video quality,Good Product,Worth for money,Nice,Good | N327: Update after 9 months of use:1. The TV is still going strong - all the good points mentioned in the original review below are still true and very happy with the TV.It's as if OnePlus have been listening to their customers! After recent firmware updates, the issues I had mentioned have almost disappeared.1. We can now arrange and move apps (YouTube, Netflix) as per our wish on the home screen itself. I am finally able to put YouTube first as it is the most used app for my toddler.2. There is no more wifi disconnect issue noted earlier.3. Prime Video still shows errors sometimes. Though I think that's an issue with the app and not the TV.Strongly recommend this TV!Original Review:I took a leap of faith in purchasing this TV as there were mixed reviews for it. However, after using it for 2 months, the following are my observations:Good:1. The picture quality is fantastic. There is no lag while watching/forwarding 4k/8k videos.2. I saw a youtube review which said its brightness was low compared to other models - The brightness is more than you would ever need from a TV. I have never needed to run it on full brightness till now, up to 40 works for me. For my toddler to watch rhymes, I set brightness to 0, and even then it is more than needed.3. There were a few reviews that said the sound quality was average and you need a soundbar. I disagree - I have watched movies with up to 50 sound and that is good enough for a 1000 sqft hall.4. Voice command - it is quite accurate and I am able to change nursery rhymes for my toddler while working in the kitchen which is around 15 - 20 feet away.5. Being able to control the TV from app is also a very useful feature - no need to look for remote. Being able to cast from the app also helps a lot. It would be even better if everything on phone (not just pictures and videos) could be cast using the appNot so good:1. If the TV goes to sleep/screensaver for more than 10 minutes,a. it often gets disconnected from wifi - have to restart it againb. prime video fails to resume - displays error - and have to restart the TV againc. On the home screen, you cannot rearrange apps to have your preferred apps first. You can do it in apps window which is useless as you need to navigate to it first - easier to navigate to your preferred app in the home screen itself.,Only Cons till now got, fast moving object looks blurr, which was known before buying by other user review, but i got this tv in 32 k,Ao over all satishfied,Only minus that too critical is the installation service provider.The product is to installed by v care installation services provider.The installation service provider is a total waste and not responded properly.Actual date of installation was on 21.02.22 but was only done by the service provider on 27.10.22.The executive who attended the installation is a total waste person and don't know how to behave to the customer.He behaved very rudely.The installation service provider is a total damage and waste. Not at all worth.,,Awesome quality of pictures and some issues with smart features like in app installation and in connection from smart phone only audio player in work properly but video not show in tv.,Dolby atom 4 k video etc,Good,Good | O327: https://m.media-amazon.com/images/I/41sSPp4pkYL._SY300_SX300_QL70_FMwebp_.jpg | P327: https://www.amazon.in/OnePlus-163-8-inches-Android-65U1S/dp/B095JPKPH3/ref=sr_1_492?qid=1672909149&s=electronics&sr=1-492
A328: B087JWLZ2K | B328: AmazonBasics 108 cm (43 inches) 4K Ultra HD Smart LED Fire TV AB43U20PS (Black) | C328: Electronics|HomeTheater,TV&Video|Televisions|SmartTelevisions | D328: â‚¹24,499 | E328: â‚¹50,000 | F328: 0.51 | G328: 3.9 | H328: 3518 | I328: Resolution: 4K Ultra HD (3840 x 2160) | Refresh Rate: 60 hertz | 178Â° wide viewing angle|Connectivity: 3 HDMI 2.0 ports to connect set top box, Blu Ray players, gaming console | 1 USB 3.0 and 1 USB 2.0 ports to connect hard drives and other USB devices | IR Port to control connected devices like Soundbars, Receivers and Set top boxes|Sound output: Inbuilt 20 Watts Powerful Speakers | Dolby Atmos|Smart TV Features: With built-in Fire TV | Built in Alexa and Alexa voice controls | DTH Set-Top Box Integration to switch between DTH TV Channels and OTT apps from home screen | Supported Apps: Prime Video | Netflix | Disney + Hotstar | YouTube | 5000+ apps from Fire OS Store | Display Mirroring | 1.95GHz Quad core processor | 1.5GB RAM/DDR | 8GB Flash Memory|Display: A+ Grade LED panel | Dolby vision | HDR 10 + HLG | Amlogic 9th Generation Imaging Engine | Ultra bright screen | Advance picture processing | Anti-aliasing | Dynamic contrast | Dynamic backlight|Warranty Information: 1 Year Comprehensive Warranty on product and 1 Year additional warranty on panel for malfunction arising from manufacturing defects. 1-click Warranty support, on Amazon for malfunction arising from manufacturing defects. Get Brand Authorized service, genuine parts and a paperless warranty claim experience through your Amazon account. Hassle free process with complete visibility to every step of your warranty claim For claiming warranty, A) Go to Your orders section, B) Select the product, C) Click on Get product support and D) Schedule an appointment.|Installation/Wall mounting/demo will be arranged by Amazon Home Services. For warranty and device related issues, go to Your Orders on Amazon.in or Amazon shopping app > Locate your TV order > Select â€˜Get Product Supportâ€™ and schedule a service. For any other information, please contact Amazon customer support | J328: AEY5PQYPSQDGMJCPRPSLJKFM6ELA,AHNQOEGE6ZB5DB2BZKMI3GXO2YEA | K328: Shankar Raman,Johnnie Sinclair | L328: R24M24UKIB5KN3,R9MTYU83EHJ96 | M328: (after nearly one year use) Value for money TV, except for the sound,Spectacular Specification, Build Quality, and Performance | N328: ,What's not to love about this all-new 55 inch Amazon Fire TV?UNBOXINGThe whole experience from delivery to commissioning was completely seamless; the packaging is strong and very sturdy, using a lot of bio-degradable materials; the unboxing was a delight, and fixing the (included) wall mount was a piece of cake.AMAZON INTEGRATIONNow comes the Amazon Magic! Switch on the TV, and it already knew me, and my Amazon Prime Account. After a brief online security check, all my content and apps automatically appeared on-screen, and setup was done!OPTICAL AUDIO OUTI'm using a JBL soundbar with sub-woofer which are connected to my 55 inch Amazon Fire TV using an optical cable (not supplied), and by simply changing settings on the TV my audio system automatically switches on and off with the TV, and the supplied TV Remote has volume controls for my cinema sound. The sound reproduction is First Class. I can't comment on the built-in TV Speakers, because I haven't used them.PICTURE QUALITYThere are lots of presets for the screen, including Natural, Cinema, Gaming, etc., and you can also set a customised screen to your own liking. The picture quality is excellent, every bit as good as my other TV from a famous brand that costs 4X the price of my 55 inch Amazon Fire TV. I'm impressed!HDMI & CONNECTIVITYI'm only using HDMI1 because all my content is streamed and I have been using an Amazon Firestick, and Google Chromecast. The Chromecast is plugged into HDMI1, and the TV automatically switches to it when you want to use it. However, I don't think I'll be using the Chromecast much, because Fire TV is so good, and has an amazing remote control.I'm also using a 2TB External hard drive plugged into the fast USB. Playing movies, even in HD, is a perfect experience with no lag or juddering.Access to the sockets on the wall-mounted TV is OK if you have small arms, and although I'm only using HDMI1, Optical Audio Out and one USB, there is plenty of connectivity for other equipment.JUST ONE THING...This version of FireTV only allows Alexa to speak 2 languages, viz. English (Indian), or Hindi.My Amazon Firestick, Echo Show 8, Echo Show 5, Echo, and Echo Dot all have settings for English UK, Aus, USA, etc, Spanish, French, German, and many other languages. I really would like to use Alexa on my 55 inch Amazon Fire TV in my native language - it makes it easier for Alexa to understand me, and easier for me to understand Alexa.I hope that this will come in a software update.CONCLUSIONI think that this 55 inch Amazon Fire TV is amazing, and I would recommend it without hesitation. | O328: https://m.media-amazon.com/images/W/WEBP_402378-T1/images/I/51z60rNcKSL._SY300_SX300_QL70_FMwebp_.jpg | P328: https://www.amazon.in/AmazonBasics-108cm-inch-Ultra-Smart/dp/B087JWLZ2K/ref=sr_1_493?qid=1672909149&s=electronics&sr=1-493
A329: B09DSXK8JX | B329: Kodak 80 cm (32 inches) HD Ready Certified Android Smart LED TV 32HDX7XPROBL (Black) | C329: Electronics|HomeTheater,TV&Video|Televisions|SmartTelevisions | D329: â‚¹10,499 | E329: â‚¹19,499 | F329: 0.46 | G329: 4.2 | H329: 1510 | I329: Resolution : HD Ready (1366x768) resolution | Refresh Rate : 60 Hertz | 178 Degree wide viewing angle|Connectivity: 3 HDMI ports to connect set top box, Blu-ray speakers or a gaming console | 2 USB ports to connect hard drives or other USB devices|Sound: 40 Watts Output | Powerful Speakers with Crystal clear Audio|Smart TV Features : Google Voice Assistance | Android 9.0 Pie | Smart Remote | Bezel-Less Design | Supported Applications : Sony Liv, Disney+Hotstar, Zee5, Youtube and more | Display Mirroring for compatible devices|Display : Durable A+ Grade DLED panel | Ultra bright screen for flawless picture quality even in bright rooms|Warranty Information: 1 Year warranty provided by Kodak TV from date of purchase|Easy Returns: This product is eligible for replacement within 10 days of delivery in case of any product defects, damage or features not matching the description | J329: AH7535IQDY5KVV2I6ASNOZJC4KAA,AHP5TFGAPXAL6K7M7LXIZUC2QMAQ,AGE4EHGVL2UE25LAURR7KYET2ZEQ,AHDAZJHREN222RBVCN5TTXZFFUKQ,AFHMLCTD3ZAK65UCZUDGPLMVRE5Q,AEHBFH46VYKCD4FWZ3AQ5GFSSILQ,AF7NGHQSFHIKMD3KTJGPRZ2SC3GA,AHX44XKUX5DHSXDUZBLZCC5SDUOQ | K329: Mahesh savale,Sameer Mandal,Sree ram vasanthada,Pulak ray,Abhishek Chauhan,Bsharat Ali,vipin gupta,Bunty s | L329: R1UFECRZY2H7ZR,R2L3OQHBC45T2X,R2IX8LIBU6MKPB,R35OUWDVRQF8R5,RHRVKXM6JJBX7,R1O89JBSE4EPL4,R364RHY5PGIWWH,R1EL7KUX3CVDVU | M329: Kodak tv,Kodak tv,Kodak tv,Very less features to control or configure picture, sound or other key features through remote.,Excellent,Kodak 32inh,Kodak tv,Good | N329: V nice and good,Good,Good,Very non responsive company,after several reminder to company and Amazon they don't bother to install the TV as committed since last 8 daysLet's see how they will respond in case of warranty or service requirement in future.,Excellent,Picture quality moderateSound quality moderateRemote access moderateAs per price product is Good.Product is Worth to buy .,Good tv with good service,Good | O329: https://m.media-amazon.com/images/W/WEBP_402378-T2/images/I/41xL87ElgjL._SY300_SX300_QL70_FMwebp_.jpg | P329: https://www.amazon.in/Kodak-inches-Certified-Android-32HDX7XPROBL/dp/B09DSXK8JX/ref=sr_1_494?qid=1672909149&s=electronics&sr=1-494
A330: B08V9C4B1J | B330: Synqe Type C to Type C Short Fast Charging 60W Cable Compatible with Samsung Galaxy Z Fold3 5G, Z Flip3 5G, S22 5G, S22 Ultra, S21, S20, S20FE, A52, A73, A53 (0.25M, Black) | C330: Computers&Accessories|Accessories&Peripherals|Cables&Accessories|Cables|USBCables | D330: â‚¹349 | E330: â‚¹999 | F330: 0.65 | G330: 4.3 | H330: 838 | I330: ã€NOTE before purchaseã€‘:This is a USB-C to USB-C cable, which means it has the same USB C plug on both ends, please be aware that this is not a USB-C to USB-A cable. Besides, you may need a USB C wall charger to charge your device.|ã€NYLON BRAIDED, SMALL SIZEã€‘: With a tested 20000+ bend lifespan, Synqe USB C charging cable with heavy duty braided and strong metal connections is far more durable. Short size makes it comfortable to use with Power Banks and Android Auto.|ã€3A/60W Rapid Chargingã€‘ï¼šBuilt-in smart chip, which makes this Type C to Type C PD cable strong enough to support max 3A current 60W power throughput, as well as support fast charging for more phone and power banks likeSamsung Galaxy Note 10 S20 Ultra S21,Realme Power Bank and more Type C devices. You need a USB C wall charger / Power Bank to charge your device and we recommend using the original wall charger.|ã€60W High Speed Chargingã€‘: Output power up to 20V 3A, which is ensured by high-speed safe charging, and the USB 2.0 supports data transfer speed can reach 40~60MB/S (480Mbps). NOTE: This product DO NOT support video output and monitor connection.|ã€12-months warrantyã€‘: 12 months warranty and friendly customer services, ensures the long-time enjoyment of your purchase. If you meet any question or problem, please don't hesitate to connect with us. | J330: AFZT774FU3LOJGEW7JSAXOD24OBQ,AGSEMC5UI32EZO6GAW4KKT5OVMOQ,AH53RLKODGV2UFIZLUG6BMHDDZNA,AFJJ4SJN2GXTYC7637ZAKSONPJWQ,AFFCEWUI7XY45CEM76XENJ2RUO2A,AHFTNP5NESJTIHQKP47SJV73TNUA,AH352HMRF7DESCSOUBMHUVJQZM7A,AEVN7RMFICHOZR6CD2KNIV7LW4IQ | K330: Uzair Drabu,Ravindra Sistu,Pranav Dhumal,Amresh singh,Palash Gandhi,Verified Customer,Anudeepika Ankam,karan | L330: RYIE3APCBZO0M,RVVUYDXJQ5FWH,R2OD8G07SP3ATQ,RV4T2P1TSYP7C,RTUH4QIEPCZI2,R176EGN5WFKYMF,R2NF8CY7JSGPIJ,R1ZHN7T42QYEMK | M330: Used for 10 months,Quality is good,Good Aftersale Service,Super fast charging suppurt,Superb Quality and value for money,Good small cable,Nice,Highly recommended | N330: Used this cable for 10 months, very sturdy, really like the cable length.,Good,Repalcement in warrenty works,I ordered this for my S21 ultra as and it is working same as my original cable... It is charging very fast with my 25W charger.,I've been using this cable since a year now and never faced a single issue till date. Quality of the cable is excellent and is very durable. It is also a value for money product. Highly recommended,Good small cable. Yet to be tested though.,Good one,This is good and long cable easy to use | O330: https://m.media-amazon.com/images/I/31FmMK7a9PL._SY445_SX342_QL70_FMwebp_.jpg | P330: https://www.amazon.in/Synqe-Braided-Charging-Compatible-Samsung/dp/B08V9C4B1J/ref=sr_1_495?qid=1672909149&s=electronics&sr=1-495
A331: B08PKBMJKS | B331: Airtel DigitalTV HD Setup Box Remote | C331: Electronics|HomeTheater,TV&Video|Accessories|RemoteControls | D331: â‚¹197 | E331: â‚¹499 | F331: 0.61 | G331: 3.8 | H331: 136 | I331: Note : please match the image with your existing remote before placing the order|Remote must be Exactly Same (Function to Function) as per your Old Remote (PLEASE MATCH PROPERLY BEFORE ORDERING)|Send Old Remote Picture at +91-9016382240 (WhatsApp), & Ask for Link to Order Compatible Remote|Exactly Same Remote will Only Work, NO BACKLIGHT IN REMOTE DISPLAY|Compatible with Airtel DTH Set Top Box Remote (Pairing Required to Sync TV Functions) | J331: AGL3JTQ3ZE2OROHL44I2WVDP2Y2A,AGQ77RQV2RP2RV3V3ILVPKJZO4PA,AFU5YK2ZGL26FL7JSOUCS4NJIA2Q,AGJCHC5GBZXUFZIJC3YHRLDBF3OA,AEAPKDGJ23GWBHSLTG3OQ4ZD72SA,AHI75BH7J42XPZ3GSVJINRNDIQGQ,AHF5BKRYGMVNIVA4ZZEYP3O4MTWQ,AHUQL2OJQVXUN6KU3XE4NNXDYWXQ | K331: Sony Soniyal,Anshul Gupta,Ajit paragond,s.neelakandan,Amazon Customer,Sourish Saha,Amareswara rao,Sandeep chauhan | L331: R2ZBBYSOYN3KBL,R2DMLU5SLI59HR,R2TALY28IA40HU,R3I8OBYQHMK5AG,R2LNUR3W2TOTL,R3W1MUYN039NGZ,RH9I43YOGMCU5,R2T1VOM1S6TMET | M331: Working fine but cheap quality,Original but small,à²¨à³€à²µà³ à²•à²³à³à²¹à²¿à²¸à²¿à²¦ à²µà²¸à³à²¤à³ à²¸à²°à²¿à²¯à²¾à²—à²¿ à²•à³†à²²à²¸ à²®à²¾à²¡à³à²¤à³à²¤à²¿à²²,Sturdy,Good,Works perfectly with Airtel HD set up box,Item is value for money.,,On Off button doesnâ€™t work. | N331: Working fine with Airtel DTH but the quality is cheap, it's not strong,Earlier airtel tv remotes had larger keys which were easy to navigate. Wish airtel could make that happen.,à²¨à³€à²µà³ à²•à²³à²¿à²¸à²¿à²°à³à²µ à²µà²¸à³à²¤à³ à²¸à²°à²¿à²¯à²¾à²—à²¿ à²•à³†à²²à²¸ à²®à²¾à²¡à³à²¤à³à²¤à²¿à²² à²ˆà²—à²¾à²—à²²à³‡ à²¨à²¾à²µà³ à²’à²‚à²¦à³ à²¬à²¾à²°à²¿ à²µà²¾à²ªà²¸à²¾à²¤à²¿ à²®à²¾à²¡à²¿ à²¦à²°à³‚ à²•à³‚à²¡à²¾ à²¨à³€à²µà³ à²•à²³à³à²¹à²¿à²¸à²¿à²¦ à²µà²¸à³à²¤à³ à²¸à²°à²¿à²¯à²¾à²—à²¿ à²•à³†à²²à²¸ à²®à²¾à²¡à³à²¤à³à²¤à²¿à²² à²†à²¦ à²•à²¾à²°à²£ à²¨à²¨à³à²¨ à²¹à²£ à²µà²¾à²ªà²¸ à²®à²¾à²¡à²¬à³‡à²•à²¾à²—à²¿ à²µà²¿à²¨à²‚à²¤à²¿,Good,Good,Works perfectly with the Airtel HD Set up box (not suitable for Airtel Xtream). Would generally be apprehensive before buying a remote online but this worked perfectly.,Genuine product.Lasts long time and it depends how u handle it.Frequent dropping leads to shorter life as it is a breakable product.Worth buying.,On Off button doesnâ€™t work. Remote doesnâ€™t work on TV. It works on Airtel setup box only. I always use 2 remotes. 1 for tv and another for setup box. Not satisfied with this remote. | O331: https://m.media-amazon.com/images/W/WEBP_402378-T1/images/I/31Lfjbfc47L._SX300_SY300_QL70_FMwebp_.jpg | P331: https://www.amazon.in/Airtel-DigitalTV-Setup-Box-Remote/dp/B08PKBMJKS/ref=sr_1_496?qid=1672909149&s=electronics&sr=1-496
A332: B0B8VQ7KDS | B332: Airtel Digital TV HD Set Top Box with FTA Pack | Unlimited Entertainment + Recording Feature + Free Standard Installation (6 Months Pack) | C332: Electronics|HomeTheater,TV&Video|SatelliteEquipment|SatelliteReceivers | D332: â‚¹1,299 | E332: â‚¹2,499 | F332: 0.48 | G332: 4.3 | H332: 301 | I332: Airtel HD Set Top Box brings theatre-like experience to your home with HD Premium Quality Video (1080i resolution) and Dolby digital plus 5.1 surround sound|Airtel D2H allows you to pause, record and play live TV so that you never miss your favourites as you can watch them later as per your convenience|Customise one of the Cheapest DTH plans with the freedom to choose from 550+ SD & HD channels|Enjoy free delivery and hassle-free installation of your DTH Set Top Box. Any other accessory which is not a part of the standard installation will be charged separately|Included are only Basic Free to Air Channels, you can add other channels by subscribing to them and paying an additional respective amount. | J332: AGQYZLWPXBTZCFFSJ7N4E5MU6FQA,AGXCSQZYYIGXCSMQD7HKL67TZBRQ,AHBSBZBVPHQ3DNFSVUEISWFKZWEQ,AFZLNTIDI2YFJVCQS4EXCTGWVWEQ,AFCDITQYYSHB5DVHMFMO6M3PV3NA,AEZDOXSJW5A65GIYXQSDYBWNVTCQ,AGJZ4GRH4YOMZSQ7JWZDVPBSW7RA,AHQSA6UQCAE7UBCWEVA4FSRIKTNA | K332: Amazon Customer,Chhaya Singh,Ankit bisen,Amazon Customer,Rajesh Raj,Krishna upadhyay,Ajay p.,lusang k | L332: R1SLOPXHKI14S6,R1OXLNAD6QN3PK,R4RAOBEKJMT1E,R2DJOU9710152I,R3FXVCBQCGNPLW,R12LALSYGQEMTT,R2XY6WL3YCCBBU,R2VRNRRSOHXHYW | M332: Good ptoduct,Overall good product,, and good choice,, â˜ºï¸,Cable is short,Good,All channel view nice,Very fast and good service,Ok,The product was ðŸ™Œ | N332: Good product,I like it's picture quality and recharge plan,,,,,Cable is very short, ground floor ke liye bhi Chhota tha,Good product problem in channel selecting,Like picture quality,I m impressed, service is very good,All channels not available,https://m.media-amazon.com/images/I/71j79HDIG5L._SY88.jpg | O332: https://m.media-amazon.com/images/I/41Jy61seJKL._SX300_SY300_QL70_FMwebp_.jpg | P332: https://www.amazon.in/Airtel-Pack-Entertainment-Installation-Months/dp/B0B8VQ7KDS/ref=sr_1_497?qid=1672909149&s=electronics&sr=1-497
A333: B086JTMRYL | B333: ESR USB C to Lightning Cable, 10 ft (3 m), MFi-Certified, Braided Nylon Power Delivery Fast Charging for iPhone 14/14 Plus/14 Pro/14 Pro Max, iPhone 13/12/11/X/8 Series, Use with Type-C Chargers, Black | C333: Computers&Accessories|Accessories&Peripherals|Cables&Accessories|Cables|USBCables | D333: â‚¹1,519 | E333: â‚¹1,899 | F333: 0.2 | G333: 4.4 | H333: 19763 | I333: MFi Certified: this USB-C to Lightning cable is certified MFM (Made for iPhone) by Apple to ensure safe, reliable, and fast charging and syncing|PD Fast Charging: charge your iPhone 13 up to 50% in 30 minutes when used with USB-C PD charger; fast charging compatible with iPhone 14/14 Pro/14 Pro Max/14 Plus, iPhone 13/12/11/X/8 series, iPhone SE (2020), iPad 8/Pro 12.9" (1st and 2nd Gen)/Pro 10.5"|Stable File Transfer: connect your Lightning-enabled iPhone, iPad, or iPod to your USB-C ready Mac, iMac, or iPad Pro and transfer files rat blisteringly fast speeds without worrying about the dreaded â€œAccessory may not be supportedâ€ alert|Built to Last: the durable braided nylon casing ensures fewer tangles and more tensile strength than Appleâ€™s official cables; aluminum cased plug heads ensure your cable wonâ€™t get damaged when plugging in and out|Compatibility: this USB-C to Lighting iPhone cable supports fast charging for iPhone 14/13/12/11/X/8/7/6 series, iPhone SE 3/2, iPad Pro 12.9 (1st and 2nd Gen), iPad 8th Gen, iPad Pro 10.5"; 18W or above USB-C PD adapter required | J333: AHOYUSKWQFXDLOTRT43FCSHP3WIA,AGUVNZPD7JF3AK422LRYK6R5GOJA,AGVJMKJLZZGBV7VOYJGQ2HZKELXQ,AH7RKVVU3Y2ZGA4WEW5RXKMQWDLA,AGSODW32ZSTEY4AMCL24COIXUV5A,AFK4V6NRIQGVYQCCBMQCSLRG2ZXQ,AEK45RYTIY4GBPAVTYBHIA6OGYDQ,AHVNGU6PZRRCJEDDJMZOTR5K5K4A | K333: Mohammed Auquib Hussain A,Yashwantrao chavan,jesna j.,Saurabh jaybhaye,Yash Patodi,Maaz Shaikh,Amazon Customer,Suraj S. | L333: R1NBVCQUPQGZSG,R1AYTJ3HGDXBPB,R1SZXE4S0X94AV,R18V2LFU0A6Z1Z,REEEYL5KDQ81L,R1648XOMK16YKC,R30X514IQ3NWX4,R3UV2ZJIR07U21 | M333: Go for it,Fast charging,Good product,Good,So Far So Good,Quality is good ðŸ‘ you can go for it â™¥ï¸,Excellent Product,Yup good in all over | N333: Everything is great go for it after all itâ€™s esr common,Length is good and charge fast. Need to maintain well cause of itâ€™s length.,Fast charging.,Value for money,Its been more than a month since I am using it and it is working as expected.,Nice product go for it,Excellent product with a good sturdiness. The product quality is worth the money spent., | O333: https://m.media-amazon.com/images/I/41I2mS67DyL._SY300_SX300_QL70_FMwebp_.jpg | P333: https://www.amazon.in/ESR-Lightning-MFi-Certified-Delivery-Charging/dp/B086JTMRYL/ref=sr_1_498?qid=1672909149&s=electronics&sr=1-498
A334: B09RWQ7YR6 | B334: MI 138.8 cm (55 inches) 5X Series 4K Ultra HD LED Smart Android TV L55M6-ES (Grey) | C334: Electronics|HomeTheater,TV&Video|Televisions|SmartTelevisions | D334: â‚¹46,999 | E334: â‚¹69,999 | F334: 0.33 | G334: 4.3 | H334: 21252 | I334: Note : The brands, Mi and Xiaomi, are part of the same multinational conglomerate|Resolution : 4K Ultra HD (3840 x 2160) Resolution | Refresh Rate : 60 Hertz|Connectivity: Dual Band Wi-Fi | 3 HDMI ports to connect latest gaming consoles, set top box, Blu-ray Players | 2 USB ports to connect hard drives and other USB devices | ALLM | eARC | Bluetooth 5.0 | Optical | Ethernet|Sound: 40 Watts Output | Dolby Atmos | DTS-HD|Smart TV Features : Android TV 10 | PatchWall 4 with IMDb integration | Kids Mode with Parental Lock | 300+ Free Live Channels | Universal search | Language Universe (16+ Languages) | India's Top 10 | Miracast | Supported Apps: Prime Video | Netflix | Disney + Hotstar | YouTube | Apple TV | 5000+ apps from Play Store | Quad core A55 CPU processor | Chromecast built-in | Ok Google | Far-field Mics | Auto Low Latency Mode | 2GB RAM + 16GB Storage|Display: 4K HDR | Metal Bezel-less Design | Dolby Vision | HDR10+ | HLG | Reality Flow MEMC | Vivid Picture Engine 2 | DCI-P3 94% Colour Gam|Warranty Information: 1 year comprehensive warranty on product and 1 year additional on Panel provided by the brand from the date of purchase | J334: AGTBGMKWQPUZJ2GA2XPICHD2VTKQ,AF3TVTF3FVMHGLCA2QB2GTUTCUIQ,AH52X5G5PGIEWVC5D7TPBTTVJR2A,AEA6UPUVSSMVOTGA6JN7GFG2AZ7A,AEDU5UVD5ZMYRMBTNQTU7QUFLDVQ,AF4VLR2GRW5ZRKW5QXT6IB6QVLOQ,AESB32BXL4JEWHLRLUHZEDXYSDXQ,AFYSLM4L6FC755CARUNV6FXNANLA | K334: Amazon Customer,Rampratap singh,Arjun vaidya,Apurav,MAHESH KANCHARANA,Val Coutinho,Pravin Bhati,Nalla srinivas Reddy | L334: R19JWR6NN6DMRW,R3NNMZRL819Q5I,R27MVISBFA27B0,R26UM4M5FX7MOX,R3OS23S4DLG4RW,R6CTY16XAGKZ3,R3GTDALXXTDMU4,RXYNQRMH2KD0E | M334: It's super,Value of money ðŸ’°,Display and build,Good Sound and pictures,Good product ðŸ‘,Good and smart tv for reasonable rate,Good for low budget,Good | N334: It's very good peace what I read.,Institutions free is very expensive and difficult prasasan but thanks for Amazon,My review is after 2 months of buyExcellent Mi Tv 55inchI like the its built quality.Picture quality is osm and working good no issue with display 55 inch is much big and in dark looks like theater experienceSound quality better and much loud, bass is good with 40w speakerWorking good with no issue and Android with no lag good storage with all ports with Dolby vision hdr 10No issue with pachtwallConsI face an issue with Chromecast, i think i should be solved on tv updateOther all features are amazingMust buy it ....,Good,Nice clarity good product,Good tv for reasonable rate. So far the tv is working fine and the picture quality is also excellent. Sound quality is also good but low compared to Sony or Samsung, anyways I have connected to sound bar so that does not matter me anymore. Voice recognition and commands work fine. All in all its a good tv to buy.I am only disappointed about is that i had ordered tv with 8gb internal memory but i got was 4gb. I really dont understand the logic behind it.,Good for low budget peopels,, | O334: https://m.media-amazon.com/images/W/WEBP_402378-T2/images/I/41mW+TS5WKL._SY300_SX300_.jpg | P334: https://www.amazon.in/138-8-inches-Ultra-Android-L55M6-ES/dp/B09RWQ7YR6/ref=sr_1_499?qid=1672909149&s=electronics&sr=1-499
A335: B00OFM6PEO | B335: Storite USB Extension Cable USB 3.0 Male to Female Extension Cable High Speed 5GBps Extension Cable Data Transfer for Keyboard, Mouse, Flash Drive, Hard Drive, Printer and More- 1.5M - Blue | C335: Computers&Accessories|Accessories&Peripherals|Cables&Accessories|Cables|USBCables | D335: â‚¹299 | E335: â‚¹799 | F335: 0.63 | G335: 4.3 | H335: 1902 | I335: Length: 150cm-1.5M. Higher transfer rates up to 5 Gbps|Full-duplex data transmission support for new transfer types in the future|Increased device current draw to better provide power for High power demand devices|Features shielding that provides protection against noise from electromagnetic and radio-frequency signals, keeping your signal clear with less loss of bandwidth for higher performance|USB 3.0 uses less power, but has increased power output - up to 4.8 Gbit/s. Compared with the USB 2.0 transmission speed, USB 3.0 is 10 times faster|PS: This cable does not work with camera. Please contact us before purchasing. | J335: AGHG6WZFWKAYCOJU6QMZHYDRE54A,AFWQNHRUPQTARC3F4UKWPQF4TRSA,AHU3VEDJKG6OTDUXLAHJRKFXZYFQ,AFT4RR5NOUV3SV4DAF4EMMD3U43A,AFWFSLAC7CL5SNIGOEERFGNG74SQ,AFGYFEYGHTS5QRQ6WTYBPJUADAMA,AGSY42AHUKI5KGZBZU3SAGJBWHQQ,AEIEQNRYFSUJ4WYXO4BTUHBCC5IA | K335: Manoj S.,Placeholder,Vanchinathan G,Vicky dhruw,Gandham gopi,harmeet,LAKSHMIREDDY P,Ajinkya Pathak | L335: R1NNND9Z9O7ZFX,RI4YG0LQODJ1Z,R2RJKDVMA6HJAF,R1CK70KKIQTXQY,R1MU7OXDCRE59A,R3OUTRCSE95S7U,R1H2SUFJGR1SC5,R3O0A0XNHT8365 | M335: Works perfect for connecting my Dslr to ipad & tethering. Seems like a durable cable,H,GOOD,USB,Supar,It's good,Very good cable,Okaysih | N335: Works perfect for connecting my Dslr to ipad & tethering. Seems like a durable cable.,Good,WORTH FOR MONEY, EASY TO USE,Nice easy to carry,Supar,Product is nyc.. Price is bit high,Good,Okayish | O335: https://m.media-amazon.com/images/W/WEBP_402378-T2/images/I/51R1cOolXRL._SX300_SY300_QL70_FMwebp_.jpg | P335: https://www.amazon.in/Storite%C2%AE-150cm-Female-Extension-Printers/dp/B00OFM6PEO/ref=sr_1_500?qid=1672909149&s=electronics&sr=1-500
A336: B0BF57RN3K | B336: Fire-Boltt Ninja Call Pro Plus 1.83" Smart Watch with Bluetooth Calling, AI Voice Assistance, 100 Sports Modes IP67 Rating, 240*280 Pixel High Resolution | C336: Electronics|WearableTechnology|SmartWatches | D336: â‚¹1,799 | E336: â‚¹19,999 | F336: 0.91 | G336: 4.2 | H336: 13937 | I336: Fire-Boltt is India' No 1 Wearable Watch Brand Q122 by IDC Worldwide quarterly wearable device tracker Q122.ã€Bluetooth Calling Watchã€‘- Fire-Boltt Ninja Call Pro Plus Smartwatch enables you to make and receive calls directly from your watch via the built-in speaker and microphone. This smartwatch features a dial pad, option to access recent calls & sync your phoneâ€™s contacts.|ã€1.83" HD Display Smart Watchã€‘- The 46.48mm (1.83-inch) HD display makes the display clear and true-to-life, with vivid colours ensuring smooth readability and keeping the watch as exquisite to look at as when you first lay your eyes on it.|ã€AI Voice Assistantã€‘- With built-in Voice assistant, you can simply speak to the smartwatch & get things done on your command|ã€100 Sport Modesã€‘- Track every trek you take or every football, cricket kabaddi match you play. With over 100 sports modes Fire-Boltt Ninja Call Pro Plus has you covered.|ã€Fire-Boltt Health Suiteã€‘- With advanced technology and HRS chipset the smartwatch can give out near to accurate SpO2, Heart Rate readings. This mini health device tracks your sleep to ensure glowing and fresh look each day | J336: AEC6UDCEAUIBIFHGQDQ4KR67GC4A,AHRKSUOZXKKDERRY3VZBVMMWX37Q,AH4F4OZIOIIBXGLL6IZIJAXSTDXA,AEGBGS574C35NMBICCMQLC5ODEKQ,AGM7ETOYBL3UFKCLZW36JM6POQ6A,AHM4G7MHKTEAZ7KQ6ADSZOTL5BEA,AHHYFEVKBVQB52YMNNKAZT6C75LA,AGZ54F47MOFAEMWXXR76OUBC75SQ | K336: venkatesh kg,Raghuram,YOGESH,Manan Parmar,Nikunj .R. kukadiya,Shivansh Sharma,KAPIL NIMKER,Suriya | L336: R1PKIMKR1E8X8T,R23UV7ZBIEEZD3,RYRHNVDKS5RFY,RS1V5P4B8NSAO,R1H7L32HFCGUIR,R1Y0X6TPG7EJ3V,R3UZD33WNT4AD,R2MLZRSEQB0C49 | M336: Worth the money,Good smart watch,the screen does not turn on and off on double tap, for that you have to press the button.,User friendly UI,Best Allrounder Budget SmartWatch Under 2K ðŸ”¥,This smart watch is awesome,Nice watch in budget,The step count is not that accurate but the call quality and other things are good | N336: I liked it, worth the money, light weight and comfortable at every situation.this one i got here has stable ui,no lag even,feels premium (mainly the soft strap and the cool crown button adds up much)..the main reason I bought this because it brings all the features everyone needs today with out of the box looks.If someone feels that they have a thin wrist and it wouldn't fit them,don't worry.Even i thought it wouldn't fit me coz i have a thin wrist but it was just fine.,,In this watch, the screen does not turn on and off on double tap, for that you have to press the button and the battery also takes more than 1 hour instead of 35 minutes to get fully charged. And the battery also lasts only 3-4 days, just hope that in the future, if I update the software, then the double tap option will come.,Watch is user friendly, UI is great.Calling feature is great.This watch is different from others in music playing in watch speaker.Great experience.Watchfaces option is good.We can add watchfaces as we can.In my other watch this feature is missing.Love this watch.,This Smartwatch is perfect for beginners who's buy first time smartwatch. ninja call pro plus is recently launched so it comes with latest features and specifications. Display Is top Notched and and brightness is enough for use at outdoor. Heart measure and Spo2 is well accurate all sensors are efficiently worked. Reading of data is accurate near 90 to 95% you can trust on it at emergency situations. It comes with 100 sports mods all types of activities and sports are coverd. Calling experience is also very nice, speaker and microphone is quite decent sufficient voice at indoor. But battery should be better it has require charge 1 time in day. 3D curved display give awasome visual experience. Strap quality is very soft and female also use it very smoothly. So overall it has best smartwatch under 2K Display, Calling, Sensors, Bulit quality, Battery Back-up, sports Mods, Waterproof, etc. You should definitely go for this one. Satisfied Product.ðŸ‘ðŸ”¥ðŸ‘,This watch is very good but 1 problem im using this watch from 1 week and a few days back its pixels were droping, the screen was not working properly but after restarting, it was working properly and from then i didn,t face that problem again.,Nice watch with good UI interface with calling feature. Power packed with features in very low price. If you are on tight budget and looking for caling smartwatch you should definitely go for this one.,The build quality is great.The review about this watches are as follows:Good call quality and Google assistant supportThe UI experience is very smooth except the split screen feature it's a little bit laggyThe only thing that is only bad about this product is the step accuracy I feel like its a little bit lagging back but it catches up to it after a half an hourYou can buy this product if you are on a tight budget and want calling and good UI experience you can buy this product | O336: https://m.media-amazon.com/images/I/41WCgGbvwhL._SX300_SY300_QL70_ML2_.jpg | P336: https://www.amazon.in/Fire-Boltt-Bluetooth-Calling-Assistance-Resolution/dp/B0BF57RN3K/ref=sr_1_1?qid=1672895748&s=electronics&sr=1-1
A337: B0B3RRWSF6 | B337: Fire-Boltt Phoenix Smart Watch with Bluetooth Calling 1.3",120+ Sports Modes, 240*240 PX High Res with SpO2, Heart Rate Monitoring & IP67 Rating | C337: Electronics|WearableTechnology|SmartWatches | D337: â‚¹1,998 | E337: â‚¹9,999 | F337: 0.8 | G337: 4.3 | H337: 27696 | I337: Fire-Boltt is India' No 1 Wearable Watch Brand Q122 by IDC Worldwide quarterly wearable device tracker Q122.ã€Bluetooth Calling Watchã€‘- Fire-Boltt Phoenix enables you to make and receive calls directly from your watch via the built-in speaker and microphone. This smartwatch features a dial pad, option to access recent calls & sync your phoneâ€™s contacts.;ã€High Resolution Displayã€‘- Comes with a 1.3" TFT Color Full Touch Screen and a 240*240 Pixel High Resolution this watch is covered to flaunt the sleek and stylish look always.|ã€120+ Sports Modesã€‘- Track each activity effectively with this smartwatch & activity tracker. Track your calories, steps and much more while you are on your fitness journey. This fitness tracker has it all;ã€In Built Mic & Speakerã€‘- Get HD calling experience with this power-packed watch. Enhance the look of your wrist with attractive colors and sleek finish|ã€Smart Healthã€‘- With the latest HRS3300 technology track your heart rate anytime of the day or even while you perform some activity. The optical sensors assure results so accurate. Monitor your blood oxygen levels to stay fit and healthy;ã€Smartphone Notificationsã€‘- Get all your mobile phone notifications on this 1.3" Round Display Full touch smartwatch and never be late for a meeting, party or date.|ã€Gaming On Wristã€‘- Enjoy playing games on the wrist itself as you are on the go. ã€Breathe Functionã€‘- Ensure your breathing exercise is fit and healthy with the breathing function.; ã€Multiple Watch Facesã€‘- Over 100 Cloud based watch faces to choose from and match your outfit and look each day everyday|Included Components: 1 Smartwatch, 1 Manual, 1 Magnetic Charger, 1 Warranty Card; Band Color: Black; Band Material Type: Silicone; Color Name: Black; Human Interface Input: Buttons touch Screen; Case Material Type: Stainless Steel; Clasp Type: Tang Buckle; Compatible Devices: Smartphone tablet iphone android, **Disclaimer** The charging USB needs to be connected to a 4.7V to 5V adapter only for best battery backup | J337: AHUGCKS7YANTMDYINXQG2UDTU4JQ,AGHQ2VHXMPWZV5SV25S5N3OENXSQ,AH3GZWZM5RVOFCJCXRU7QFBAJ5NQ,AGQ2RWOECSEFEQMIGE7VTXP65OKQ,AEVUBEFT2MRH2PRVW53SJEL7H42A,AENY7L4XGCQMI627A27G3NVIBJNA,AHQISETKX3OXMZ4IX3YO7YV4UZ6Q,AGESGUTIYJQOZ7PU563DHLYSPRTQ | K337: yogita ratre,Arun k.,Amol Basutkar,janarthanan,Naman,keshav Chelmeti,Hritik jain,Jatin Shah | L337: R34816YEM3Y2VJ,R3P1QZDIWJJYVR,R2HXC35HKL6S3E,R2CUWR6SL0MMRR,R3PWLUFNP117X0,R2PK2034NVCPNH,R2YJZKVTCUJAVZ,R27X5G6UFUKCM9 | M337: 7-8/10, Decent, good for day to day use,Good choice under budget of Rs2000,Average product.,Budget friendly,Overall it's a good watch,Good product,Best in design, accuracy and looks fancy. A must buy for every person who is watch enthusiast.,Having a great experience | N337: 2 months review- its been working fine, there's been no problem as of now.. some things-the whole step tracking thing, i bought it due to that reason, it didn't basically satisfy me to that level with that, but it does count steps accurately in the walking mode(activity)Its got some scratches in it.. but its not that noticeable at first glancethe backgrounds, I believe it could've been wayyyy better if we could change 4-5 backgrounds of 10, but we can only have 2, 1 customised and 1 download from the app(which has limited options) the other backgrounds are just.. eh..the looks, I'll give it 9/10, it's good looking stylish differenttouch screen is goodthe sleep tracking too is kinda accurate(i still haven't understood it that well lol)battery life is muah, I use it without Bluetooth and it easily survives for 6-7 daysspo2 and heart rate, I just believe what it says as i can't check prove if that's correct.the water resistance, I haven't used it in water (ofc am scared) the calling feature works fine.. its got good sound overall its a decent watch and can be used in day to day activities, am quite satisfied with it as my first smart watch ðŸ˜—,I've used this product for 4 days, and i'm going to rate the various features and different aspects of this smartwatch which could help the customers here -So, Bluetooth calling (4/5) - the in-built mic of this watch is excellent and the voice gets to the other side without any disturbance, watch connects smoothly with the mobile and don't get disconnected automatically until you do it yourself through watch or phone. Only con is you can't silent the incoming call which is annoying sometime, hope they fix it with an update.Built quality and looks (4.5/5) - metallic built which looks premium and straps are also quite smooth and comforting. Best thing is, it also looks good over skinny wrists(poor me, with 5.6 inch wrist). Only con is you can get scratches on display so protect with it some sort of screen guard.Touch screen (5/5) - it's almost buttery smooth without any lag which is pretty impressive for a smartwatch under 2k. I bet you will not get any laggy experience ever.Accuracy (3.5/5) - SpO2 and HR has fairly decent accuracies, it gives you a rough idea of your being, so its quite reasonable for a watch under 2k. Count steps with decent accuracy as well. Sleep accuracy is also just acceptable.To sum up, you should definitely go for this watch if you've a budget, constrained under 2000 rs,,I recently purchased the Fire Bolt Phoniex watch, which is quite stylish, and the Bluetooth calling is excellent. The voice gets to the other side without any disturbance.The build quality is good over the wrists, but you can get scratches on the display, so protect it with some screen guard. You should go for this watch if you want a budget-friendly smartwatch under 2000.,It's a good watch but i have faced two problems in it the first one is there is no feature of raise to wake and the second one is there is no option to silent it when someone calls you.....i think you should purchase it if in future company add these two features...,I recently purchased the Fire Boltt Phoenix Watch, and I am very happy with my purchase. The watch is quite stylish, and I get compliments every time I wear it. The watch is also quite comfortable to wear, and the strap is adjustable to fit any wrist size. The watch also has a great battery life, and I can go for days without having to charge it. The watch also has a number of features, including a step counter, heart rate monitor, and sleep tracker. All of these features are very useful and make it easy to track my activity and health. Overall, I am very pleased with my purchase and would highly recommend the Fire Boltt Phoenix Watch to anyone who is looking for a stylish and functional watch.,This watch is absolutely stunning and great value for money. Really pleased with the design and shape of watch, definitely a must buy for every person .loved the colour, durability and accuracy is super ðŸ‘. just go for it.,I liked the product it has so many features like sleep tracking, sp02, Heart rate measuring, music player, temperature checker my only nitpick would be that it only have 2 games and secondly it has good wallpapers but a Ben 10 Omnitrix wallpaper would give it an even more awesome look | O337: https://m.media-amazon.com/images/I/41sHRWXCfvL._SX300_SY300_QL70_ML2_.jpg | P337: https://www.amazon.in/Fire-Boltt-Phoenix-Bluetooth-Calling-Monitoring/dp/B0B3RRWSF6/ref=sr_1_4?qid=1672895748&s=electronics&sr=1-4
A338: B0B5B6PQCT | B338: boAt Wave Call Smart Watch, Smart Talk with Advanced Dedicated Bluetooth Calling Chip, 1.69â€ HD Display with 550 NITS & 70% Color Gamut, 150+ Watch Faces, Multi-Sport Modes,HR,SpO2, IP68(Active Black) | C338: Electronics|WearableTechnology|SmartWatches | D338: â‚¹1,999 | E338: â‚¹7,990 | F338: 0.75 | G338: 3.8 | H338: 17831 | I338: Bluetooth Calling- Wave Call comes with a premium built-in speaker and bluetooth calling via which you can stay connected to your friends, family, and colleagues|Dial Pad- Its dial pad is super responsive and convenient. You can also save upto 10 contacts in this smart watch|Screen Size- Wave Call comes with a 1.69â€ HD Display that features a bold, bright, and highly responsive 2.5D curved touch interface|Resolution- With 550 nits of brightness get sharper color resolution that brightens your virtual world exponentially.|Design- The ultra slim and lightweight design of the watch is ideal to keep you surfing your wave all day!|Watch Faces- Wave Call comes with 150+ Cloud watchfaces for you to pick from, complementing your every mood and outfit|HR, SpO2 & Breathing- Monitor your heart rate and blood oxygen levels on-the-go with the heart rate and SpO2 monitor. It also comes with Guided Breathing to help you relax and embrace mindfulness. | J338: AHPYDFW6Y3FIQGD2RJPBFF5QNVRQ,AG7DTVYZDY2NWU6V2G4KSIB67TDA,AHNQJPSI4I23HHMRHCCCI7QOBK7A,AHPOQQONRLZMHYLDKYP5SQOKRIEA,AGDD5ACY3AGTMTVBQOC3DMUR6REA,AFZV4ISJSNGDUD5TU3VYMTYQ5JGA,AGKPRGZCV5XK7ZNVLQWUGRB6CVVQ,AE7DX25DQCE7MXLEASO6I3YLWHRQ | K338: AV,Mathan kumar,Amol Manjrekar,Suraj_nirmalkar,ASIF ANSARI,Jugalkishor yadav,Chinmayee Ninawe,Samba Shiva | L338: R3EKLFGQGV02SG,R23WEMNZK46UV3,R1G2C7XV8CAM7W,R1O1T0NB6M5CU4,RY95PJLUIT03E,R2HMI9LDLJ1S2Y,R216CF66UYJR2A,R1XD0A6A2KGJZ6 | M338: Not Polished Enough. (Improving with updates),Best for the budget ðŸ‘,Value of money,nice product,Good product,Super value for money,Awesome product,Product itv | N338: [Update: Sept 29] boAt seems to have heard the feedback ðŸ˜€ and updated the watch faces. Now there are a few good ones to pick but a slight improvement over the ones the watch earlier had. Bit Impressed. Added one star for it.Not a very polished product. The fonts are tacky and look ugly in the watch for notification text and caller name text. The watch faces are a lazy design job. No point having 150 watch faces if only 10-20 are good or usable. Rest are useless.[UPDATE: Oct 11] boAt seems to be on a smartwatch launch spree. And thanks to that, they are constantly updating the phone app and the watch faces. Now you have many good looking watch faces to choose from. So overall, still the Smartwatch UI needs work. But atleast you have good watch faces.Good:- Screen quality- Battery life- Looks and the metallic frame- Call clarity- BT calling at the price- Reasonably accurate sensorsBad:- The UI, fonts - they are all very ugly and tacky. They could have tried to give the Chinese software some makeover. But it is a clearly lazy job by the tech team. A copy paste job to be precise of getting an outsourced software and plastering it with brand logos.- Restarts randomly when the call is going on on the watch even for 1 min or so.- Watch faces. Again a job of the design / tech / UI team. BoAt doesn't have a good team of designers and UI guys to really offer simple yet good software features like good watch faces and good watch UI.- No option to silence a call or reply with quick replies.Look for Noise Smart Watches in the Same Range. Noise Colorfit Pulse Go Buzz is cheaper and better alternative + has better watch faces and UI and quick reply to notifications and call silence and mute options for lower prices which this watch has clearly missed.You can go for boAt Wave Call also - It isn't an outright bad watch, but there are better options available for the price.boAt - If you have a team who reads and wants to improve, get some good UI and design folks in your team. Your products are good, but the UI and design is what the people see and that's what makes them feel good about your products. You have really average UI.,Boat wave call watch is best for budget.Call is too good and sound quality is also too good.Battery is good.Totally the watch is good for range.,It's good value for money smart watch.Light weight. Touch is smooth.All the features are 90-95% accurate.,a good product in this price range must buy itGOOD LOOKINGGOOD QUALITY,Good product is mst h,Average for calling good looking,I'm really happy to purchase this watch! It's very affordable having so many features. The calling feature works really well! Overall, if you're looking so good brand & good features, go for this ..,Product does not turn onPlease return the item. Please. | O338: https://m.media-amazon.com/images/I/41d69zua5LL._SX300_SY300_QL70_ML2_.jpg | P338: https://www.amazon.in/boAt-Wave-Call-Dedicated-Multi-Sport/dp/B0B5B6PQCT/ref=sr_1_5?qid=1672895748&s=electronics&sr=1-5
... A1280: B07JGCGNDG | B1280: Crompton Amica 15-L 5 Star Rated Storage Water Heater (Geyser) with Free Installation (White) | C1280: Home&Kitchen|Heating,Cooling&AirQuality|WaterHeaters&Geysers|StorageWaterHeaters | D1280: â‚¹6,800 | E1280: â‚¹11,500 | F1280: 0.41 | G1280: 4.1 | H1280: 10308 | I1280: PRODUCT: Crompton's energy efficient storage water heater with fast heating|TECHNICAL SPECIFICATIONS: Wattage: 2000 W; Capacity: 15L; Star Rating 5; Pressure 8 bar|3 LEVEL SAFETY: Capillary Thermostat, automatic thermal cut-out & multi-functional valve to provide higher safety|ANTI-RUST: Fitted with specially designed magnesium anode which prevents corrosion due to hard water quality|QUALITY COMPONENTS: ISI marked nickel coated special element to provide resistance against scale formation | J1280: AHVHHPNIDA6XPCW2ODA2IHXUHZYA,AF2IWKFSVGHOYJKFBTMNDELPVFVQ,AGB7UMNSKR6R3WD2NM5KY7S6W57A,AEOULYDSLLD2FVDNR7WTWLQFRG7Q,AEW2QMVUPCPVEBXBZXT6GXJ7T4CA,AHTIXIDXG2UN6WNFRRMQ3VLNU2EA,AGI7FLR5BUYXHCEJCWGQPYKFSWXQ,AFI5ILRQ2722AXN6DPUEV63DSY6A | K1280: Aryan Raj Singh,Akash Saini,Shalini Rani,Sayan Roy,vivek vishwakarma,NITIN,Mahesh singh,krishnareddy | L1280: R1Q8U0KHBE4RAJ,R3M5X5REVHJUFI,R2G64QBZXNF1G2,R7HQDX5RMXVNS,R3J3KGQAFR06WR,RXZ2UHPZ7431G,R1OF1W4L7V2MFV,R37WO2GKN6E3Q9 | M1280: Good product st this price,Good Product,Good product,Awesome product,Pipe is not there it's mentioned that pipe is with this order,Easy to install,best price.,Good,Good product | N1280: As always amazon never disappointes if you are finding best quality product st low price go for it.,https://m.media-amazon.com/images/W/WEBP_402378-T2/images/I/51-YaFM4jHL._SY88.jpg,I like the product.itâ€™s too cheap on Amazon,Good product,Where is pipes ????? It's with gyser as described,Product is good and price is best but it takes half an hour to fully heat 25 litre of water.,Ok,Good product | O1280: https://m.media-amazon.com/images/W/WEBP_402378-T2/images/I/31RWtNDo6EL._SX300_SY300_QL70_FMwebp_.jpg | P1280: https://www.amazon.in/Crompton-Greaves-ASWH-2015-15-Litre-Storage/dp/B07JGCGNDG/ref=sr_1_294_mod_primary_new?qid=1672923607&s=kitchen&sbo=RZvfv%2F%2FHxDF%2BO5021pAnSA%3D%3D&sr=1-294
A1281: B08L12N5H1 | B1281: Eureka Forbes car Vac 100 Watts Powerful Suction Vacuum Cleaner with Washable HEPA Filter, 3 Accessories,Compact,Light Weight & Easy to use (Black and Red) | C1281: Home&Kitchen|Kitchen&HomeAppliances|Vacuum,Cleaning&Ironing|Vacuums&FloorCare|Vacuums|HandheldVacuums | D1281: â‚¹2,099 | E1281: â‚¹2,499 | F1281: 0.16 | G1281: | | H1281: 992 | I1281: No Installation is provided for this product|100 Watts Powerful Motor|Powerful Suction|In-Built LED Torch|Range of accessories for different cleaning needs|Fit type: Universal Fit | J1281: AGTDSNT2FKVYEPDPXAA673AIS44A,AER2XFSWNN4LAUCJ55IY5SOMF7WA,AE3MSW6H3AL6F3ZGR5LCN5AHJO6A,AG5OL5WIIPJBY25HISJLM5K2UBTQ,AGHFSIBYVYXUGSNYUDAHBGOIZ3KQ,AHYH6AZT3U3U44CDW5Y563UYIIUA,AFLOAOURRZZZGFBF7F6IKGXRB6NQ,AGNWBYEVAIII4MPQNKN3LFVOHYZQ | K1281: Divya,Dr Nefario,Deekshith,Preeti,Prasanth R,Pradeep kashiram Tetgure.,Abhijin Janardhan,Prashant | L1281: R2KKTKM4M9RDVJ,R1O692MZOBTE79,R2WRSEWL56SOS4,R3VZRQJOKCBSH4,R2QI4626ASSCIT,R1TFFJ5ON6ATEO,R14JK9VQCXXEKU,R1V4J4B7RXHG8T | M1281: Decent product,doesn't pick up sand,Ok ok,Must Buy,Good one for basic use with normal suction power,Super,First review,Perfect product for my car | N1281: Does the job well,doesn't work on sand. though the suction is very good, the sand stays back no matter which lead you use.,Ok ok,Easy to use product (I used it for the first time without knowing the know-how of its use). Cleans almost 90% of your mess inside the car. Highly recommended.,Pros: look and feel, easy to hold and handle, Cord length, useful led light during night, normal suction power but good enough for general useCons: noise is bit loud, suction power could be better,Good,Hmm,Strudy design, quality accessories,reputated brand.I have seen some car vaccum cleaners especially the low cost one's where dust comes out of machine due to poor locking mechanism, so ofcourse you don't want the dust to be falling back when the sole purpose is to remove it!!!You get what you pay for, I have home vaccum clear from same company with has a good suction and does the job well, I wanted a battery pluggable clearner where I can use it anywhere.Believe me no vaccum cleaner is good enough for heavily soiled cars, so if you are expecting a commercial level cleaning the don't buy any.Car vaccum cleaner is a portable device which gives decent satisfaction but not a perfect, I have seen some people who do not take out mats and just shove the cleaner in it and say it's not good.Mats need to be take out which actually collects big dust and derbies, this poor small machine can't handle a 100% cleaning on that.If the car is heavily soiled the you must get it cleaned at a professional clearner then start using the small one.I found this to be doing the job when compared to my house vaccum clearner.One thing I observed was the wires was getting hot and has a soft component which makes it even thinner when it's hit but I think I can handle the job, accessories quality is good and fir and finishe is good.I did not seen any dust seeping through the compartment and it was well contained in the dust chamber.Suction is decent and you can give almost a clean and tidy look to your car with this machine, again a professional grade cleaners can doa good job which cost nothing less tha 15K.I would say worth a buy it used delligently by not expecting too much.I only hope if the company can provide a bag to carry it for the price or find one in your own which can fit your needs.,Perfect | O1281: https://m.media-amazon.com/images/W/WEBP_402378-T1/images/I/41lZEy8e9DL._SX300_SY300_QL70_FMwebp_.jpg | P1281: https://www.amazon.in/Eureka-Forbes-Vacuum-Cleaner-Washable/dp/B08L12N5H1/ref=sr_1_295?qid=1672923607&s=kitchen&sr=1-295
A1282: B07GWTWFS2 | B1282: KENT 16025 Sandwich Grill 700W | Non-Toxic Ceramic Coating | Automatic Temperature Cut-off with LED Indicator | Adjustable Height Control, Metallic Silver, Standard | C1282: Home&Kitchen|Kitchen&HomeAppliances|SmallKitchenAppliances|SandwichMakers | D1282: â‚¹1,699 | E1282: â‚¹1,975 | F1282: 0.14 | G1282: 4.1 | H1282: 4716 | I1282: Compact and sleek looking modern appliance, KENT Sandwich Grill is perfect for a healthy and tasty quick snack|It is multi-functional and helps you grill, toast, roast and even make multi-layered sandwiches with great ease|The appliance has non-toxic ceramic coating that uses less oil or butter and ensures easy flipping as nothing sticks to the surface|The ceramic coating also makes the grill easy to clean|With its ergonomic handle, you donÃ¢â‚¬t have to concern about the safety|KENT Sandwich GrillÃ¢â‚¬s adjustable height lets you easily cook various sizes of snacks|The automatic temperature cut-off turns off the appliance once your dish is cooked | J1282: AEY6PEMQ7DII44WSUSC67JEWDE3A,AFMVVM2AXA3WHTC23D2ZQH4YUTZA,AEQGRU6X2E3PF6OHP7HL7ZVTHOTQ,AEB4KX3FFG2DE2Q5CNKYTOWP5CBQ,AEASTV5BKJJIYW6WVS6JUBSK4MHA,AHQ7UT4SYDQMQB6DJDBVVHQBCXXA,AEZFDGHBWLHUXOLDPVNS3UERDNSQ,AFPMGJN4SHWHD3DBQBS2FXGBZ6TA | K1282: Tabassum,Ark,AMIT GROVER,-,deshraj s.,Ankisha Mishra,NITIN,Jai goyal | L1282: RXPUKJKEHY256,R1DXJ48GMFWOZD,R24RXWIR7PL4IW,R12KBR8IKSS7J2,R1MJZTN0DNDU71,RMUCAZHGYK1RB,R2KJM0QA35OC7I,R1UYOQA2722J9E | M1282: Only for grill sandwich use cord length is too shorthort,Decent product, has some old flaws,Good ðŸ‘,Every home should have this,Weak body material,but overall good product,Good one with a small issue.,Trusted brand,Nice product but cord length had to be replaced..very short | N1282: Good quality but cord is too short .it is ok for sandwiches.,Value for money product, does what it promises. Ceramic coating.Peoduct designers did not make a single sandwich with this. Product usage images and actual usage does not match. The hinge mechanism is flawed and will result in flat sandwiches. If you force the hinge/ clip to shut, it may just break.Poor product design in 2022.,Good Toster and easy to clean,Superb product. Every home should have this product. Especially if you have aged parents, not feeling well. Cooking difficult. Can eat something. Even aged persons/ parents can use it and start their day having a breakfast on time, morning. Evening snack, etc auto power cutoff feature is the greatest attraction, and easy cleaning. Built quality is superb. Most busy persons skip breakfast, you dont have to skip it if you have this product, and a pack of bread, and if there are some vegetables, luxury breakfast with this product,You can make big to small sandwich without any problem,at a time 2 sandwich...but be careful body is weak ,possibility of damage is more.,Pros-1. Ceramic coating & non-toxic.2. Can make 2 jumbo sandwiches at once.3. Takes only 3-4 minutes.Cons-1. Had to manually close it as the height adjuster is small.,The brand vakue is justified. The Product is good , easy to handle,Go ahead and buy, if ubr looking for a trusted griller,Likes the product but cord length is short..had to replace it | O1282: https://m.media-amazon.com/images/W/WEBP_402378-T2/images/I/41mtYvY3VdS._SX300_SY300_QL70_FMwebp_.jpg | P1282: https://www.amazon.in/Kent-16025-700-Watt-Sandwich-Grill/dp/B07GWTWFS2/ref=sr_1_296?qid=1672923607&s=kitchen&sr=1-296
A1283: B09KRHXTLN | B1283: Candes Gloster All in One Silent Blower Fan Room Heater Ideal for Small and Medium Area, 2000 Watts (White) | C1283: Home&Kitchen|Heating,Cooling&AirQuality|RoomHeaters|FanHeaters | D1283: â‚¹1,069 | E1283: â‚¹1,699 | F1283: 0.37 | G1283: 3.9 | H1283: 313 | I1283: Motor : Powerful Motor for Quick Heating|Heat Setting : 2 Heat Setting 1000/2000 W|Warranty: 1 year limited warranty. For warranty claim|Over Heat Protection|Handle for Easy Portability|Heat Resistant Body and Stand for Stability|Hot Air Outlet and Safety Grills | J1283: AGDD5ACY3AGTMTVBQOC3DMUR6REA,AFHT3WYWI4DB6Z42VVJZQGFFNIZA,AFSHYGNQHXNKBEXS62GRETNGH3GQ,AEZVJENT2FC3K3MKMIB4ZXDWNDPA,AHUKNKB6OS7JE4VQCHKF5363DOKA,AEIETT5YH6XRP434INQB4KSDMI4Q,AG7Y3XXKXV7O63XWG4Q7FKGNR6LA,AFZCNPDZYVYZCJ2JE5AH4SKJ7WQQ | K1283: ASIF ANSARI,Amazon Customer,Shashank,p k kishen pejathaya,Rohit,Deepak Sarkar,sudhananda,Rahul sharma | L1283: R2H4C76KXFUF5N,R2X2MGZJI8JOV5,R2PHMY74SQMCM4,R2EOV466KP2TSZ,R3HO5I93IRXGK4,R1IKS35P0F8TAJ,R3GCXN4RSB3T4Z,R3GM1KFHUQJ886 | M1283: Good product,Value for money,Auto cut is not working properly and fan continues even after auto cut...,Room heater,Worth of money,Budget friendly,Best room heater,Not satisfied with the product | N1283: Good product but price 800-900 ok it's product good,Easy to use, Very Handy.,Auto cut continue starts fan...which lower down the temp.,I liked the swivelling action to spread the heat,Beat product,,Best room heater.thank you,I received the broken article but there is no replacement service for this product | O1283: https://m.media-amazon.com/images/I/41IJvfYMaZL._SY300_SX300_QL70_FMwebp_.jpg | P1283: https://www.amazon.in/Candes-Gloster-Silent-Blower-Heater/dp/B09KRHXTLN/ref=sr_1_297?qid=1672923607&s=kitchen&sr=1-297
A1284: B09H34V36W | B1284: Inalsa Electric Fan Heater Hotty - 2000 Watts Variable Temperature Control Cool/Warm/Hot Air Selector | Over Heat Protection | ISI Certification, White | C1284: Home&Kitchen|Heating,Cooling&AirQuality|RoomHeaters|FanHeaters | D1284: â‚¹1,349 | E1284: â‚¹2,495 | F1284: 0.46 | G1284: 3.8 | H1284: 166 | I1284: Powerful 2400 RPM copper winded motor for quick heating and can be used vertically or horizontally.|Cool, Warm or Hot Air selection knob for heat setting (Please note that regulator changes heating power & not fan speed)|Variable Temperature Control for setting Room Temperature as desired.|Plastic body with rust resistant metal front grill.|Built-in overheat Safety protection.|Lightweight with Carry Handle for easy portability.|Do not worry if you experience some burning smell when you run your room heater for the 1st time. This is due to the motor varnish getting heated for the 1st time. The problem should not recur in subsequent usage. If it does, please contact our Customer support|Caution - Always use the product with 16A socket. Using it on lower rating sockets may result in melting of socket or the plug. This Consumes 2 KW when operated on high heat setting. | J1284: AF7PPF6P5ZASHL4RYP7AZQBHRRTQ,AHSCASHEA5LLVORCEIHZYHNTHUMA,AEKWTFXLMJ5IK4T2CSJT2AY2CGYA,AHDL7PIYXZ36YFNS7NBPEFD3WRUQ,AGFYVS63J2YEAO7NGQCRW3TTFB3Q,AE6VPREPQCXMNBLLF3SDM4ZWRSLA,AG35AFPFHGMNYSEFQYN6USFG3FJQ,AH7JGQRRWMJTCWMZPQZDA7324DUA | K1284: Alok Vajpayee,Amazon Customer,Pilot Muhammed M Khan,pradeep Verma,RNMISHRA,Takshak Tathagat,Amazon Customer,Anamika Nagpal | L1284: R1QHY0304RCZS6,RV3GIBR7FUXWH,R3M83QIXOQMO9J,R227LWX8C4MTYQ,R1B938V5HN71BQ,R2K9QFBTB6FYEF,R2K0ND1WP31RYH,R35YG940TYIGK5 | M1284: Worth Buying,Very good,Good and sturdy room heater with compact design.,Inalsa Hotty Heater,Good for winter,Don't buy it go for Amazon brand,Package,Decent | N1284: Heater is good for regular sized room, might not work on bigger room or hall but for regular sized room it's heavenly,Like very much.,The hotty model produced by inalsa is sturdy and compact in design easy to handle good quality of cable and fast heating ability with auto cut out system. I had received this product with crack inlet air net however it replaced with new one by inalsa and amazone at ease. It would be added advantage if air deflector be facilitated in this with good quality of indication light. All and all good quality product in this price range,This hotel heater is very light weighted and compact in design, it has a fast heating ability and comes with auto cut out system, its good for a medium size room the blower keeps your room warm for great amount of period, the price is also reasonable overall a great product by Inalsa.,Must have in cold season for small room,Don't buy it go for Amazon brand. No value for money.,Package is damaged but product is in good condition,Reasonable performance for the price | O1284: https://m.media-amazon.com/images/W/WEBP_402378-T2/images/I/411uVIJr+QL._SY300_SX300_.jpg | P1284: https://www.amazon.in/Inalsa-Electric-Heater-Hotty-Certification/dp/B09H34V36W/ref=sr_1_298_mod_primary_new?qid=1672923607&s=kitchen&sbo=RZvfv%2F%2FHxDF%2BO5021pAnSA%3D%3D&sr=1-298
A1285: B09J2QCKKM | B1285: Havells Zella Flap Auto Immersion Rod 1500 Watts | C1285: Home&Kitchen|Heating,Cooling&AirQuality|WaterHeaters&Geysers|ImmersionRods | D1285: â‚¹1,499 | E1285: â‚¹3,500 | F1285: 0.57 | G1285: 4.1 | H1285: 303 | I1285: Indiaâ€™s 1st Immersion WH with auto cut off & Temperature setting Knob (Low, Medium & High)|Its smart dual purpose collapsible flap works as a cover as well as a hanger when completely open|Heating Indicator; Heavy duty 3 Pin molded plug|Efficient heat transfer heating element; Nickel plating heating element|Touch protection cover; Elegant & sturdy safe bucket hanger | J1285: AG2VWPTTUEHEZWGDIYDJWPX7IDJQ,AEDNFNVOPMOWPCSBXQJFW6PCP3ZQ,AHJQJ4BFKEDVWHP6FIXGMF75XSSA,AENPKYWO4NMYRYNE3PNVGD4CVOAA,AEZOCEHWCXQRBNLIQCNEC43TNMGQ,AFGGQUIZ4KW57HMRGQTSERDLCFEA,AHQ5BOJJTHUA6XD6IIN7GLN53DVA,AHPM47CWRZDB6XMDV2IVXQR3KDUQ | K1285: Jignesh malvi,Garry,sonu,Amazon Customer,SANJAY PATEL,SANJIV KUMAR,Md Nafis Ansari,Subhash kushwaha | L1285: R2PDTLV982BZ70,R2DG09GG88T9WZ,R2FI87586PEKJ8,R3BT931YPQDPLF,R2609G1V725LV1,R29G2BHEEMZ8TK,R12M631S82DWX9,R3HBBWJEZQNBH4 | M1285: product good but service bad unexpected,Its good,Very nice product,Efficient Product,Nice,Very good and useful product as expected before buy.,Handle length is too good you can use whole dram,Very fast heating | N1285: no doubt product is good but after 2 month product auto power cut funtion not working so try to claim warrenty but havells said talk to amazon and amazon said talk to havells both the comany raise our hand. by the way product gave 2 year warrenty but they gave me only excusses. very bad experiences with havells. never expected,Its good the ony pro and cons can be the flap ..Pros us can say is that the flap can be used for wider bucket of water for heating Cons u can say is the again the flaps bcoz while not in use flaps must be closed and you can't hang the heater anywhere bcoz there is no option given . Flaps can cause issue bcoz it have to be kept on the ground while not in use ..Rest all is good . Auto cut feature is best,Cord length is shortEnergy efficiency good &Temperature control too good,I realt like the design and auto shutoff features of the product. But there's is also design flaw that you can't insert it into the half filled bucket and water should be full.,Awesome,Very good product,,Energy efficiency is ok not good | O1285: https://m.media-amazon.com/images/I/21TQo2rZRbL._SX300_SY300_QL70_FMwebp_.jpg | P1285: https://www.amazon.in/Havells-Zella-Immersion-Watts-White/dp/B09J2QCKKM/ref=sr_1_299?qid=1672923607&s=kitchen&sr=1-299
A1286: B09XRBJ94N | B1286: iBELL SM1301 3-in-1 Sandwich Maker with Detachable Plates for Toast / Waffle / Grill , 750 Watt (Black) | C1286: Home&Kitchen|Kitchen&HomeAppliances|SmallKitchenAppliances|SandwichMakers | D1286: â‚¹2,092 | E1286: â‚¹4,600 | F1286: 0.55 | G1286: 4.3 | H1286: 562 | I1286: MULTIPURPOSE: Different Sandwich Plates for Toast / Grill / Waffle plates to make the snack of your choice|Detachable Non-Stick Plates are easy to clean and maintain|Thermostatically controlled Heating Element | Auto shut off function|Grip handle | Elegant black finish body|Power : 750W | Voltage: 220V-240V;|Warranty: 1 Year Standard Warranty + 1 Year Additional Warranty on FREE Registration | J1286: AFIO2JLNOU6SSNCHMG2ZED34SVNQ,AFKJ6IC227YNTE5PYNVT4YBPT2SA,AFV3HKJKN55O6CQNAAIYSAPMCPXA,AGW3GPXDCYJJB5FMX6SOXTO7PKPQ,AEYJQQMMMEZZQ2D7WGG2KJG7EUJA,AF67RC7KNNJB3EMMFB5RSJ73N7SQ,AE6DZEFBVJYVMURYFDATZFAANXJA,AF34LKGQ5JFWGMS3TVAZMUKQCO4A | K1286: Srishty,Somesh Bandopadhyay,sowjanya,pritamsharma,Jaseyfiroz,Basanth Balram,Prem,Ritesh Mehta | L1286: R2P85TVQQPR3XX,R3IGUN8ESO1GE5,RAO29VFIR7Y20,R21E4GVF798QBC,R2600ZN2HS1KVZ,R44ZNSYWMMKWH,R5E0YEMP9TLPD,R11PAFU64U5LGV | M1286: Nice Product,Three options (toaster/grill/waffle maker) are neatly packed into this readily usable device.,Product arrived in under 24 hrs...yet to test it,Good Quality,Very nice,Don't know why I waited so long to get this!,Value for money,Good quality, could have been somewhat lower in price | N1286: Overall nice poduct just one problem is that is the cord length only rest awesome. Easy to clean and easy to handle.,We used this for sandwich making and it performed well. The plates for grill and waffle making are readily interchangeable. The cord length is adequate although slightly longer cord would have been great.The device is readily portable because of its size and weight. Overall very useful.!,https://m.media-amazon.com/images/I/71cciIOHxUL._SY88.jpg,The quality of product is good,Used a couple of times .....and sandwitch came good,I wanted a sandwich maker and refused to buy one from a store since it was all 2k-4k and didn't have half the features that i was looking for. Saw this and love iBell as an upcoming Indian brand (own an electrical sander too), so didn't think twice and got this. Don't regret it one bit!! Pros are the 3 interchangeable plates for different ourposes. Grill one is just fantastic to hear all kinds of sandwiches and rolls and other food. All the plates are easily removable and washable too. Only con that i saw to this was the latch wasn't properly latching while making a heavily loaded sandwich in the sandwich maker. Otherwise it's a top of the range product in comparison with other big brands!,All the 3 functionalities works pretty well. Only thing is it should have had auto switch off feature. Nevertheless it is a very good product and worth the money. Sandwich also gets made fast.,I ordered vguard removable plates sandwich maker, but it came in faulty. The plates eject button had an issue. Later I ordered this one as was recommended by someone I know. It's of good quality, only that could have been somewhat lower price | O1286: https://m.media-amazon.com/images/I/41iHB-nmy8L._SX300_SY300_QL70_FMwebp_.jpg | P1286: https://www.amazon.in/SM1301-Sandwich-Detachable-Plates-Waffle/dp/B09XRBJ94N/ref=sr_1_300?qid=1672923607&s=kitchen&sr=1-300
A1287: B07SLNG3LW | B1287: Inalsa Vacuum Cleaner Wet and Dry Micro WD10 with 3in1 Multifunction Wet/Dry/Blowing| 14KPA Suction and Impact Resistant Polymer Tank,(Yellow/Black) | C1287: Home&Kitchen|Kitchen&HomeAppliances|Vacuum,Cleaning&Ironing|Vacuums&FloorCare|Vacuums|Wet-DryVacuums | D1287: â‚¹3,859 | E1287: â‚¹10,295 | F1287: 0.63 | G1287: 3.9 | H1287: 8095 | I1287: Wet or dry, bagged or bagless - No matter it is dust, hair, daily waste, the device can clean the dirt perfectly. You don't need to change filter during operation. Please take out the cloth dust filter and use sponge filter when sucking liquid|Blower function- The blower function is suitable for drying and cleaning of narrow and hard- to-reach indoor or outdoor areas. For effective blowing results, do not use any filter in vacuum cleaner. To hold a large amount of waste, this vacuum cleaner boasts a container capacity of 10 litres|Powerful and durable â€“ Equipped with powerful motor delivers 14KPA strong suction power and ensures long time operation. The vacuum cleaner has an impact resistant polymer tank for longer usage life|Safe buoy technology â€“ Safe Buoy technology immediately stops sucking water when the liquid capacity reaches the critical point. This protects the machine from being damaged and guarantees superior lifetime. This device ensures low-noise operation|Flexible and convenient - With ergonomically carry handle, along with four 360Â° rotating wheels enable it to move flexibly to anywhere you need. Its compact and lightweight is easy to store without occupying much space | J1287: AE6YWSEP7SYHCL2F5WLM3JLAPTDA,AGMOSQZYENCGDYQFYZG76EYEMCGA,AF33L2INL2ERR46KPNMQ6R5BRYXQ,AG247WO5BV4INTTCQ3H35SSEPVJQ,AER4JBQGMSVBHQGHMB6GOMU3BS3A,AGTJV66YYDYUYNBXEY2LCR7M5O5A,AHJDJPODT66LJAPROAV3ENMD4PLA,AGL5JWV3DFJIR6T23UKXMUS7BQTA | K1287: Sunny Senpai,Prashant,chetna,Surendran,Harisha,Raju Gupta,Shabazuddin,Defence aspirant | L1287: RPH459PHQQOP4,R17ZRY0K8T3ZVJ,R1UCB8TXKZ7JE0,R1YM20O66MTQUR,R1R7T8TNV9C1DX,R3OCX18B6XDQ39,RRIN800K9UFKC,R8EDW68GK5IJK | M1287: Great value,Very Nice product,Very good product at reasonable price,Nice Product. Cost efficient,Value for money,good product for the price,very powerfull motor best product i like it,Good product | N1287: Bought this almost a month ago, so far it works well. Suction power is above average. Blower feature is a nice addition. Only con is it's a bit loud.,Very nice product.....really amazing,It's very sturdy, wheels are very good so u can take it wherever you want. Electric cable is long.,Deserves the purpose.,Just value for money,good for domestic use,very powerfull motor best product i like it,The product is good honestly i have tested it for cleaning the dry dirt. And in that this works great.Good long power chord and nice attachments that gives the cleaning abmngle a better approach. | O1287: https://m.media-amazon.com/images/W/WEBP_402378-T1/images/I/414PLTPvJBL._SX300_SY300_QL70_FMwebp_.jpg | P1287: https://www.amazon.in/Inalsa-Micro-WD10-1000W-Multifunction-Resistant/dp/B07SLNG3LW/ref=sr_1_301?qid=1672923607&s=kitchen&sr=1-301
A1288: B0BNDGL26T | B1288: MR. BRAND Portable USB Juicer Electric USB Juice Maker Mixer Bottle Blender Grinder Mixer,6 Blades Rechargeable Bottle with (Multi color) (MULTI MIXER 6 BLED) | C1288: Home&Kitchen|Kitchen&HomeAppliances|SmallKitchenAppliances|JuicerMixerGrinders | D1288: â‚¹499 | E1288: â‚¹2,199 | F1288: 0.77 | G1288: 2.8 | H1288: 109 | I1288: Portable & Convenient to Charge: This little body light weight design is easy for you carry it to school, office, parks, camping, anywhere you want to. and it also convenient for charge by power bank, laptop, computer, car or other usb devices.|Easy and Safe Cleaning - It has have smart safety protection device, magnetic sensing switch ultra safe to use and clean, the juicer cup's body and bottom can be separated, you can easy to clean it|Multi-function - With our juice blender mixing kinds of fruit and vegetables, you can make natural tasty juice, milkshake, smoothie and other baby food. It's very portable and great for traveling, outdoor.|Enjoy your fruit juice anytime and anywhere.|6 stainless steel blades, sharp and durable, can last for long time. | J1288: AEJKHGA26MUVUZIYWZOW4B6I4X7Q,AF3B47EOSBULYG63EGZZZGO6HTNA,AGNSXRFJBDVGM7FS7YYPNCEO7XFQ,AHR53IW5LAAXGGFK3DRWRMXMM7KQ,AE5W6S5KCJV6L2WMBIOKYWQJN37Q,AH5J4DROVHI6XHMTCBAK7WWU3F4Q,AE5KAK3S3XZDPRUR2VCND2QNZTUQ,AEKG7ELYA43YNPZ2YT3ORIL2VSOA | K1288: Yashvant Gote,Nargis Sultana,S.I.KUMAR,Ravi,Lokesh Hegde,Abhinav Anand,Any babar,Sarada peram | L1288: RGB7OLWZEBW2D,R35V1I6KBBWDA1,R2S9K0UTNSD0L6,R3RC91ZJN8FXRE,RHM5Q098AI06R,R2QOHI14M69TVA,R2PQH5L3O1O0F4,R3TYY0655P2RMO | M1288: Portable but not much powerful,not so good. power back up is very poor.its more like a toy for my 9 years old girl.,500 rs ok,Don't be fooled by ratings, not a good product,Not recommended,Worst Battery, no use,It is affordable .,User friendly blender, Recommended to buy nice products | N1288: Not sufficient power,the product is more like a toy for kids. can't use it as a proper juicer. power back up is very poor.,Ok,I had to replace this product first time because it was leaking and now after replacement the new one has no battery backup and vibrates too much.The MRP is above 2000 rupees which is not at all justfied by the product.After buying the product I found that with the product they are giving a cashback offer of 25 to 100 rs if you give 5 star review, probably that's why it has good ratings. I feel I was fooled by the ratings.,Waste product as the juicer is leaking which creates the whole place mess and the juicer doesn't grind properly where the pieces of fruits remain ungrinded. I generally dont write reviews but i was forced to write this one as this is just waste of moneySpend it wisely for something better,It's does not work properly at all, after charging for 4 hours the battery last only 30 - 45 sec. Very bad product.And they have given a cashback coupon to attract good rating.Misleading information is given on the detail page.,I bought this mostly for milk shake and it does an amazing job and it is affordable but it didn't worked while charging,User friendly blender, very useful for the pg accommodaters. I am using this to make a protein shake from day one when I was received from Amazon. | O1288: https://m.media-amazon.com/images/I/51pFS9lDzML._SY300_SX300_QL70_FMwebp_.jpg | P1288: https://www.amazon.in/MR-BRAND-Portable-Electric-Rechargeable/dp/B0BNDGL26T/ref=sr_1_302?qid=1672923607&s=kitchen&sr=1-302
A1289: B095PWLLY6 | B1289: Crompton Hill Briz Deco 1200mm (48 inch) High Speed Designer Ceiling Fan (Smoked Brown) | C1289: Home&Kitchen|Heating,Cooling&AirQuality|Fans|CeilingFans | D1289: â‚¹1,804 | E1289: â‚¹2,380 | F1289: 0.24 | G1289: 4 | H1289: 15382 | I1289: PRODUCT: Crompton's premium design ceiling fan with a strong cooling effect TECHNICAL SPECIFICATIONS: Sweep Size 1200 mm; Speed 380 RPM; Air Delivery 210 CMM; Input Power 70W|SUPERIOR COMPONENTS: 100% copper motor, double ball bearings and dynamically balanced blades|RUST FREE: Powder coated aluminium blades offer life long corrosion resistance|PACKAGE CONTENTS: 1 Ceiling Fan, 1 Motor, Set of Blades, Set of 2 Canopy, 1 Down Rod, 1 Shackle assembly, Instructions Manual and Warranty Card|Collection Name: Crompton Hill Briz Deco Designer Ceiling Fan; Finish Type: Painted; Mounting Type: Downrod Mount | J1289: AEKMKQMXK2FBIL6MRKHIPN56QJAQ,AGPNJEK2EUJ6YFFPND6OSSAVG5WA,AHY5LCCPN4ZSDFIFF3JUXP2YS4TQ,AG5TXXR5HQ3GX2KC5IHGIAEZXEPA,AH7GMEHVW44SQG6NRGTTTK4EQPOA,AEOCUF6Q6MJC37C4Z5LQT3RUWV5A,AHASKB67VHNUNB3RITEIHSC2YNMQ,AGEYV75NXF3MUJH7XB456WFUK2GA | K1289: David,Pujeshwar Sharma,Abhishek,U can buy,Ravinder singh,Gururaj B.,suresh,Jaswalshashi | L1289: R4F2HUXYO2V7U,R26UCI4JLBHQQA,RQH9Q1TBCSHWW,RLNUKMIVTZF3D,R3L9VSEBHFY0CO,R3RD12MBAHBOGJ,R3JX5CDKU775U,R1UOXH0VDEH21G | M1289: Good Fan for this Price,Good fan with high speed,A decent product for the price.,Good,Good in price,Very happy with Amazon,Good,Good | N1289: It doesn't make any noise. Speed okay for this price range. Light weight. I don't face' any issues in this fan. Over are good.,Good fan from Crompton,Fan was well built and value for money. The noise at the top speed is kinda loud. (can't complain with this price.),Speed control not working,Good,Nice product ðŸ‘,Good , while running time slightly shaking . We don't no why .. but it's fixed properly,Good | O1289: https://m.media-amazon.com/images/W/WEBP_402378-T2/images/I/31uAkMaOShS._SX300_SY300_QL70_FMwebp_.jpg | P1289: https://www.amazon.in/Crompton-1200mm-Designer-Ceiling-Smoked/dp/B095PWLLY6/ref=sr_1_303?qid=1672923607&s=kitchen&sr=1-303
A1290: B07Y9PY6Y1 | B1290: Sujata Powermatic Plus, Juicer Mixer Grinder with Chutney Jar, 900 Watts, 3 Jars (White) | C1290: Home&Kitchen|Kitchen&HomeAppliances|SmallKitchenAppliances|JuicerMixerGrinders | D1290: â‚¹6,525 | E1290: â‚¹8,820 | F1290: 0.26 | G1290: 4.5 | H1290: 5137 | I1290: Warranty: 1 year warranty provided by the manufacturer from date of purchase|Includes: 1 unit Motor, 1 Jucier attachment, 1 Blender jar, 1 Grinder jar, 1 Chutney jar|Most powerful 9 watts motor with double ball bearings for efficiency, low maintenance and trouble free running for years|Juicer with unique honeycomb filter mesh for finer juice with higher yield|22 rpm operation- retains flavor and aroma of juices and food|9 mins. continuous running- suitable for longer usage|Totally shock-proof and safe|Low maintenance, trouble free running.customer care: 11-45793882 / 27691512 | J1290: AHXQPNDQMOD2RJE2S6KG3CM6QRXA,AHEDAEYXIZIPVLI6HSDRKIGYILCA,AHNDQGC5II2W2NNJDKODYCGFN77A,AFEOPOMJ6P77R4KX2YKC4UXVHCMQ,AEGFHIVVOOMWQ2JRIPHMTSZ2VIYA,AEBIN6NSCXXL32OUISQKEN575X2A,AEAUDCMXHJHTKQNGANQYEVTM5ZYA,AFPWUFA4L6HJ5LJTBDR4J3MKJ4XA | K1290: Arjun A,shwetha murthy,rahul,Jubaida H.,Hemali Thacker,Amazon Customer,Alexis engg and mktg Pvt ltd,Amazon Customer | L1290: R3MKON00OQCF7T,RACP11DCWDX8H,R2AFW2I68NL7DV,R2Z8JARJBUORLB,R12IW90EHDETBO,R23PRYLHN54BOF,R3NY4R1RGDRP6I,R2EKZLAZBSNIGH | M1290: Best mixer juicer,Nice,Best product in this price,Good Product, can buy it.,Very easy to handle and very sturdy mixer,Realy great product... Noone providing such heavy motor.,Good product,Value for Money | N1290: One of the best juicer mixer I have ever used till date. Used almost all renowned brands but this one is class apart. 3rd purchase in the family circle,Nice,It is unique machine it can do everything which we went from a. Juicer machine fine quality of mixing grinder in few seconds and use both domestic or shops and very easy to use and clean I choose it after many machine used it is best all of them.,If u want to take out the juice after several days gap then u can prefer it,bit on the regular basis it is not good because I had taken out mausambi juice from it but it's waste was not containing some juice in it which can give a loss to u. Else it's good.,I have not used juicer thus, 4 stars. But mixer grinder is excellent. Even hard items like coconut ðŸ¥¥ pieces grind in just 3-4 turns. Very happy with the product . Easy to clean. Just waiting to use the juicer though.,Very good experience using this produc from year's.,Very nice products and most powerful motor,Nice Machine meets the purpose as I was looking for a strong performing juicer. its just that. manufacturing quality is also good and sturdy. though I feel the motor is loose fitted as one can feel it hitting both sides inside while cleaning or shifting | O1290: https://m.media-amazon.com/images/I/41yPeG8kXxL._SX300_SY300_QL70_FMwebp_.jpg | P1290: https://www.amazon.in/Plastic-Powermatic-Jar-Juicer-Grinder-Chutney/dp/B07Y9PY6Y1/ref=sr_1_307?qid=1672923607&s=kitchen&sr=1-307
A1291: B0BJ966M5K | B1291: Aquadpure Copper + Mineral RO+UV+UF 10 to 12 Liter RO + UV + TDS ADJUSTER Water Purifier with Copper Charge Technology black & copper Best For Home and Office (Made In India) | C1291: Home&Kitchen|Kitchen&HomeAppliances|WaterPurifiers&Accessories|WaterFilters&Purifiers | D1291: â‚¹4,999 | E1291: â‚¹24,999 | F1291: 0.8 | G1291: 4.6 | H1291: 124 | I1291: RO technology reduces TDS, hardness, and removes pesticides & heavy metals. Eliminates harmful bacteria, viruses, protozoa & cysts|1 year warranty*;10-12 Liter capacity; Booster Pump is required for the functioning of water purifier in case of inlet water pressure being less than 0.3kg/cm sq. Available through our service technician at an additional cost.|Ultra Filtration imparts crystal clear clarity to your drinking water in addition to making is safe from viral & bacterial contaminations* UV+UF removes viruses; Patented Mineral Guard Technology to retain essential minerals in your water|Color: Black and Copper, Capacity: 10-12 liters, Power: 60 watts, Input Water Temperature: 10Ëš to 40ËšC, Operative Input voltage: 100 -300V ac; 50Hz, Material tank type: Food grade engineered plastic; Can be used for TDS upto 1500 ppm. Please use a TDS meter to find out the correct TDS of your water source before buying a water purifier|1 year warranty for electrical parts, except UV Lamp. Warranty starts from date of dispatch. Filters are consumables, get blocked or choked because of water only. If water quality is good filters life will be more, If water quality is bad (More turbidity or more TDS) Filters life will be less. so, not covered in Warranty. Electrical part will be send through; Installation will be completed within 48 to 72 hrs.|Taste Adjuster (TDS) controller enables adjustment of taste depending upon the source of water|12 stage filtrations,12 liter storage, High quality grey & Black color filters. With Active Copper Filter Series;ncludes Ã¢â‚¬â€œ RO Purifier, Pre Filter, Installation accessories, user manual. Installation You need to pay Up-to Rs. 500/- to the technician for installation. | J1291: AHZJHJWFZLYD64GVP4PXVI2F4LXA,AEUCRZPOISXKHXMCZUH6BXTUXUWA,AFL2ICS3EEESPGYLFF7OTVYMLVJA,AG63J3CFIT6RYX32RHHYWRZ2WKKA,AE6EGCFBVJIZEZ4XPPIY3PES2SDQ,AHUZG5YJCM4UWL66ALQ744FD3OOA,AEIKB2XA64MPG7BBXRG4DT57QKPQ,AF4ECPZRARF7SK2GDSBPTINVA2CA | K1291: Manish Mehekare,Rajesh,Nitesh singh,Lalit,Prathamesh poojari,Charan,santhakumar,Nikhil Bhagat | L1291: R410I44U1ORFS,R2EL6RDO42L8HA,R2LMSC4S998NYI,R2RVMZV1I42LGA,ROS3I3HXBLAYE,R2V70PAEVT1EYU,R1GYY0PDUBZVOK,R2180U6SP2A0B1 | M1291: service is excellent, installation guy is very professional, I liked the service,Amazing,Value for money,Nice product,Water is clean and tasty also. Its cleans very well,Good. Happy with the installation,Nice product at affordable price.,Affordable and we'll functioning R.O. | N1291: I like the service most and the product,Note: Writing the product right after installation.Product looks nice and the storage capacity is good enough for a family of 5. The technician is very friendly and installed the product without issues. Will write a detailed review after using the product thoroughly.,It's value for money product.Works fine and installation was on time.,Nice product, and service is also good,Product is very good. Purity of water is excellent.,https://m.media-amazon.com/images/W/WEBP_402378-T1/images/I/71NXtZ0RVWL._SY88.jpg,Product and installation is excellent.must buy item at this range.,Value for money R.O. water dispenserSufficient capacity | O1291: https://m.media-amazon.com/images/W/WEBP_402378-T1/images/I/41ZvKRULvDL._SY445_SX342_QL70_FMwebp_.jpg | P1291: https://www.amazon.in/Aquadpure-Copper-ADJUSTER-Purifier-Technology/dp/B0BJ966M5K/ref=sr_1_308?qid=1672923607&s=kitchen&sr=1-308
A1292: B086GVRP63 | B1292: Amazon Basics 650 Watt Drip Coffee Maker with Borosilicate Carafe | C1292: Home&Kitchen|Kitchen&HomeAppliances|Coffee,Tea&Espresso|DripCoffeeMachines | D1292: â‚¹1,189 | E1292: â‚¹2,400 | F1292: 0.5 | G1292: 4.1 | H1292: 618 | I1292: Compact & powerful 650 watt drip coffee maker for home and office use;Brews up to 5 cups at a time (25 ounces or 740 ml)|Premium quality materials are food grade with a glass borosilicate carafe;Reusable filter and removable filter basket is convenient and does not require additional paper filters|Auto keep warm function is ideal for instant, anytime coffee;Easy to use & set up|Please Note: Carafe is to be hand washed (not dishwasher safe);Package Contents:- 1 x 650 W Drip Coffee Maker with Borosilicate Carafe|Color Name: Black; Material Type: Metal; Size Name: Standard | J1292: AH6NXC2M3PH6OZHLJ6YXG54VIBMA,AGSDBEOHKXCL3WBEIN5VEZK4JY4A,AFCHIB73U3D4VQHZCH4MV2Z5FESA,AGLFKVLO32UB72C43CQNOPGQVKGA,AHBUPKENA77XVDAUGWUHVZLCKSEA,AEY34MNYOS24F3P7Q3IGMQVH3ZUA,AHMBANCEQ5AJOQVPFHONG2QTDE7Q,AFNQQLFJGPPNZCI6BVYZCEAZQZQQ | K1292: Subhajit Sadhu,Indrajit Sarkar,Ashwath,Dorje,Harish R.,Jana,Amazon Customer,Viknesh Harren | L1292: R3NLWGZTKSITSC,R1NCNL2F8KAM4L,R32I8HG9OTUY0V,R1Y6YHN4M285CN,RIR2EVLB3KG1Q,R2KUZ1CLHNTJAY,R27RDEPJ1W7VOQ,RQWPQXKORWT5I | M1292: Okay to use,Good value for a well finished product - recommended,Do not buy this product,Better than expected.,Best carafe from amazon,Build quality is not that great,Replacement parts not available or sold for twice as much as the value of the entire product,Good product | N1292: The pricing is good, using is very easy but the product is not too much worth to buy.,I have been using a similar coffee percolator for over 20 years now - and my old workhorse, a Chinese (Nova) is still capable. Since it was white, and therefore a very unappetising sight now, I needed a new one.Packaging: The design of packaging was perfect - stiff corrugated sandwich board box, foam profiled panels stuck on board for bottom and top, board wrapping around the glass kettle, the whole unit inside a thick ply cover. Frankly, this sort of packaging is more common in high end audio equipment. 5 * plus for the packaging design.Size: This is a small machine - and will make about 600 ml of coffee - sufficient for 2 mugs in one go. If you need a larger volume - look elsewhere.Body and finish: The plastic body is well made - the matte finish looks good. The bottom metal plate is seamless and black - will have to wait and see when spots appear. The kettle is good quality glass, and though no branding is present, feels thick enough to withstand minor washing bumps. The filter bucket and the holder with the flow control spring is OK - hopefully the spring and washer - which are fixed - will last. The lid moves smoothly and the hinges and the sprinkler also look sturdy. Switch is firm.Function: It worked very well on the first use. I had used an extra coffee filter paper on top of the nylon filter bucket. The flow was smooth. Coffee liquor starts weak, and then picks up strength. The drip stops well with the removal of the kettle - and though the manual cautiously states a 10 sec gap for drip stop, I did not find any leakage on longer removal.Overall: Very satisfied with my new coffee maker. Recommend buying.,Product doesnâ€™t work within a month,Easy to use, and it turned out better than I expected it to be for the price.,Just Magnificent. Saves lot of time.,The plastic quality for this product is poor. It feels like a toy. I had bought a Amazon basics air fryer it had great build quality comparing to this Amazon basics product,If you try to find a replacement part it costs twice its value,its cheap and breakable. And the coffee is very very light,waste of coffee and also not a good flavour.,Nice product and simple to use | O1292: https://m.media-amazon.com/images/I/41EuzetRjTL._SX300_SY300_QL70_FMwebp_.jpg | P1292: https://www.amazon.in/AmazonBasics-Drip-Coffee-Maker-Black/dp/B086GVRP63/ref=sr_1_309?qid=1672923607&s=kitchen&sr=1-309
A1293: B08MVXPTDG | B1293: Crompton Insta Delight Fan Circulator Room Heater with 3 Heat Settings (Slate Grey & Black, 2000 Watt) | C1293: Home&Kitchen|Heating,Cooling&AirQuality|RoomHeaters|FanHeaters | D1293: â‚¹2,590 | E1293: â‚¹4,200 | F1293: 0.38 | G1293: 4.1 | H1293: 63 | I1293: Tapping into a natural phenomenon known as â€œconvectionâ€ InstaDelight|Circulates air through a fan after passing it through the heating element|Its easy portability and multiple heat settings makes it a quintessential appliance on a chilly day|Comes with a 3-heat setting and turbo fan design to spread heat quickly in the room|Powered for over heat protection and height adjustable stand for comfort with ease of use|An ISI approved product powered with shock proof body and a carrying handle|Warranty: 1 years warranty provided by crompton from date of purchase, covers on manufacturing defects kindly read the usermanual for more details | J1293: AGYS2OMZE7DCEFQOBUJ7OSMPG3DQ,AF56UQ52OFSZL2KX2TPXPHBSNZ3Q,AFCOSVW2NHSFLPG7O5EKP2YRUERQ,AENAIK2GP3PTBWPAWBEFRET5BZ3Q,AH5CZZYZK64I4UNJA35AVYAY3SLA,AEPFMS33QLD2SPSAW7OBES4S5MTA,AEQBRKHWGFEJSWMMD7NCRL47IAUQ,AGQKV65KDMYKBD6ZQTXSQ74VID4A | K1293: Kanwar Singh,mukesh bajpai,Deepak Kumar,sreekanth veerla,Divyesh Patel,Jitendra Kumar singh,MAHESH L,Amazon Customer | L1293: R1KQ8JLFP0TG78,R1NBW7YR79U41D,R3J7GSQFAQVB31,RBQNYREQ6R6XW,RSL0KWN4H04GJ,R2NZ0UNFFXKZUB,R23D039HGB5VNX,R12EIACNZU7VVH | M1293: no,Good and reliable product ðŸ‘,Overall very fine Quality,Useful product helped my family a lot in winter,Operating switch is too hard for aged person,Sabse badhiya,Good product,Good product at this price | N1293: no,There should be a fan speed control option.,Overall very good,Little noisy but expected,Fan is slightly noiseOperating switch is too hard for aged person,Best in market,Good product. easy to use.,Received 2 days ago, looks, color r good. Heating nice, 3 adjustments for heating 660W 1200W 2000W, whichever u requireNo auto cut or over-heat protection available | O1293: https://m.media-amazon.com/images/I/31vL9-jaaJL._SX300_SY300_QL70_FMwebp_.jpg | P1293: https://www.amazon.in/Crompton-Delight-Circulator-Heater-Settings/dp/B08MVXPTDG/ref=sr_1_311?qid=1672923607&s=kitchen&sr=1-311
... A1466: B01486F4G6 | B1466: Borosil Jumbo 1000-Watt Grill Sandwich Maker (Black) | C1466: Home&Kitchen|Kitchen&HomeAppliances|SmallKitchenAppliances|SandwichMakers | D1466: â‚¹2,863 | E1466: â‚¹3,690 | F1466: 0.22 | G1466: 4.3 | H1466: 6987 | I1466: Brand-Borosil, Specification Ã¢â‚¬â€œ 23V ~ 5Hz;1 W Power for Faster Grilling|Makes 2 Sandwiches in minutes;Stainless Steel Mirror Finish Body; Easy to use;Easy to clean coated plates|Auto-lock latch;Larger deep ribbed grill plates for Krisp grilling|Rubber feet to avoid slipping on Countertop;Indicator Display.|Material Type: Plastic|Suitable for gifting on Diwali and other special occasions. | J1466: AFGW5PT3R6ZAVQR4Y5MWVAKBZAYA,AG7QNJ2SCS5VS5VYYBNV4HDSIJ4Q,AFUDGN5MEXLKUULNTM7Y2G5P7TYA,AHXCDNSXAESERITAFELQABFVNLCA,AGRZD6CHLCUNOLMMIMIHUCG7PIFA,AFQZVGSOSOJHKFQQMCEI4725QEKQ,AEALVGXXIP46OZVXKRUXSDWZJMEA,AGEFL3AY7YXEFZA4ZJU3LP7K7OJQ | K1466: Rajib,Ajay B,Vikas Kahol,PARDEEP,Anindya Pramanik,Vikas Singh,Harshada Pimple,Saw a. | L1466: R20RBRZ0WEUJT9,ROKIFK9R2ISSE,R30EEG2FNJSN5I,R2ZC03S4QXOW4Y,R186H8YW34BQD5,R10NC3D321N59G,REKF75G4SOAOX,R2G0ZT4JQX322I | M1466: Works perfect,Ok good product,Nice Product. Recommend it. But cleaning its exterior is cumbersome.,Excellent productâœŒ,A good product for household use,à¤®à¥à¤à¥‡ à¤¬à¤¿à¤²à¥à¤•à¥à¤² à¤­à¥€ à¤®à¤œà¤¾ à¤¨à¤¹à¥€à¤‚ à¤†à¤¯à¤¾ à¤”à¤° à¤µà¤¾à¤ªà¤¸ à¤•à¤° à¤¦à¤¿à¤¯à¤¾à¥¤,Best product,Good | N1466: It does it job perfectly..only issue is temp control is not perfect . U need to keep checking the browness of sandwich untill it gets upto ur choise,Product is good, but the control knob is to be be modified cause after the cooking process completes the control knob should be return back to initial starting place. If not that process timer should be given basically. So think well what happens whether didn't had atleast one option.Not a indicator option.,It is a nice product, easy to use. The grilling function is also wonderful. But the exterior metallic finish picks up finger marks and other spots which tend to become permanent. Cleaning them is almost impossible.,Very good product,This is a pretty powerful sandwich maker, for home use. The product looks good, has a sturdy build, and heats up quick. The sandwiches are made pretty quickly, without burning.,à¤¬à¥‹à¤°à¥‹à¤¸à¤¿à¤² à¤¬à¥à¤°à¤¾à¤‚à¤¡ à¤•à¤¾ à¤¯à¤¹ "à¤¸à¥‡à¤‚à¤¡à¤µà¤¿à¤š à¤®à¥‡à¤•à¤°" à¤¦à¥‡à¤–à¤¨à¥‡ à¤®à¥‡à¤‚ à¤¤à¥‹ à¤…à¤šà¥à¤›à¤¾ à¤²à¤—à¤¤à¤¾ à¤¹à¥ˆ à¤®à¤—à¤° à¤‡à¤¸à¤•à¥€ à¤¬à¤¿à¤²à¥à¤¡ à¤•à¥à¤µà¤¾à¤²à¤¿à¤Ÿà¥€ à¤…à¤šà¥à¤›à¥€ à¤¨à¤¹à¥€à¤‚ à¤¹à¥ˆà¥¤ à¤¯à¤¹ à¤²à¤—à¤­à¤— Rs 3000 à¤•à¥‡ à¤†à¤¸à¤ªà¤¾à¤¸ à¤†à¤¤à¤¾ à¤¹à¥ˆà¥¤ à¤‡à¤¸ à¤ªà¥à¤°à¤•à¤¾à¤° à¤•à¥€ à¤¬à¤¿à¤²à¥à¤¡ à¤•à¥à¤µà¤¾à¤²à¤¿à¤Ÿà¥€ â‚¹2000 à¤•à¥‡ à¤•à¤°à¥€à¤¬ à¤®à¤¿à¤² à¤œà¤¾à¤¤à¥€ à¤¹à¥ˆ à¤¤à¥‹ à¤•à¥‹à¤ˆ à¤•à¥à¤¯à¥‹à¤‚ â‚¹1000 à¤…à¤§à¤¿à¤• à¤­à¥à¤—à¤¤à¤¾à¤¨ à¤•à¤°à¥‡à¤‚à¥¤ à¤ªà¤¹à¤²à¥‡ à¤®à¥ˆà¤‚à¤¨à¥‡ à¤‡à¤¸à¥‡ review à¤¦à¥‡à¤–à¤¨à¥‡ à¤•à¥‡ à¤¬à¤¾à¤¦ à¤‘à¤°à¥à¤¡à¤° à¤•à¤¿à¤¯à¤¾ à¤¥à¤¾ à¤²à¥‡à¤•à¤¿à¤¨ à¤œà¤¬ à¤˜à¤° à¤ªà¤° à¤¡à¤¿à¤²à¥€à¤µà¤°à¥€ à¤¹à¥‹à¤¨à¥‡ à¤•à¥‡ à¤ªà¤¶à¥à¤šà¤¾à¤¤ unboxing à¤•à¤°à¤•à¥‡ à¤¦à¥‡à¤–à¤¾ à¤¤à¥‹ à¤‡à¤¸à¤•à¥€ à¤¬à¤¿à¤²à¥à¤¡ à¤•à¥à¤µà¤¾à¤²à¤¿à¤Ÿà¥€ à¤•à¥à¤› à¤–à¤¾à¤¸ à¤¨à¤¹à¥€à¤‚ à¤²à¤—à¥€ à¤‡à¤¸à¤²à¤¿à¤ à¤…à¤ªà¤¨à¥‡ à¤ªà¥ˆà¤¸à¥‡ à¤¬à¤šà¤¾à¤¨à¥‡ à¤•à¥‡ à¤²à¤¿à¤ à¤®à¥ˆà¤‚à¤¨à¥‡ à¤‡à¤¸à¥‡ à¤µà¤¾à¤ªà¤¸ à¤­à¥‡à¤œ à¤¦à¤¿à¤¯à¤¾à¥¤ à¤®à¥ˆà¤‚à¤¨à¥‡ à¤‡à¤¸à¤•à¥€ à¤ªà¥ˆà¤•à¥‡à¤œà¤¿à¤‚à¤—, à¤®à¥ˆà¤¨à¥à¤…à¤² à¤”à¤° à¤¸à¥ˆà¤‚à¤¡à¤µà¤¿à¤š à¤®à¥‡à¤•à¤° à¤•à¥€ à¤«à¥‹à¤Ÿà¥‹à¤—à¥à¤°à¤¾à¤« à¤†à¤ª à¤¸à¤­à¥€ à¤¸à¥‡ à¤¶à¥‡à¤¯à¤° à¤•à¥€ à¤¹à¥ˆà¥¤ à¤†à¤ª à¤¸à¥à¤µà¤¯à¤‚ à¤¦à¥‡à¤– à¤•à¥‡ à¤…à¤¨à¥à¤®à¤¾à¤¨ à¤²à¤—à¤¾ à¤¸à¤•à¤¤à¥‡ à¤¹à¥ˆà¤‚à¥¤,Recommend work as expected,Its easy tp use | O1466: https://m.media-amazon.com/images/W/WEBP_402378-T1/images/I/51J2Wk-+c+L._SY300_SX300_.jpg | P1466: https://www.amazon.in/Borosil-Jumbo-1000-Watt-Grill-Sandwich/dp/B01486F4G6/ref=sr_1_506?qid=1672923617&s=kitchen&sr=1-506

Sheet Clean_Data
A1: product_id | B1: product_name | C1: category | D1: Main_Category | E1: Reliability_Flag | F1: discounted_price | G1: actual_price | H1: Price_Band | I1: discount_percentage | J1: Discount_Bucket | K1: rating | L1: rating_count | M1: Rating_Tier | N1: about_product | O1: user_id | P1: user_name | Q1: review_id | R1: review_title | S1: review_content | T1: img_link | U1: product_link
A2: B07JW9H4J1 | B2: Wayona Nylon Braided USB to Lightning Fast Charging and Data Sync Cable Compatible for iPhone 13, 12,11, X, 8, 7, 6, 5, iPad Air, Pro, Mini (3 FT Pack of 1, Grey) | C2: Computers&Accessories|Accessories&Peripherals|Cables&Accessories|Cables|USBCables | D2: =LEFT(C2, FIND("|",C2)-1) -> Computers&Accessories | E2: =IF(COUNTIF($D$2:$D$1466,$D2)<10,"Small Sample (<10)",IF(COUNTIF($D$2:$D$1466,$D2)<50,"Caution (10-50)","Reliable (50+)")) -> Reliable (50+) | F2: 399 | G2: 1099 | H2: =IF(F2<=200,"Under ₹200",IF(F2<=500,"₹200-500",IF(F2<=1500,"₹500-1500","₹1500+"))) -> ₹200-500 | I2: 0.64 | J2: =IF(I2<=0.3,"0-30%",IF(I2<=0.5,"31-50%",IF(I2<=0.7,"51-70%","71%+"))) -> 51-70% | K2: 4.2 | L2: 24269 | M2: =IF(L2<1000,"Low (<1k)",IF(L2<=10000,"Medium (1k-10k)","High (10k+)")) -> High (10k+) | N2: High Compatibility : Compatible With iPhone 12, 11, X/XsMax/Xr ,iPhone 8/8 Plus,iPhone 7/7 Plus,iPhone 6s/6s Plus,iPhone 6/6 Plus,iPhone 5/5s/5c/se,iPad Pro,iPad Air 1/2,iPad mini 1/2/3,iPod nano7,iPod touch and more apple devices.|Fast Charge&Data Sync : It can charge and sync simultaneously at a rapid speed, Compatible with any charging adaptor, multi-port charging station or power bank.|Durability : Durable nylon braided design with premium aluminum housing and toughened nylon fiber wound tightly around the cord lending it superior durability and adding a bit to its flexibility.|High Security Level : It is designed to fully protect your device from damaging excessive current.Copper core thick+Multilayer shielding, Anti-interference, Protective circuit equipment.|WARRANTY: 12 months warranty and friendly customer services, ensures the long-time enjoyment of your purchase. If you meet any question or problem, please don't hesitate to contact us. | O2: AG3D6O4STAQKAY2UVGEUV46KN35Q,AHMY5CWJMMK5BJRBBSNLYT3ONILA,AHCTC6ULH4XB6YHDY6PCH2R772LQ,AGYHHIERNXKA6P5T7CZLXKVPT7IQ,AG4OGOFWXJZTQ2HKYIOCOY3KXF2Q,AENGU523SXMOS7JPDTW52PNNVWGQ,AEQJHCVTNINBS4FKTBGQRQTGTE5Q,AFC3FFC5PKFF5PMA52S3VCHOZ5FQ | P2: Manav,Adarsh gupta,Sundeep,S.Sayeed Ahmed,jaspreet singh,Khaja moin,Anand,S.ARUMUGAM | Q2: R3HXWT0LRP0NMF,R2AJM3LFTLZHFO,R6AQJGUP6P86,R1KD19VHEDV0OR,R3C02RMYQMK6FC,R39GQRVBUZBWGY,R2K9EDOE15QIRJ,R3OI7YT648TL8I | R2: Satisfied,Charging is really fast,Value for money,Product review,Good quality,Good product,Good Product,As of now seems good | S2: Looks durable Charging is fine tooNo complains,Charging is really fast, good product.,Till now satisfied with the quality.,This is a good product . The charging speed is slower than the original iPhone cable,Good quality, would recommend,https://m.media-amazon.com/images/W/WEBP_402378-T1/images/I/81---F1ZgHL._SY88.jpg,Product had worked well till date and was having no issue.Cable is also sturdy enough...Have asked for replacement and company is doing the same...,Value for money | T2: https://m.media-amazon.com/images/W/WEBP_402378-T1/images/I/51UsScvHQNL._SX300_SY300_QL70_FMwebp_.jpg | U2: https://www.amazon.in/Wayona-Braided-WN3LG1-Syncing-Charging/dp/B07JW9H4J1/ref=sr_1_1?qid=1672909124&s=electronics&sr=1-1
A3: B098NS6PVG | B3: Ambrane Unbreakable 60W / 3A Fast Charging 1.5m Braided Type C Cable for Smartphones, Tablets, Laptops & other Type C devices, PD Technology, 480Mbps Data Sync, Quick Charge 3.0 (RCT15A, Black) | C3: Computers&Accessories|Accessories&Peripherals|Cables&Accessories|Cables|USBCables | D3: =LEFT(C3, FIND("|",C3)-1) -> Computers&Accessories | E3: =IF(COUNTIF($D$2:$D$1466,$D3)<10,"Small Sample (<10)",IF(COUNTIF($D$2:$D$1466,$D3)<50,"Caution (10-50)","Reliable (50+)")) -> Reliable (50+) | F3: 199 | G3: 349 | H3: =IF(F3<=200,"Under ₹200",IF(F3<=500,"₹200-500",IF(F3<=1500,"₹500-1500","₹1500+"))) -> Under ₹200 | I3: 0.43 | J3: =IF(I3<=0.3,"0-30%",IF(I3<=0.5,"31-50%",IF(I3<=0.7,"51-70%","71%+"))) -> 31-50% | K3: 4 | L3: 43994 | M3: =IF(L3<1000,"Low (<1k)",IF(L3<=10000,"Medium (1k-10k)","High (10k+)")) -> High (10k+) | N3: Compatible with all Type C enabled devices, be it an android smartphone (Mi, Samsung, Oppo, Vivo, Realme, OnePlus, etc), tablet, laptop (Macbook, Chromebook, etc)|Supports Quick Charging (2.0/3.0)|Unbreakable â€“ Made of special braided outer with rugged interior bindings, it is ultra-durable cable that wonâ€™t be affected by daily rough usage|Ideal Length â€“ It has ideal length of 1.5 meters which is neither too short like your typical 1meter cable or too long like a 2meters cable|Supports maximum 3A fast charging and 480 Mbps data transfer speed|6 months manufacturer warranty from the date of purchase | O3: AECPFYFQVRUWC3KGNLJIOREFP5LQ,AGYYVPDD7YG7FYNBXNGXZJT525AQ,AHONIZU3ICIEHQIGQ6R2VFRSBXOQ,AFPHD2CRPDZMWMBL7WXRSVYWS5JA,AEZ346GX3HJ4O4XNRPHCNHXQURMQ,AEPSWFPNECKO34PUC7I56ITGXR6Q,AHWVEHR5DYLVFTO2KF3IZATFQSWQ,AH4QT33M55677I7ISQOAKEQWACYQ | P3: ArdKn,Nirbhay kumar,Sagar Viswanathan,Asp,Placeholder,BharanI,sonia,Niam | Q3: RGIQEG07R9HS2,R1SMWZQ86XIN8U,R2J3Y1WL29GWDE,RYGGS0M09S3KY,R17KQRUTAN5DKS,R3AAQGS6HP2QUK,R1HDNOG6TO2CCA,R3PHKXYA5AFEOU | R3: A Good Braided Cable for Your Type C Device,Good quality product from ambrane,Super cable,As,Good quality,Good product,its good,Good quality for the price but one issue with my unit | S3: I ordered this cable to connect my phone to Android Auto of car. The cable is really strong and the connection ports are really well made. I already has a Micro USB cable from Ambrane and it's still in good shape. I connected my phone to the car using the cable and it got connected well and no issues. I also connected it to the charging port and yes it has Fast Charging support.,It quality is good at this price and the main thing is that i didn't ever thought that this cable will be so long it's good one and charging power is too good and also supports fast charging,Value for money, with extra lengthðŸ‘,Good, working fine,Product quality is good,Good,very good,Bought for my daughter's old phone.Brand new cable it was not charging, I already repacked and requested for replacement.I checked again, and there was some green colour paste/fungus inside the micro USB connector. I cleaned with an alcoholic and starts working again.Checked the ampere of charging speed got around 1400ma-1500ma - not bad, came with braided 1.5m long cable, pretty impressive for the price.Can't blame the manufacturer.But quality issues by the distributor, they might have stored in very humid place. | T3: https://m.media-amazon.com/images/W/WEBP_402378-T2/images/I/31zOsqQOAOL._SY445_SX342_QL70_FMwebp_.jpg | U3: https://www.amazon.in/Ambrane-Unbreakable-Charging-Braided-Cable/dp/B098NS6PVG/ref=sr_1_2?qid=1672909124&s=electronics&sr=1-2
A4: B096MSW6CT | B4: Sounce Fast Phone Charging Cable & Data Sync USB Cable Compatible for iPhone 13, 12,11, X, 8, 7, 6, 5, iPad Air, Pro, Mini & iOS Devices | C4: Computers&Accessories|Accessories&Peripherals|Cables&Accessories|Cables|USBCables | D4: =LEFT(C4, FIND("|",C4)-1) -> Computers&Accessories | E4: =IF(COUNTIF($D$2:$D$1466,$D4)<10,"Small Sample (<10)",IF(COUNTIF($D$2:$D$1466,$D4)<50,"Caution (10-50)","Reliable (50+)")) -> Reliable (50+) | F4: 199 | G4: 1899 | H4: =IF(F4<=200,"Under ₹200",IF(F4<=500,"₹200-500",IF(F4<=1500,"₹500-1500","₹1500+"))) -> Under ₹200 | I4: 0.9 | J4: =IF(I4<=0.3,"0-30%",IF(I4<=0.5,"31-50%",IF(I4<=0.7,"51-70%","71%+"))) -> 71%+ | K4: 3.9 | L4: 7928 | M4: =IF(L4<1000,"Low (<1k)",IF(L4<=10000,"Medium (1k-10k)","High (10k+)")) -> Medium (1k-10k) | N4: ã€ Fast Charger& Data Syncã€‘-With built-in safety proctections and four-core copper wires promote maximum signal quality and strength and enhance charging & data transfer speed with up to 480 mb/s transferring speed.|ã€ Compatibilityã€‘-Compatible with iPhone 13, 12,11, X, 8, 7, 6, 5, iPad Air, Pro, Mini & iOS devices.|ã€ Sturdy & Durableã€‘-The jacket and enforced connector made of TPE and premium copper, are resistant to repeatedly bending and coiling.|ã€ Ultra High Qualityã€‘: According to the experimental results, the fishbone design can accept at least 20,000 bending and insertion tests for extra protection and durability. Upgraded 3D aluminum connector and exclusive laser welding technology, which to ensure the metal part won't break and also have a tighter connection which fits well even with a protective case on and will never loose connection.|ã€ Good After Sales Serviceã€‘-Our friendly and reliable customer service will respond to you within 24 hours ! you can purchase with confidence,and every sale includes a 365-day worry-free Service to prove the importance we set on quality. | O4: AGU3BBQ2V2DDAMOAKGFAWDDQ6QHA,AESFLDV2PT363T2AQLWQOWZ4N3OA,AHTPQRIMGUD4BYR5YIHBH3CCGEFQ,AEUVWXYP5LT7PZLLZENEO2NODPBQ,AHC7MPW55DOO6WNCOQVA2VHOD26A,AFDI6FRPFBTNBG7BAEB7JDJSMKDQ,AFQKCEEEKXCOHTDG4WUN3XPPHJQQ,AHKUUFNMBZIDLSSPA4FEHIO2EC7Q | P4: Kunal,Himanshu,viswanath,sai niharka,saqib malik,Aashiq,Ramu Challa,Sanjay gupta | Q4: R3J3EQQ9TZI5ZJ,R3E7WBGK7ID0KV,RWU79XKQ6I1QF,R25X4TBMPY91LX,R27OK7G99VK0TR,R207CYDCHJJTCJ,R3PCU8XMU173BT,R1IMONDOWRNU5V | R4: Good speed for earlier versions,Good Product,Working good,Good for the price,Good,Worth for money,Working nice,it's a really nice product | S4: Not quite durable and sturdy,https://m.media-amazon.com/images/W/WEBP_402378-T1/images/I/71rIggrbUCL._SY88.jpg,Working good,https://m.media-amazon.com/images/W/WEBP_402378-T1/images/I/61bKp9YO6wL._SY88.jpg,Product,Very nice product,Working well,It's a really nice product | T4: https://m.media-amazon.com/images/W/WEBP_402378-T1/images/I/31IvNJZnmdL._SY445_SX342_QL70_FMwebp_.jpg | U4: https://www.amazon.in/Sounce-iPhone-Charging-Compatible-Devices/dp/B096MSW6CT/ref=sr_1_3?qid=1672909124&s=electronics&sr=1-3
A5: B08HDJ86NZ | B5: boAt Deuce USB 300 2 in 1 Type-C & Micro USB Stress Resistant, Tangle-Free, Sturdy Cable with 3A Fast Charging & 480mbps Data Transmission, 10000+ Bends Lifespan and Extended 1.5m Length(Martian Red) | C5: Computers&Accessories|Accessories&Peripherals|Cables&Accessories|Cables|USBCables | D5: =LEFT(C5, FIND("|",C5)-1) -> Computers&Accessories | E5: =IF(COUNTIF($D$2:$D$1466,$D5)<10,"Small Sample (<10)",IF(COUNTIF($D$2:$D$1466,$D5)<50,"Caution (10-50)","Reliable (50+)")) -> Reliable (50+) | F5: 329 | G5: 699 | H5: =IF(F5<=200,"Under ₹200",IF(F5<=500,"₹200-500",IF(F5<=1500,"₹500-1500","₹1500+"))) -> ₹200-500 | I5: 0.53 | J5: =IF(I5<=0.3,"0-30%",IF(I5<=0.5,"31-50%",IF(I5<=0.7,"51-70%","71%+"))) -> 51-70% | K5: 4.2 | L5: 94363 | M5: =IF(L5<1000,"Low (<1k)",IF(L5<=10000,"Medium (1k-10k)","High (10k+)")) -> High (10k+) | N5: The boAt Deuce USB 300 2 in 1 cable is compatible with smartphones, tablets, PC peripherals, Bluetooth speakers, power banks and all other devices with Type-C as well as Micro USB port|It ensures 3A fast charging and data transmissions with rapid sync at 480 mbps|The premium Nylon braided skin makes it sturdy and invincible against external damage|Its Aluminium alloy shell housing makes it last longer with 10000+ Bends Lifespan with extended frame protection for strain relief|The resilient and flexible design offers a tangle free experience seamlessly|Deuce USB 300 cable offers a perfect 1.5 meters in length for smooth & hassle-free user experience|2 years warranty from the date of purchase | O5: AEWAZDZZJLQUYVOVGBEUKSLXHQ5A,AG5HTSFRRE6NL3M5SGCUQBP7YSCA,AH725ST5NW2Y4JZPKUNTIJCUK2BA,AHV3TXIFCJPMS4D5JATCEUR266MQ,AGWIGDEMFIIUAOXYY2QATNBSUGHA,AFSTSLQUV4EVEXWKBOLEFHL2H5YQ,AGAKDNBHY2FKX7I4ACRGILU7QL7A,AFNWJUWJRHCC6HN52KMG5AKZY37Q | P5: Omkar dhale,JD,HEMALATHA,Ajwadh a.,amar singh chouhan,Ravi Siddan,Himanshu Goel,Udaykumar | Q5: R3EEUZKKK9J36I,R3HJVYCLYOY554,REDECAZ7AMPQC,R1CLH2ULIVG5U3,R2DMKIBGFKBD6R,RC89B5IAJUTR5,R3B3DDON5FH8DS,R13WAEJDI5RS36 | R5: Good product,Good one,Nice,Really nice product,Very first time change,Good,Fine product but could be better,Very nice it's charging like jet | S5: Good product,long wire,Charges good,Nice,I bought this cable for Rs.339 worthy product for this price, i tested it in various charger adapters 33w and 18w it supports fast charging as well.,Good,Ok,I had got this at good price on sale on Amazon and product is useful with warranty but for warranty you need to go very far not practical for such a cost and mine micro to type c connector stopped working after few days only.,I like this product | T5: https://m.media-amazon.com/images/I/41V5FtEWPkL._SX300_SY300_QL70_FMwebp_.jpg | U5: https://www.amazon.in/Deuce-300-Resistant-Tangle-Free-Transmission/dp/B08HDJ86NZ/ref=sr_1_4?qid=1672909124&s=electronics&sr=1-4
A6: B08CF3B7N1 | B6: Portronics Konnect L 1.2M Fast Charging 3A 8 Pin USB Cable with Charge & Sync Function for iPhone, iPad (Grey) | C6: Computers&Accessories|Accessories&Peripherals|Cables&Accessories|Cables|USBCables | D6: =LEFT(C6, FIND("|",C6)-1) -> Computers&Accessories | E6: =IF(COUNTIF($D$2:$D$1466,$D6)<10,"Small Sample (<10)",IF(COUNTIF($D$2:$D$1466,$D6)<50,"Caution (10-50)","Reliable (50+)")) -> Reliable (50+) | F6: 154 | G6: 399 | H6: =IF(F6<=200,"Under ₹200",IF(F6<=500,"₹200-500",IF(F6<=1500,"₹500-1500","₹1500+"))) -> Under ₹200 | I6: 0.61 | J6: =IF(I6<=0.3,"0-30%",IF(I6<=0.5,"31-50%",IF(I6<=0.7,"51-70%","71%+"))) -> 51-70% | K6: 4.2 | L6: 16905 | M6: =IF(L6<1000,"Low (<1k)",IF(L6<=10000,"Medium (1k-10k)","High (10k+)")) -> High (10k+) | N6: [CHARGE & SYNC FUNCTION]- This cable comes with charging & Data sync function|[HIGH QUALITY MATERIAL]- TPE + Nylon Material to make sure that the life of the cable is enhanced significantly|[LONG CORD]- The Cable is extra thick 1.2 meter long, optimized for an easy use for your comfort at home or office|[MORE DURABLE]-This cable is unique interms of design and multi-use and is positioned to provide the best comfort and performance while using|[UNIVERSAL COMPATIBILITY]- Compatible with all devices like iPhone XS, X, XR, 8, 7, 6S, 6, 5S, iPad Pro, iPad mini and iPad Air | O6: AE3Q6KSUK5P75D5HFYHCRAOLODSA,AFUGIFH5ZAFXRDSZHM4QB2KPKFUQ,AFK4NJOLFSJGWLOJIUIAROJF6YVA,AFUOTYRFUXVPEBGIXVZZ7DR3CZUA,AFDLRSXKDZ6U3U3KD46SQLFGZQRA,AH5VLM66SIK7J3IRG4NY7XVOQ55A,AE3MQNNHHLUHXURL5S7IAR7JTGNQ,AFSEOFZY67MYC7UAJU264Z5NFTLA | P6: rahuls6099,Swasat Borah,Ajay Wadke,Pranali,RVK,Bhargav,Durai Vignesh,Amazon Customer | Q6: R1BP4L2HH9TFUP,R16PVJEXKV6QZS,R2UPDB81N66T4P,R3KK4GT934ST3I,RCFHMWUSBIJO,RDO7DACXMAJ84,R3A6MEZL3LY66Z,R1ESIEKPGAYA29 | R6: As good as original,Decent,Good one for secondary use,Best quality,GOOD,Amazing product at a mind blowing price!,Nice Quality,Good product | S6: Bought this instead of original apple, does the work for 150rs, not as fast as apple charger but its a good option if you want cheap and good product, bought it for iPad pro 10.5 and it's working flawlessly, build quality is ok, its not like i am gonna hang my clothes on it and i want a very strong cable, even a braided cable stop working after a year, i have used both Anker and Apple store strong braided cable they all stop working after a year so please don't buy high end cables just for that instead choose a this one and even if it's stops working withing a year you only loose 150rs compares to 2000rs.UPDATE------------------------------------pin has stopped charging from one side, now i have to slip the pin to charge from other side, but i will update and let know for how long does it work,,Itâ€™s good. Not sure about durability as the pin area feels a bit fragile,Does not support apple carplaySo was little disappointed about thatOther than that cable is made up of very good quality,Best to buy,100% NOT FATHFUL,Writing this review post 10 months and 3 orders of the same product.Honestly Portronics Konnect L lightning cable works like magic with the original Apple charging brick.Seeing the price of the cable I initially hesitated buying as it was as low as 99/- with the offers and so I wasnâ€™t sure if it would work well with my iPhone 12 or whether it would impact my iPhoneâ€™s battery health because all the other lightning cable brands were costing over 350/- like Wayona, Amazon Basics, etc.Earlier I was using Wayona Brand lightning cable with eventually frayed and stopped working.Charging Speed:Charges my iPhone fast enough almost similar compared to the original cable level when used with 12W Original Apple power adapter.Quality and Durability:Great quality braided cable and doesnâ€™t tangle easily and can withstand day-to-day usage.L-Shaped pin:This is very innovative by Portronics and it makes sure the cable doesnâ€™t get damaged even if used while charging.CarPlay and Data Sync:Works smoothly with CarPlay and syncs data effortlessly.PS: I have used this cable only with the Original Apple Charging Brick and extremely satisfied with its performance.,Better than I expect the product I like that Quality and I plan to buy same type cable come with usb C to Lighting cable for emergency purpose that much I love this cable. Buy for this cable only emergency uses only since Good one,Good product and value for money | T6: https://m.media-amazon.com/images/W/WEBP_402378-T2/images/I/31VzNhhqifL._SX300_SY300_QL70_FMwebp_.jpg | U6: https://www.amazon.in/Portronics-Konnect-POR-1080-Charging-Function/dp/B08CF3B7N1/ref=sr_1_5?qid=1672909124&s=electronics&sr=1-5
A7: B08Y1TFSP6 | B7: pTron Solero TB301 3A Type-C Data and Fast Charging Cable, Made in India, 480Mbps Data Sync, Strong and Durable 1.5-Meter Nylon Braided USB Cable for Type-C Devices for Charging Adapter (Black) | C7: Computers&Accessories|Accessories&Peripherals|Cables&Accessories|Cables|USBCables | D7: =LEFT(C7, FIND("|",C7)-1) -> Computers&Accessories | E7: =IF(COUNTIF($D$2:$D$1466,$D7)<10,"Small Sample (<10)",IF(COUNTIF($D$2:$D$1466,$D7)<50,"Caution (10-50)","Reliable (50+)")) -> Reliable (50+) | F7: 149 | G7: 1000 | H7: =IF(F7<=200,"Under ₹200",IF(F7<=500,"₹200-500",IF(F7<=1500,"₹500-1500","₹1500+"))) -> Under ₹200 | I7: 0.85 | J7: =IF(I7<=0.3,"0-30%",IF(I7<=0.5,"31-50%",IF(I7<=0.7,"51-70%","71%+"))) -> 71%+ | K7: 3.9 | L7: 24871 | M7: =IF(L7<1000,"Low (<1k)",IF(L7<=10000,"Medium (1k-10k)","High (10k+)")) -> High (10k+) | N7: Fast Charging & Data Sync: Solero TB301 Type-C cable supports fast charge up to 5V/3A for devices and data syncing speed up to 480Mbps.|Universal Compatibility: This USB charging cable connects USB Type-C devices with standard USB devices like laptops, hard drives, power banks, wall and car chargers, etc..Connector One: Reversible Type C|Connector Two: USB A Type|Rough & Tough Type-C Cable: Charging cable with a double-braided exterior, premium aramid fiber core and metal plugs. It has passed 10,000 bending tests and can easily withstand daily use.|Extended Length: 1.5-meter long c-type cable uses nylon material to protect the wire and avoid knots.|Perfect Fit Connectors: pTron Soler USB-C has passed the 5KG load test, swing test, 5000+ times connect & disconnect to ensure that there are no loose connections. | O7: AEQ2YMXSZWEOHK2EHTNLOS56YTZQ,AGRVINWECNY7323CWFXZYYIZOFTQ,AHBAT6VLOXWGYDL57KHCNCLPXAKA,AF7NDY2H6JVYTSQOZP76GCATQ34Q,AFV7ZA733ZLME4KNLZPMPCBUNPPA,AHFAAPSY2MJ5HYOU2VQDJ7AQY4NQ,AH2WGV2PEBUTICRPBEEVKF24G5LA,AEP4MK3EKOBDKTGPJTRN5RBDIODA | P7: Jayesh,Rajesh k.,Soopy,amazon customer,Aman,Shankar,dinesh,Chitra,Ajaybabu.O.M | Q7: R7S8ANNSDPR40,R3CLZFLHVJU26P,RFF7U7MPQFUGR,R1MV1NKC23DWPI,R11D3U0V2XKDKF,R18MP1KLUE18PC,RWGJNVEH5ZQME,R1XN72FU6Q37IH | R7: It's pretty good,Average quality,very good and useful usb cable,Good USB cable. My experience was very good it is long lasting,Good,Nice product and useful,-,Sturdy but does not support 33w charging | S7: It's a good product.,Like,Very good item strong and useful USB cableValue for moneyThanks to amazon and producer,https://m.media-amazon.com/images/I/51112ZRE-1L._SY88.jpg,Good,Nice product and useful product,-,Sturdy but does not support 33w charging | T7: https://m.media-amazon.com/images/I/31wOPjcSxlL._SX300_SY300_QL70_FMwebp_.jpg | U7: https://www.amazon.in/Solero-TB301-Charging-480Mbps-1-5-Meter/dp/B08Y1TFSP6/ref=sr_1_6?qid=1672909124&s=electronics&sr=1-6
A8: B08WRWPM22 | B8: boAt Micro USB 55 Tangle-free, Sturdy Micro USB Cable with 3A Fast Charging & 480mbps Data Transmission (Black) | C8: Computers&Accessories|Accessories&Peripherals|Cables&Accessories|Cables|USBCables | D8: =LEFT(C8, FIND("|",C8)-1) -> Computers&Accessories | E8: =IF(COUNTIF($D$2:$D$1466,$D8)<10,"Small Sample (<10)",IF(COUNTIF($D$2:$D$1466,$D8)<50,"Caution (10-50)","Reliable (50+)")) -> Reliable (50+) | F8: 176.63 | G8: 499 | H8: =IF(F8<=200,"Under ₹200",IF(F8<=500,"₹200-500",IF(F8<=1500,"₹500-1500","₹1500+"))) -> Under ₹200 | I8: 0.65 | J8: =IF(I8<=0.3,"0-30%",IF(I8<=0.5,"31-50%",IF(I8<=0.7,"51-70%","71%+"))) -> 51-70% | K8: 4.1 | L8: 15188 | M8: =IF(L8<1000,"Low (<1k)",IF(L8<=10000,"Medium (1k-10k)","High (10k+)")) -> High (10k+) | N8: It Ensures High Speed Transmission And Charging By Offering 3A Fast Charging And Data Transmissions With Rapid Sync At 480 Mbps|The Braided Skin Makes It Durable And Invincible Against External Damage So You Can Have An Absolute Hassle-Free & Tangle Free Experience|Its Durable Pvc Housing And The Flexible Design Makes It Last 6 Times Longer Than Other Cables|Usb Cable Offers A Perfect 1.5 Meters In Length For Smooth & Hassle-Free User Experience For Superior Charging & Data Transfer Tasks|The Compact And Smooth Aluminium Connector Fits Most Cases Seamlessly And Resists Corrosion For Signal Purity|Micro Usb 55 Cable Offers Universal Compatibility As It Is Compatible With Most Android Smartphones, Tablets, Pc Peripherals, Bluetooth Speakers, Power Banks, Game Consoles & All Micro-Usb Enabled Devices|2 years warranty from the date of purchase | O8: AG7C6DAADCTRQJG2BRS3RIKDT52Q,AFU7BOMPVJ7Q3TTA4G67RASTGYIQ,AER5ZGIXXVYG3AWZTRZT7M2BYCEA,AHE76XQSOLGOP5ZEKTIW6KUPDWBQ,AGXTMB2XHZBEWZ2UIX7ODZ4XTU6Q,AHNM2XVU745EDPNGUOAG74PTSNRA,AH5RWQ4S72IVLZD6O75OPCFIVDXQ,AG322TYKVPLPBDXE7ABEUK5QTALQ | P8: Vivek kumar,Amazon Customer,SARTHAK,Chiranjeevi,V V GIRI KUMAR,Rajnandini,Akshay Talla,sudhanshu chaubey | Q8: R8E73K2KWJRDS,RSD0JTIIWQQL8,R64CRSTE9SLW1,R2FRTNIIUFJE1F,RWGNX3W7UOJ7W,R32TYHHODHTF5D,RQL9ZMQUTY7P2,R280XJ5VZUBOXV | R8: Long durable.,good,Does not charge Lenovo m8 tab,Best charging cable,good,Boat,Product was good,1.5 m à¤•à¤¾ à¤•à¥‡à¤¬à¤² à¤®à¥‡à¤°à¥‡ à¤²à¤¿à¤ à¤¬à¤¹à¥à¤¤ à¤¹à¥€ à¤²à¤¾à¤­à¤¦à¤¾à¤¯à¤• à¤¹à¥ˆ à¥¤ | S8: Build quality is good and it is comes with 2 year warranty.,Good Product,Bought it for charging my mobile & tab but it doesn't work for Lenovo m8 tab,Guys this cable is is best compare of everyone over heat protection, quickly charging, but chance to shock circuit,good,Nice,Good quality,1.5à¤à¤® à¤•à¤¾ à¤¡à¤¾à¤Ÿà¤¾ à¤•à¥‡à¤¬à¤² à¤®à¥‡à¤°à¥‡ à¤²à¤¿à¤ à¤¬à¤¹à¥à¤¤ à¤¹à¥€ à¤²à¤¾à¤­à¤¦à¤¾à¤¯à¤• à¤¹à¥ˆ à¥¤ à¤®à¥ˆà¤‚ à¤‡à¤¸ à¤•à¥‡à¤¬à¤² à¤•à¥‹ à¤²à¤¾à¤‡à¤¨ à¤®à¥‡à¤‚ à¤šà¤¾à¤°à¥à¤œ à¤•à¤°à¤¤à¥‡ à¤¸à¤®à¤¯ à¤«à¥‹à¤¨ à¤¬à¤¹à¥à¤¤ à¤†à¤°à¤¾à¤® à¤¸à¥‡ à¤‰à¤ªà¤¯à¥‹à¤— à¤•à¤° à¤ªà¤¾ à¤°à¤¹à¤¾ à¤¹à¥ à¥¤ à¤†à¤ª à¤‡à¤¸ à¤•à¥‡à¤¬à¤² à¤¸à¥‡ 15watt à¤•à¤¾ à¤šà¤¾à¤°à¥à¤œà¤° à¤‰à¤¸à¥‡ à¤•à¤° à¤¸à¤•à¤¤à¥‡ à¤¹à¥ˆ (à¤‡à¤¸à¤¸à¥‡ à¤œà¤¡à¤¼à¤¾ à¤¨à¤¹à¥€) à¥¤ à¤²à¥‹à¤•à¤² à¤¬à¤¾à¤œà¤¾à¤° à¤®à¥‡à¤‚ à¤‡à¤¸à¤•à¤¾ à¤¦à¤¾à¤® 150 à¤¹à¥ˆ , à¤…à¤®à¥‡à¤œà¤¨ à¤ªà¥‡ à¤¯à¥‡ à¤•à¥‡à¤¬à¤² à¤®à¥à¤à¥‡ 67 à¤®à¥‡à¤‚ à¤®à¤¿à¤²à¤¾ à¥¤ à¤—à¤°à¥à¤µ à¤¸à¥‡ à¤•à¤¹à¥‹ à¤¹à¤® à¤¹à¤¿à¤‚à¤¦à¥‚ à¤¹à¥ˆ , à¤œà¤¯ à¤¹à¤¿à¤‚à¤¦ à¤œà¤¯ à¤­à¤¾à¤°à¤¤ , | T8: https://m.media-amazon.com/images/W/WEBP_402378-T2/images/I/41jlwEZpa5L._SX300_SY300_QL70_FMwebp_.jpg | U8: https://www.amazon.in/boAt-Micro-USB-Tangle-Free-Transmission/dp/B08WRWPM22/ref=sr_1_8?qid=1672909124&s=electronics&sr=1-8
